Workbook

Sheet 题库数据
A4: 题号 | B4: 题目 | C4: 选项A | D4: 选项B | E4: 选项C | F4: 选项D | G4: 选项E | H4: 选项F | I4: 你的选择 | J4: 正确答案_数据 | K4: 解析_数据 | L4: 是否正确 | M4: 正确选项 | N4: 解析显示
A5: 1 | B5: 一家公司有一个托管在 AWS 上的网站该网站位于应用程序负载均衡器(ALB)的后面,该应用程序负载均衡器(ALB)配置为分别处理 HTTP 和 HTTPS.该公司希望将所有请求转发到该网站,以便这些请求将使用 HTTPS.什么解决方案架构师应该做些什么来满足这个要求? | C5: 更新 ALB 的网络 ACL 以仅接受 HTTPS 流量 | D5: 创建一个规则,将 URL 中的 HTTP 替换为 HTTPS. | E5: 在 ALB 上创建一个监听器规则,将 HTTP 流量重定向到 HTTPS. | F5: 将 ALB 替换为配置为使用服务器名称指示(SNI)的网络负载均衡器. | I5: C | J5: C | K5: Cant be implemented on Lambda because the timeout for Lambda is 15mins and the Job takes 60minutes to complete | L5: ✅正确 | M5: C - 在 ALB 上创建一个监听器规则，将 HTTP 流量重定向到 HTTPS | N5: Cant be implemented on Lambda because the timeout for Lambda is 15mins and the Job takes 60minutes to complete
A6: 2 | B6: 一家公司正在 AWS 上开发一个两层 Web 应用程序,该公司的开发人员已将该应用程序部署在直接连接到后端 Amazon RDS 数据库的 Amazon EC2 实例上.该公司不得在应用程序中硬编码数据库凭证.该公司还必须实施定期自动轮换数据库凭据的解决方案.哪种解决方案能够以最少的运营开销满足这些要求? | C6: 将数据库凭证存储在实例元数据中.使用 Amazon EventBridge (Amazon CloudWatch Events)规则运行计划的 AWS Lambda 函数,该函数同时更新 RDS 凭证和实例元数据. | D6: 将数据库凭证存储在加密 Amazon S3 存储桶中的配置文件中.使用 Amazon EventBridge (Amazon CloudWatch Events)规则运行计划的 AWS Lambda 函数,该函数同时更新 RDS 凭证和配置文件中的凭证.使用 S3 版本控制确保能够回退到以前的值. | E6: 将数据库凭证作为秘密存储在 AWS Secrets Manager 中.打开秘密的自动轮换.将所需的权限附加到EC2 角色以授予对秘密的访问权限. | F6: 将数据库凭证作为加密参数存储在 AWS Systems Manager Parameter Store 中.为加密参数启用自动轮换.将所需权限附加到 EC2 角色以授予对加密参数的访问权限. | J6: C | K6: AWS Secrets Manager 是比 SSM Parameter store 更新的服务. https://docs.aws.amazon.com/secretsmanager/latest/userguide/create_database_secret.html | N6: AWS Secrets Manager 是比 SSM Parameter store 更新的服务. https://docs.aws.amazon.com/secretsmanager/latest/userguide/create_database_secret.html
A7: 3 | B7: 一家公司正在向 AWS 部署一个新的公共 Web 应用程序.该应用程序将在 Application Load Balancer (ALB)之后运行,该应用程序需要在边缘使用由外部证书颁发机构颁发的 SSL/TLS 证书进行加密(CA).证书必须在证书到期之前每年轮换.解决方案架构师应该做什么来满足这些要求? | C7: 使用 AWS Certificate Manager (ACM) 颁发 SSL/TLS 证书.将证书应用到 ALB.使用托管续订功能自动轮换证书. | D7: 使用 AWS Certificate Manager (ACM)颁发 SSL/TLS 证书.从证书中导入密钥材料.将证书应用到 ALB.使用托管续订功能自动轮换证书. | E7: 使用 AWS Certificate Manager (ACM) 私有证书颁发机构从根 CA 颁发 SSL/TLS 证书.将证书应用到 ALB.使用托管续订功能自动轮换证书. | F7: 使用 AWS Certificate Manager (ACM) 导入 SSL/TLS 证书.将证书应用到 ALB.使用 Amazon EventBridge (Amazon CloudWatch Events)在证书即将到期时发送通知.手动轮换证书. | J7: D | K7: It's a third-party certificate, hence AWS cannot manage renewal automatically. The closest thing you can do is to send a notification to renew the 3rd party certificate. | N7: It's a third-party certificate, hence AWS cannot manage renewal automatically. The closest thing you can do is to send a notification to renew the 3rd party certificate.
A8: 4 | B8: 一家公司在 AWS 上运行其基础设施,并拥有700.000 名注册用户,用于 res 文档管理应用程序,该公司打算创建一个将大型 pdf 文件转换为 jpg Imago 文件的产品 .. pdf 文件的平均大小为5 MB.公司需要存储原始文件和转换后的文件,解决方案架构师必须设计一个可扩展的解决方案,以适应随着时间的推移而迅速增长的需求.哪种解决方案最经济高效地满足这些要求? | C8: 将 pdf 文件保存到 Amazon S3.配置 S3 PUT 事件以调用 AWS Lambda 函数将文件转换为 jpg 格式并将它们存储回 Amazon S3. | D8: 将 pdf 文件保存到 Amazon DynamoDB.使用 DynamoDB Streams 功能调用 AWS Lambda 函数将文件转换为 jpg 格式并将它们存储在 DynamoDB 中. | E8: 将 .pdf 文件上传到包含 Amazon EC2 实例的 AWS Elastic Beanstalk 应用程序.Amazon Elastic Block Store (Amazon EBS) 存储和 Auto Scaling 组.在 EC2 实例中使用程序将文件转换为 jpg 格式保存.EBS 商店中的 pdf 文件和 .jpg 文件. | F8: 将 .pdf 文件上传到包含 Amazon EC2 实例.Amazon Elastic File System (Amazon EFS) 存储和 Auto Scaling 组的 AWS Elastic Beanstalk 应用程序.使用 EC2 实例中的程序将文件转换为 jpg 格式保存EBS 商店中的 pdf 文件和 jpg 文件. | J8: A | K8: This solution will meet the company's requirements in a cost-effective manner because it uses a serverless architecture with AWS Lambda to convert the files and store them in S3. The Lambda function will automatically scale to meet the demand for file conversions and S3 will automatically scale to store the original and converted files as needed.该解决方案将以经济高效的方式满足公司的要求,因为它使用了带有AWS Lambda的无服务器架构来转换文件并将其存储在S3中。Lambda功能将自动缩放以满足文件转换的需求,S3将根据需要自动缩放以存储原始文件和转换后的文件。 | N8: This solution will meet the company's requirements in a cost-effective manner because it uses a serverless architecture with AWS Lambda to convert the files and store them in S3. The Lambda function will automatically scale to meet the demand for file conversions and S3 will automatically scale to store the original and converted files as needed.该解决方案将以经济高效的方式满足公司的要求,因为它使用了带有AWS Lambda的无服务器架构来转换文件并将其存储在S3中。Lambda功能将自动缩放以满足文件转换的需求,S3将根据需要自动缩放以存储原始文件和转换后的文件。
A9: 5 | B9: 一家公司在本地运行的 Windows 文件服务器上拥有超过5 TB 的文件数据用户和应用程序每天与数据进行交互该公司正在将其 Windows 工作负载转移到 AWS.随着公司继续这一过程,该公司需要访问以最小的延迟连接到AWS 和本地文件存储.公司需要一种解决方案,最大限度地减少运营开销,并且不需要对现有文件访问模式进行重大更改.公司使用 AWS Site-to-Site VPN 连接来连接到 AWS.解决方案架构师应该怎么做才能满足这些要求? | C9: 在 AWS 上部署和配置 Amazon FSx for Windows File Server.将本地文件数据移动到 FSx for Windows File Server.重新配置工作负载以在 AWS 上使用 FSx for Windows File Server. | D9: 在本地部署和配置 Amazon S3 文件网关.将本地文件数据移动到 S3 文件网关,重新配置本地工作负载和云工作负载以使用 S3 文件网关 | E9: 在本地部署和配置 Amazon S3 文件网关.将本地文件数据移动到 Amazon S3.重新配置工作负载以直接使用 Amazon S3 或 S3 文件网关,具体取决于每个工作负载的位置. | F9: 在 AWS 上部署和配置 Amazon FSx for Windows File Server.在本地部署和配置 Amazon FSx 文件网关.将本地文件数据移动到 FSx 文件网关.配置云工作负载以使用 FSx for Windows File Server AWS.配置本地工作负载以使用 FSx 文件网关. | J9: D
A10: 6 | B10: 一家医院最近使用Amazon API Gateway 和AWS Lambda 部署了一个RESTful API.该医院使用API Gateway 和Lambda 上传PDF 格式和JPEG 格式的报告.医院需要修改Lambda 代码以识别受保护的健康信息(PHI)在报告中.哪种解决方案将以最少的运营开销满足这些要求? | C10: 使用现有的 Python 库从报告中提取文本并从提取的文本中识别 PHI. | D10: 使用 Amazon Textract 从报告中提取文本.使用 Amazon SageMaker 从提取的文本中识别 PHI. | E10: 使用 Amazon Textract 从报告中提取文本.使用 Amazon Comprehend Medical 从提取的文本中识别 PHI. | F10: 使用 Amazon Rekognition 从报告中提取文本.使用 Amazon Comprehend Medical 从提取的文本中识别 PHI. | J10: C | K10: Textract and Comprehend 符合 HIPPA.https://aws.amazon.com/blogs/machine-learning/amazon-textract-is-now-hipaaeligible/ | N10: Textract and Comprehend 符合 HIPPA.https://aws.amazon.com/blogs/machine-learning/amazon-textract-is-now-hipaaeligible/
A11: 7 | B11: 一家公司有一个应用程序生成大量文件,每个文件大小约为5 MB.这些文件存储在 Amazon S3 中.公司政策要求文件存储 4年才能删除始终可立即访问需要,因为文件包含不易复制的关键业务数据.文件在对象创建的前30天内经常访问,但在前30天后很少访问哪种存储解决方案最具成本效益? | C11: 创建一个S3存储桶生命周期策略,在创建对象后30天内将文件从S3 Standard移动到S3 Glacier。在创建对象4年后删除文件 | D11: 创建一个S3存储桶生命周期策略,在创建对象后30天内将文件从S3 Standard移动到S3 One Zone Un频繁访问(S3 One Zone IA)。在创建对象4年后删除文件 | E11: 创建一个S3存储桶生命周期策略,在创建对象后30天内将文件从S3 Standard移动到S3 Standard Infrequent Access (S3 Standard IA)。在创建对象4年后删除文件。 | F11: 创建 S3 存储桶生命周期策略,在对象创建后 30 天将文件从S3 标准移动到 S3 标准-不频繁访问(S3 标准-IA).在对象装箱 4年后将文件移动到 S3 Glacier. | J11: C | K11: 始终需要立即访问,因为文件包含关键业务数据 | N11: 始终需要立即访问,因为文件包含关键业务数据
A12: 8 | B12: 一家公司在多个 Amazon EC2 实例上托管应用程序,应用程序处理来自 Amazon SQS 队列的消息写入 Amazon RDS 表并从队列中删除消息在 RDS 表中偶尔发现重复记录.SQS 队列没有包含任何重复的消息.解决方案架构师应该怎么做才能确保消息只被处理一次? | C12: 使用 CreateQueue API 调用创建新队列 | D12: 使用 Add Permission API 调用添加适当的权限 | E12: 使用 ReceiveMessage API 调用设置适当的等待时间 | F12: 使用 ChangeMessageVisibility APi 调用来增加可见性超时 | J12: D | K12: 可见性超时在 Amazon SQS 返回消息时开始.在此期间,消费者会处理并删除消息.但是,如果消费者在删除消息之前失败,并且您的系统在可见性超时到期,该消息对其他消费者可见,并再次收到该消息.如果一条消息必须只接收一次,您的消费者应在可见性超时期限内将其删除.https://docs.aws.amazon.com/AWSSimpleQueueService/latest/SQSDeveloperGuide/sqs-visibilitytimeout.html 关键字:SQS 队列写入 Amazon RDS 由此,选项 D 最佳套件 &其他选项排除[选项A-您不能在现有队列中再插入一个队列;选项 B-only Permission & Option C-Only Retrieves Messages] FIF O 队列旨在从不引入重复消息.但是,您的消息生产者可能会在某些情况下引入重复消息:例如,如果生产者发送消息,没有收到响应,然后重新发送消息相同的消息.Amazon SQS API 提供重复数据删除功能,可防止您的消息生产者发送重复数据.消息生产者引入的任何重复数据都会在5分钟的重复数据删除间隔内删除.对于标准队列,您可能偶尔会收到消息的重复副本(至少一次传递).如果使用标准队列,则必须将应用程序设计为幂等的(即,在多次处理同一消息时,它们不得受到不利影响). | N12: 可见性超时在 Amazon SQS 返回消息时开始.在此期间,消费者会处理并删除消息.但是,如果消费者在删除消息之前失败,并且您的系统在可见性超时到期,该消息对其他消费者可见,并再次收到该消息.如果一条消息必须只接收一次,您的消费者应在可见性超时期限内将其删除.https://docs.aws.amazon.com/AWSSimpleQueueService/latest/SQSDeveloperGuide/sqs-visibilitytimeout.html 关键字:SQS 队列写入 Amazon RDS 由此,选项 D 最佳套件 &其他选项排除[选项A-您不能在现有队列中再插入一个队列;选项 B-only Permission & Option C-Only Retrieves Messages] FIF O 队列旨在从不引入重复消息.但是,您的消息生产者可能会在某些情况下引入重复消息:例如,如果生产者发送消息,没有收到响应,然后重新发送消息相同的消息.Amazon SQS API 提供重复数据删除功能,可防止您的消息生产者发送重复数据.消息生产者引入的任何重复数据都会在5分钟的重复数据删除间隔内删除.对于标准队列,您可能偶尔会收到消息的重复副本(至少一次传递).如果使用标准队列,则必须将应用程序设计为幂等的(即,在多次处理同一消息时,它们不得受到不利影响).
A13: 9 | B13: 一位解决方案架构师正在设计一种新的混合架构,以将公司的本地基础设施扩展到 AWS.公司需要与 AWS区域保持一致的低延迟的高可用性连接.公司需要最大限度地降低成本并愿意接受如果主连接失败,则流量会变慢.解决方案架构师应该怎么做才能满足这些要求? | C13: 提供与区域的 AWS Direct Connect 连接.如果主要 Direct Connect 连接失败,提供 VPN 连接作为备份. | D13: 为专用连接提供到区域的 VPN隧道连接.为专用连接提供第二条 VPN 隧道,并在主 VPN 连接失败时作为备用. | E13: 提供与区域的 AWS Direct Connect 连接.如果主要 Direct Connect 连接失败,则提供与同一区域的第二个 Direct Connect 连接作为备份. | F13: 为区域提供 AWS Direct Connect 连接.如果主要 Direct Connect 连接失败,则使用 AWS CLI 中的 Direct Connect 故障转移属性自动创建备份连接. | J13: A | K13: “在某些情况下,仅此连接是不够的,保证备用连接作为DX的备份总是更好.有多种选择,但使用 AWS Site-To-Site VPN 实施它是一项真正的成本- 可用于降低成本的有效解决方案,或者同时等待第二个DX的设置."https://www.proud2becloud.com/hybridcloud-networking-backup-aws-direct-connect-network-connection-with-aws-site-to-site-vpn/ | N13: “在某些情况下,仅此连接是不够的,保证备用连接作为DX的备份总是更好.有多种选择,但使用 AWS Site-To-Site VPN 实施它是一项真正的成本- 可用于降低成本的有效解决方案,或者同时等待第二个DX的设置."https://www.proud2becloud.com/hybridcloud-networking-backup-aws-direct-connect-network-connection-with-aws-site-to-site-vpn/
A14: 10 | B14: 一家公司正在 Application Load Balancer 后面的 Amazon EC2 实例上运行关键业务 Web 应用程序.EC2 实例位于 Auto Scaling 组中.该应用程序使用部署在单个可用区中的 Amazon Aurora PostgreSQL 数据库.公司希望应用程序具有高可用性,停机时间最短,数据丢失最少.哪种解决方案能够以最少的运营工作满足这些要求? | C14: 将 EC2 实例放置在不同的 AWS 区域中.使用 Amazon Route 53 运行状況检查来重定向流量.使用 Aurora PostgreSQL 跨区域复制. | D14: 将 Auto Scaling 组配置为使用多个可用区.将数据库配置为多可用区,为数据库配置 Amazon RDS 代理实例. | E14: 将 Auto Scaling 组配置为使用一个可用区.生成数据库的每小时快照.在发生故障时从快照中恢复数据库. | F14: 将 Auto Scaling 组配置为使用多个 AWS 区域.将数据从应用程序写入 Amazon S3.使用 S3 事件通知启动 AWS Lambda 函数以将数据写入数据库. | J14: B | K14: 用于 Aurora 的 RDS 代理 https://docs.aws.amazon.com/AmazonRDS/latest/AuroraUserGuide/rds-proxy.html | N14: 用于 Aurora 的 RDS 代理 https://docs.aws.amazon.com/AmazonRDS/latest/AuroraUserGuide/rds-proxy.html
A15: 11 | B15: 公司的 HTTP 应用程序位于网络负载均衡器(NLB)的后面.NLB 的目标组配置为使用 Amazon EC2 Auto Scaling 组,该组具有多个运行 Web 服务的 EC2 实例.公司注意到 NLB 未检测到 HTTP应用程序的错误.这些错误需要手动重新启动运行 Web 服务的 EC2 实例.公司需要在不编写自定义脚本或代码的情况下提高应用程序的可用性.解决方案架构师应该如何满足这些要求? | C15: 在 NLB 上启用 HTTP 健康检查.提供公司应用程序的 URL. | D15: 向EC2实例添加一个cron作业,每分钟检查一次本地应用程序的日志,如果检测到HTTP错误,应用程序将重新启动. | E15: 将 NLB 替换为 Application Load Balancer.通过提供公司应用程序的 URL 来启用 HTTP 运行状况检查.配置 Auto Scaling 操作以替换运行状况不佳的实例. | F15: 创建监控 NLB 的 UnhealthyHostCount 指标的 Amazon Cloud Watch 警报.配置 Auto Scaling 操作以在警报处于 ALARM 状态时替换不健康的实例. | J15: C | K15: NLB 工作在第 4层,因此不支持 HTTP/HTTPS.替代 ALB 是最佳选择. | N15: NLB 工作在第 4层,因此不支持 HTTP/HTTPS.替代 ALB 是最佳选择.
A16: 12 | B16: 一家公司运行一个购物应用程序,该应用程序使用 Amazon DynamoDB 存储客户信息.在数据损坏的情况下,解决方案架构师需要设计一个满足15分钟恢复点目标(RPO)和恢复时间目标(RTO)的解决方案)1小时.解决方案架构师应该推荐什么来满足这些要求? | C16: 配置 DynamoDB 全局表.对于 RPO 恢复,将应用程序指向不同的 AWS 区域. | D16: 配置 DynamoDB 时间点恢复,对于 RPO恢复,恢复到所需的时间点. | E16: 每天将 DynamoDB 数据导出到 Amazon S3 Glacier.对于 RPO 恢复,将数据从 S3 Glacier 导入到 DynamoDB. | F16: 每 15 分钟为 DynamoDB 表安排 Amazon Elastic Block Store (Amazon EBS) 快照.对于 RPO 恢复,使用 EBS 快照还原 DynamoDB 表. | J16: B | K16: A - DynamoDB 全局表提供多区域和多活动数据库,但它在“数据损坏的情况下“无效.在这种情况下,您需要备份,此解决方案无效. B-Point in Time Recovery 被设计为连续备份,可以快速恢复,它完美地涵盖了RPO,可能还有 RTO. https://docs.aws.amazon.com/amazondynamodb/latest/developerguide/PointInTimeRecovery.html C - 每日导出不会涵盖 15分钟的RPO. D - DynamoDB 是无服务器的. | N16: A - DynamoDB 全局表提供多区域和多活动数据库,但它在“数据损坏的情况下“无效.在这种情况下,您需要备份,此解决方案无效. B-Point in Time Recovery 被设计为连续备份,可以快速恢复,它完美地涵盖了RPO,可能还有 RTO. https://docs.aws.amazon.com/amazondynamodb/latest/developerguide/PointInTimeRecovery.html C - 每日导出不会涵盖 15分钟的RPO. D - DynamoDB 是无服务器的.
A17: 13 | B17: 一家公司运行的照片处理应用程序需要经常从位于同一 AWS 区域的 Amazon S3 存储桶上传和下载图片,一位解决方案架构师注意到数据传输费用的成本增加,需要实施一种解决方案来减少这些成本.解决方案架构师如何满足这一要求? | C17: 将 Amazon API Gateway 部署到公有子网并调整路由表以通过它路由 S3 调用. | D17: 将 NAT 网关部署到公共子网中,并附加一个允许访问S3 存储桶的端点策略. | E17: 将应用程序部署到公共子网中,并允许其通过互联网网关路由以访问S3 存储桶 | F17: 将 S3 VPC 网关终端节点部署到VPC中,并附加一个终端节点策略以允许访问S3 存储桶. | J17: D | K17: 为了降低成本,去掉了NAT 网关,VPC 端点到 S3. | N17: 为了降低成本,去掉了NAT 网关,VPC 端点到 S3.
A18: 14 | B18: 一家公司最近在私有子网中的 Amazon EC2 上启动了基于 Linux 的应用程序实例,并在 VPC的公共子网中的 Amazon EC2 实例上启动了基于 Linux 的堡垒主机.解决方案架构师需要从本地连接网络,通过公司与堡垒主机和应用程序服务器的互联网连接.解决方案架构师必须确保所有 EC2 实例的安全组都允许该访问.解决方案架构师应采取哪些步骤组合来满足这些要求?(选择两个) | C18: 将堡垒主机的当前安全组替换为仅允许来自应用程序实例的入站访问的安全组 | D18: 将堡垒主机的当前安全组替换为只允许公司内部IP范围的入站访问的安全组 | E18: 将堡垒主机的当前安全组替换为只允许公司外部IP范围入站访问的安全组 | F18: 将应用程序实例的当前安全组替换为仅允许从堡垒主机的私有IP地址进行入站 SSH 访问的安全组 | G18: 将应用程序实例的当前安全组替换为仅允许从堡垒主机的公共IP 地址进行入站 SSH 访问的安全组 | J18: C,D | K18: 选项C(仅允许来自外部 IP的访问)和 D(允许来自堡垒主机的私有 IP的入站 SSH) . https://digitalcloud.training/sshinto-ec2-in-private-subnet/ | N18: 选项C(仅允许来自外部 IP的访问)和 D(允许来自堡垒主机的私有 IP的入站 SSH) . https://digitalcloud.training/sshinto-ec2-in-private-subnet/
A19: 15 | B19: 一位解决方案架构师正在设计一个两层 Web 应用程序.该应用程序由托管在公共子网中的 Amazon EC2 上的面向公众的 Web 层组成.数据库层由在私有子网中的 Amazon EC2 上运行的 Microsoft SQL Server 组成.公司的高优先级.在这种情况下应该如何配置安全组? (选择两个) | C19: 将 Web 层的安全组配置为允许来自 0.0.0.0/0 的端口 443 上的入站流量. | D19: 将 Web 层的安全组配置为允许来自 0.0.0.0/0 的端口 443 上的出站流量. | E19: 配置数据库层的安全组以允许来自 Web 层安全组的端口 1433 上的入站流量. | F19: 配置数据库层的安全组以允许端口 443 和 1433 上的出站流量到 Web 层的安全组. | G19: 配置数据库层的安全组以允许来自 Web 层安全组的端口 443 和 1433 上的入站流量. | J19: A,C | K19: 公共子网上的 EC2 Web+私有子网上的EC2 SQL+安全性是高优先级.因此,选项A 允许来自任何地方的 HTTPS.加上选项C 以允许来自 Web 实例的 SQL 连接, | N19: 公共子网上的 EC2 Web+私有子网上的EC2 SQL+安全性是高优先级.因此,选项A 允许来自任何地方的 HTTPS.加上选项C 以允许来自 Web 实例的 SQL 连接,
A20: 16 | B20: 一家公司希望将多层应用程序从本地迁移到 AWS 云以提高应用程序的性能.该应用程序由通过 RESTful 服务相互通信的应用程序层组成.当一层过载时,事务将被丢弃.解决方案架构师必须设计一个解决方案来解决这些问题并使应用程序现代化.哪个解决方案满足这些要求并且最有效地运行? | C20: 使用 Amazon API Gateway 并将事务定向到 AWS Lambda 函数作为应用程序层.使用 Amazon Simple Queue Service (Amazon SQS)作为应用程序服务之间的通信层. | D20: 使用 Amazon CloudWatch 指标分析应用程序性能历史,以确定服务器在性能故障期间的峰值利用率.增加应用程序服务器的Amazon EC2 实例的大小以满足峰值要求. | E20: 使用 Amazon Simple Notification Service (Amazon SNS)处理 Auto Scaling 组中 Amazon EC2 上运行的应用程序服务器之间的消息传递.使用 Amazon CloudWatch 监控 SNS 队列长度并根据需要进行扩展和缩减. | F20: 使用 Amazon Simple Queue Service (Amazon SQS)处理 Auto Scaling 组中 Amazon EC2 上运行的应用程序服务器之间的消息传递.使用 Amazon CloudWatch 监控 SQS 队列长度并在检测到通信故障时向上扩展. | J20: A | K20: https://aws.amazon.com/getting-started/hands-on/build-serverless-web-app-lambda-apigateway-s3-dynamodbcognito/module-4/ | N20: https://aws.amazon.com/getting-started/hands-on/build-serverless-web-app-lambda-apigateway-s3-dynamodbcognito/module-4/
A21: 17 | B21: 一家公司每天从位于一家工厂的多台机器接收 10 TB 的仪器数据.这些数据由存储在工厂内部数据中心的存储区域网络(SAN)上的 JSON 文件组成.公司想要将此数据发送到 Amazon S3,在那里可以由几个提供关键近乎实时分析的附加系统访问它.安全传输很重要, 因为数据被认为是敏感的.哪种解决方案提供最可靠的数据传输? | C21: AWS DataSync 通过公共互联网 | D21: AWS DataSync 通过 AWS Direct Connect | E21: AWS Database Migration Service (AWS DMS) 通过公共互联网 | F21: AWS 数据库迁移服务(AWS DMS)通过 AWS Direct Connect | J21: B | K21: DMS 用于数据库,这里指的是“JSON文件”.公共互联网不可靠.所以最好的选择是 B.这些是 AWS DataSync 的一些主要用例 :数据迁移-通过网络将活动数据集快速移动到适用于 Windows File Server 的 Amazon S3.Amazon EFS 或 FSx.DataSync 包括自动加密和数据完整性验证以帮助确保您的数据安全.完整地到达并准备好使用.DataSync 包括加密和完整性验证,以帮助确保您的数据安全.完整地到达并准备好使用.https://aws.amazon.com/数据同步/常见问题/ | N21: DMS 用于数据库,这里指的是“JSON文件”.公共互联网不可靠.所以最好的选择是 B.这些是 AWS DataSync 的一些主要用例 :数据迁移-通过网络将活动数据集快速移动到适用于 Windows File Server 的 Amazon S3.Amazon EFS 或 FSx.DataSync 包括自动加密和数据完整性验证以帮助确保您的数据安全.完整地到达并准备好使用.DataSync 包括加密和完整性验证,以帮助确保您的数据安全.完整地到达并准备好使用.https://aws.amazon.com/数据同步/常见问题/
A22: 18 | B22: 一家公司需要为其应用程序配置实时数据摄取架构.该公司需要一个 API.一个在数据流式传输时转换数据的流程,以及一个数据存储解决方案.哪种解决方案将满足这些要求最少的运营开销? | C22: 部署 Amazon EC2 实例以托管将数据发送到 Amazon Kinesis 数据流的 API.创建使用 Kinesis 数据流作为数据源的 Amazon Kinesis Data Firehose 传输流.使用 AWS Lambda 函数转换数据.使用Kinesis Data Firehose 传输流将数据发送到 Amazon S3. | D22: 部署 Amazon EC2 实例以托管将数据发送到 AWS Glue 的 API.停止对 EC2 实例的源/目标检查.使用 AWS Glue 转换数据并将数据发送到 Amazon S3. | E22: 配置 Amazon API Gateway API 以将数据发送到 Amazon Kinesis 数据流.创建使用 Kinesis 数据流作为数据源的 Amazon Kinesis Data Firehose 传输流.使用 AWS Lambda 函数转换数据.使用 Kinesis Data Firehose 传输流将数据发送到 Amazon S3. | F22: 配置 Amazon API Gateway API 以将数据发送到 AWS Glue.使用 AWS Lambda 函数转换数据.使用 AWS Glue 将数据发送到 Amazon S3. | J22: C | K22: (A) - 您不需要部署 EC2 实例来托管 API - 操作开销. (B)- 与 A 相同. ( ** C*) - 就是答案. (D)- AWS Glue 从 S3 而非 API GW 获取数据. AWS Glue 可以自己做 ETL,所以不需要 lambda.无意义. https://aws.amazon.com/glue/. | N22: (A) - 您不需要部署 EC2 实例来托管 API - 操作开销. (B)- 与 A 相同. ( ** C*) - 就是答案. (D)- AWS Glue 从 S3 而非 API GW 获取数据. AWS Glue 可以自己做 ETL,所以不需要 lambda.无意义. https://aws.amazon.com/glue/.
A23: 19 | B23: 一家公司需要将用户交易数据保存在 Amazon DynamoDB 表中.该公司必须将数据保留 7年.满足这些要求的运营效率最高的解决方案是什么? | C23: 使用 DynamoDB 时间点恢复持续备份表. | D23: 使用 AWS Backup 为表创建备份计划和保留策略. | E23: 使用 DynamoDB 控制台创建表的按需备份.将备份存储在 Amazon S3 存储桶中.为 S3 存储桶设置 S3 生命周期配置. | F23: 创建 Amazon EventBridge (Amazon CloudWatch Events)规则以调用 AWS Lambda 函数.配置 Lambda 函数以备份表并将备份存储在 Amazon S3 存储桶中.为 S3 存储桶设置 S3 生命周期配置 | J23: B | K23: Amazon DynamoDB 提供两种类型的备份:时间点恢复(PITR)和按需备份. ( ==>D 不是答案) PITR 用于将您的表恢复到滚动的35天窗口中的任何时间点,用于帮助客户减少因错误代码.恶意访问或用户错误而对其表的意外删除或写入.( ==>A不是答案) 按需备份专为长期归档和保留而设计,通常用于帮助客户满足合规性和法规要求. 这是关于使用 AWS Backup 为 Amazon DynamoDB 设置计划按需备份的两篇博文系列中的第二篇.第1部分介绍了从AWS 管理控制台为 DynamoDB 表设置计划备份的步骤.( ==>不是 DynamoBD 控制台,C 也不是答案) https://aws.amazon.com/blogs/database/part-2-set-up-scheduled-backups-for-amazondynamodb-using-aws-backup/ | N23: Amazon DynamoDB 提供两种类型的备份:时间点恢复(PITR)和按需备份. ( ==>D 不是答案) PITR 用于将您的表恢复到滚动的35天窗口中的任何时间点,用于帮助客户减少因错误代码.恶意访问或用户错误而对其表的意外删除或写入.( ==>A不是答案) 按需备份专为长期归档和保留而设计,通常用于帮助客户满足合规性和法规要求. 这是关于使用 AWS Backup 为 Amazon DynamoDB 设置计划按需备份的两篇博文系列中的第二篇.第1部分介绍了从AWS 管理控制台为 DynamoDB 表设置计划备份的步骤.( ==>不是 DynamoBD 控制台,C 也不是答案) https://aws.amazon.com/blogs/database/part-2-set-up-scheduled-backups-for-amazondynamodb-using-aws-backup/
A24: 20 | B24: 某公司正计划使用 Amazon DynamoDB 表进行数据存储.该公司关注成本优化.大多数早上不会使用该表.在晚上,读写流量往往无法预测.当流量尖峰出现,它们会很快发生.解决方案架构师应该推荐什么? | C24: 在按需容量模式下创建DynamoDB表. | D24: 创建具有全局二级索引的 DynamoDB 表. | E24: 创建具有预置容量和 Auto Scaling 的 DynamoDB 表. | F24: 以预置容量模式创建DynamoDB表,并将其配置为全局表. | J24: A | K24: ** A ** - 按需提供答案 https://docs.aws.amazon.com/amazondynamodb/latest/developerguide/HowItWorks.ReadWriteCapacityMode.html#HowItWorks.OnDemand B - 与不可预测的流量无关. C- 推荐用于已知模式的预置容量.不是这里的情况. D- 与C 相同 | N24: ** A ** - 按需提供答案 https://docs.aws.amazon.com/amazondynamodb/latest/developerguide/HowItWorks.ReadWriteCapacityMode.html#HowItWorks.OnDemand B - 与不可预测的流量无关. C- 推荐用于已知模式的预置容量.不是这里的情况. D- 与C 相同
A25: 21 | B25: 一家公司最近与AWS托管服务提供商(MSP)合作伙伴签署了一份合同,以帮助实施应用程序迁移计划。解决方案架构师需要与 MSP合作伙伴的AWS帐户共享现有AWS帐户中的Amazon Machine Image (AMI)。AMI由Amazon Elastic Block Store (Amazon EBS)支持,并使用AWS密钥管理服务(AWS KMS)客户管理的密钥来加密EBS卷快照。解决方案架构师与MSP合作伙伴的AWS帐户共享AMI的最安全方式是什么? | C25: 公开加密的AMI和快照。修改密钥策略以允许MSP合作伙伴的AWS帐户使用密钥。 | D25: 修改AMI的launchPermission属性。仅与MSP合作伙伴的AWS帐户共享AMI。修改密钥策略以允许MSP合作伙伴的AWS帐户使用密钥。 | E25: 修改AMI的launchPermission属性。仅与MSP合作伙伴的AWS帐户共享AMI。修改密钥策略以信任MSP合作伙伴拥有的用于加密的新KMS密钥。 | F25: 将AMI从源帐户导出到MSP合作伙伴AWS帐户中的Amazon S3存储桶,使用MSP合作合作伙伴拥有的新KMS密钥加密S3存储桶。在MSP合作伙伴的AWS帐户中复制并启动AMI。 | J25: B
A26: 22 | B26: 一位解决方案架构师正在为部署在 AWS 上的新应用程序设计云架构.该过程应并行运行,同时根据要处理的作业数量根据需要添加和删除应用程序节点处理器应用程序是无状态的解决方案架构师必须确保应用程序是松散耦合的,并且工作项是持久存储的.解决方案架构师应该使用哪种设计? | C26: 创建 Amazon SNS 主题以发送需要处理的作业.创建包含处理器应用程序的 Amazon 系统映像(AMI).创建使用 AMI 的启动配置.使用启动配置创建 Auto Scaling 组.为 Auto Scaling 组设置伸缩策略,根据 CPU 使用率添加和删除节点. | D26: 创建 Amazon SQS 队列以保存需要处理的作业.创建包含处理器应用程序的 Amazon 机器映像(AMI).创建使用 AMI 的启动配置.使用启动配置创建 Auto Scaling 组.设置Auto Scaling组的伸缩策略,根据网络使用情况添加和删除节点, | E26: 创建 Amazon SQS 队列以保存需要处理的作业.创建包含处理器应用程序的 Amazon 机器映像(AMI).创建使用 AMI 的启动模板.使用启动模板创建 Auto Scaling 组.设置Auto Scaling 组的伸缩策略,根据SQS 队列中的项目数添加和删除节点. | F26: 创建 Amazon SNS 主题以发送需要处理的作业.创建包含处理器应用程序的 Amazon 系统映像(AMI).创建使用 AMI 的启动模板.使用启动模板创建 Auto Scaling 组.为Auto Scaling组设置伸缩策略,根据发布到SNS主题的消息数量添加和删除节点 | J26: C | K26: 创建一个 Amazon SQS 队列来保存需要处理的作业.为计算应用程序创建一个 Amazon EC2 Auto Scaling 组.为 Auto Scaling 组设置扩展策略以根据项目数量添加和删除节点在SQS 队列中.在这种情况下,我们需要找到一个持久且松散耦合的解决方案来存储作业.Amazon SQS 非常适合这种用例,并且可以配置为根据队列中等待的作业数量使用动态扩展.配置此缩放,您可以使用每个实例的积压指标,目标值是每个实例可接受的积压来维护,您可以按如下方式计算这些数字:每个实例的积压:要计算每个实例的积压,从 ApproximateNumberOfMessages 队列属性开始确定 SQS 队列的长度. | N26: 创建一个 Amazon SQS 队列来保存需要处理的作业.为计算应用程序创建一个 Amazon EC2 Auto Scaling 组.为 Auto Scaling 组设置扩展策略以根据项目数量添加和删除节点在SQS 队列中.在这种情况下,我们需要找到一个持久且松散耦合的解决方案来存储作业.Amazon SQS 非常适合这种用例,并且可以配置为根据队列中等待的作业数量使用动态扩展.配置此缩放,您可以使用每个实例的积压指标,目标值是每个实例可接受的积压来维护,您可以按如下方式计算这些数字:每个实例的积压:要计算每个实例的积压,从 ApproximateNumberOfMessages 队列属性开始确定 SQS 队列的长度.
A27: 23 | B27: 一家公司在 AWS 云中托管其 Web 应用程序.该公司将 Elastic Load Balancer 配置为使用导入 AWS Certificate Manager (ACM) 的证书.必须在每个证书到期前30天通知公司的安全团队.什么解决方案架构师应该推荐满足要求吗? | C27: 添加规则 ACM 以在任何证书到期前 30 天开始每天向 Amazon Simple Notification Service (Amazon SNS)主题发布自定义消息. | D27: 创建一个 AWS Config 规则来检查将在 30 天内过期的证书.配置 Amazon EventBridge (Amazon CloudWatch Events)以在 AWS Config 报告不合规资源时通过 Amazon Simple Notification Service (Amazon SNS)调用自定义警报 | E27: 使用 AWS Trusted Advisor 检查将在几天内过期的证书.创建基于 Trusted Advisor 指标的 Amazon CloudWatch 警报以检查状态更改.配置警报以通过 Amazon Simple rectification Service (亚马逊社交网络) | F27: 创建 Amazon EventBridge (Amazon CloudWatch Events)规则以检测任何将在30 天内过期的证书.配置规则以调用 AWS Lambda 函数.配置 Lambda 函数以通过 Amazon Simple Notification Service (亚马逊 SNS). | J27: B | K27: AWS Config 有一个名为 acm-certificate-expiration-check 的托管规则来检查过期证书(可配置的天#) .https://aws.amazon.com/premiumsupport/knowledge-center/acm-certificate-expiration/ | N27: AWS Config 有一个名为 acm-certificate-expiration-check 的托管规则来检查过期证书(可配置的天#) .https://aws.amazon.com/premiumsupport/knowledge-center/acm-certificate-expiration/
A28: 24 | B28: 一家公司的动态网站使用美国的本地服务器托管,该公司正在欧洲推出其产品,它希望优化新欧洲用户的网站加载时间.该网站的后端必须保留在美国.几天后产品上线,急需解决方案.解决方案架构师应该推荐什么? | C28: 在 us-east-1 中启动一个 Amazon EC2 实例并将站点迁移到该实例. | D28: 将网站移动到 Amazon S3.使用区域之间的跨区域复制. | E28: 将 Amazon CloudFront 与指向本地服务器的自定义源一起使用. | F28: 使用指向本地服务器的 Amazon Route 53 地理邻近路由策略. | J28: C | K28: https://aws.amazon.com/pt/blogs/aws/amazon-cloudfront-support-for-custom-origins/ 您现在可以使用自定义来源创建 CloudFront 分配.每个分配都可以指向一个S3或自定义来源,这可能是另一个存储服务,也可能是更有趣和更动态的东西,例如EC2 实例甚至弹性负载均衡器 | N28: https://aws.amazon.com/pt/blogs/aws/amazon-cloudfront-support-for-custom-origins/ 您现在可以使用自定义来源创建 CloudFront 分配.每个分配都可以指向一个S3或自定义来源,这可能是另一个存储服务,也可能是更有趣和更动态的东西,例如EC2 实例甚至弹性负载均衡器
A29: 25 | B29: 一家公司希望降低其现有三层Web 架构的成本.Web.应用程序和数据库服务器在 Amazon EC2 实例上运行,用于开发.测试和生产环境.EC2 实例平均 CPU 利用率为30%高峰时段和非高峰时段10%的 CPU 使用率.生产EC2 实例每天运行 24 小时.开发和测试 EC2 实例每天至少运行8小时.公司计划实施自动化以停止开发和在EC2 实例不使用时对其进行测试.哪种 EC2 实例购买解决方案最符合公司的要求? | C29: 将 Spot 实例用于生产 EC2 实例.将预留实例用于开发和测试 EC2 实例. | D29: 将预留实例用于生产EC2 实例.将按需实例用于开发和测试 EC2 实例. | E29: 将 Spot 块用于生产 EC2 实例.将预留实例用于开发和测试 EC2 实例. | F29: 将按需实例用于生产 EC2 实例.将 Spot 块用于开发和测试 EC2 实例. | J29: B | K29: Spot 块不再可用,并且您不能在 Prod 机器上 24x7 使用 Spot 实例,因此选项 B应该是有效的. | N29: Spot 块不再可用,并且您不能在 Prod 机器上 24x7 使用 Spot 实例,因此选项 B应该是有效的.
A30: 26 | B30: 一家公司有一个生产网络应用程序,用户通过网络接口或移动应用程序上传文档.根据新的法规要求,新文档存储后不能修改或删除.解决方案架构师应该做些什么来满足这个要求? | C30: 将上传的文档存储在启用S3 版本控制和 S3 对象锁定的 Amazon S3 存储桶中 | D30: 将上传的文档存储在 Amazon S3 存储桶中.配置 S3 生命周期策略以定期存档文档. | E30: 将上传的文档存储在启用了S3 版本控制的 Amazon S3 存储桶中.配置 ACL 以将所有访问权限限制为只读. | F30: 将上传的文档存储在 Amazon Elastic File System (Amazon EFS) 卷上,通过以只读模式挂载卷来访问数据. | J30: A | K30: 您可以使用 S3 对象锁来使用一次写入多次读取(WORM)模型存储对象.对象锁定可以帮助防止对象在固定时间或无限期被删除或覆盖.您可以使用 S3 对象锁定来满足需要 WORM 存储的法规要求,或者添加额外的保护层以防止对象更改和删除. 版本控制是必需的,并在后用对象锁定时自动激活. https://docs.aws.amazon.com/AmazonS3/latest/userguide/object-lock-overview.html | N30: 您可以使用 S3 对象锁来使用一次写入多次读取(WORM)模型存储对象.对象锁定可以帮助防止对象在固定时间或无限期被删除或覆盖.您可以使用 S3 对象锁定来满足需要 WORM 存储的法规要求,或者添加额外的保护层以防止对象更改和删除. 版本控制是必需的,并在后用对象锁定时自动激活. https://docs.aws.amazon.com/AmazonS3/latest/userguide/object-lock-overview.html
A31: 27 | B31: 一家公司有多个 Web 服务器,需要经常访问一个通用的 Amazon RDS MySQL 多可用区数据库实例.该公司想要一种安全的方法让Web 服务器连接到数据库,同时满足频繁轮换用户凭证的安全要求.哪种解决方案满足这些要求? | C31: 将数据库用户凭证存储在 AWS Secrets Manager 中.授予必要的 IAM 权限以允许 Web 服务器访问 AWS Secrets Manager. | D31: 将数据库用户凭证存储在 AWS Systems Manager OpsCenter 中.授予必要的 IAM 权限以允许 Web 服务器访问 OpsCenter. | E31: 将数据库用户凭证存储在安全的 Amazon S3 存储桶中.授予必要的 IAM 权限以允许 Web 服务器检索凭证并访问数据库. | F31: 将数据库用户凭证存储在 Web 服务器文件系统上使用 AWS Key Management Service (AWS KMS)加密的文件中.Web 服务器应该能够解密文件并访问数据库. | J31: A | K31: AWS Secrets Manager 可帮助您保护访问您的应用程序.服务和 IT 资源所需的机密,该服务使您能够在整个生命周期内轻松轮换.管理和检索数据库凭证.API 密钥和其他机密.https://docs.aws.amazon.com/secretsmanager/latest/userguide/intro.html | N31: AWS Secrets Manager 可帮助您保护访问您的应用程序.服务和 IT 资源所需的机密,该服务使您能够在整个生命周期内轻松轮换.管理和检索数据库凭证.API 密钥和其他机密.https://docs.aws.amazon.com/secretsmanager/latest/userguide/intro.html
A32: 28 | B32: 一家公司在 AWS 上托管应用程序 Lambda 函数由 Amazon API Gateway API 调用.Lambda 函数将客户数据保存到 Amazon Aurora MySQL 数据库中.每当公司升级数据库时,Lambda 函数都无法建立数据库连接,直到升级完成结果是某些事件没有记录客户数据.解决方案架构师需要设计一个解决方案来存储在数据库升级期间创建的客户数据.哪种解决方案可以满足这些要求? | C32: 在 Lambda 函数和数据库之间配置一个 Amazon RDS 代理.配置 Lambda 函数以连接到 RDS 代理, | D32: 将我的Lambda函数的运行时间最大化,在代码中创建重试机制,将客户数据存储在数据库中, | E32: 将客户数据持久化到 Lambda 本地存储.配置新的 Lambda 函数扫描本地存储,将客户数据保存到数据库. | F32: 将客户数据存储在 Amazon Simple Queue Service (Amazon SQS) FIFO 队列中.创建一个新的 Lambda 函数来轮询队列并将客户数据存储在数据库中. | J32: D | K32: The question is ' a solution that stores data' -- >So for me answer is D -- >Store data in SQS | N32: The question is ' a solution that stores data' -- >So for me answer is D -- >Store data in SQS
A33: 29 | B33: 一家调查公司从美国地区收集了数年的数据该公司将数据托管在一个大小为3 TB 且还在不断增长的 Amazon S3 存储桶中.该公司已开始与欧洲营销部内共享数据拥有S3 存储桶的公司,该公司希望确保其数据传输成本尽可能低.哪种解决方案可以满足这些要求? | C33: 在公司的 S3 存储桶上配置 Requester Pays 功能 | D33: 配置从公司的 S3 存储桶到营销公司的 S3 存储桶之一的S3 跨区域复制. | E33: 为营销公司配置跨账户访问,使营销公司可以访问公司的S3存储桶. | F33: 将公司的 S3 存储桶配置为使用 S3 Intelligent-Tiering 将 S3 存储桶同步到营销公司的S3 存储桶之一 | J33: A | K33: 通常,当您想要共享数据但不会产生与访问数据的其他人相关的费用时,您将存储桶配置为请求者支付存储桶.例如,您可以在提供大型数据集(例如邮政编码目录)时使用请求者支付存储桶.参考数据.地理空间信息或网络爬取数据. https://docs.aws.amazon.com/AmazonS3/latest/userguide/RequesterPaysBuckets.html | N33: 通常,当您想要共享数据但不会产生与访问数据的其他人相关的费用时,您将存储桶配置为请求者支付存储桶.例如,您可以在提供大型数据集(例如邮政编码目录)时使用请求者支付存储桶.参考数据.地理空间信息或网络爬取数据. https://docs.aws.amazon.com/AmazonS3/latest/userguide/RequesterPaysBuckets.html
A34: 30 | B34: 某公司使用 Amazon S3 存储其机密审计文档.S3 存储桶使用存储桶策略根据最小权限原则限制对审计团队 IAM用户凭证的访问.公司经理担心 S3 存储桶中的文档被意外删除并想要一个更安全的解决方案.解决方案架构师应该如何保护审计文件? | C34: 在 S3 存储桶上启用版本控制和 MFA 删除功能. | D34: 对每个审计团队 IAM 用户账户的IAM用户凭证后用多重身份验证(MFA). | E34: 向审计团队的 IAM 用户账户添加 S3 生命周期策略,以在审计日期拒绝 s3:DeleteObject 操作, | F34: 使用 AWS Key Management Service (AWS KMS)加密 S3 存储桶并限制审计团队 IAM 用户账户访问 KMS 密钥. | J34: A | K34: accidental deletion of documents in the S3 bucket and want a more secure solution | N34: accidental deletion of documents in the S3 bucket and want a more secure solution
A35: 31 | B35: 一家公司正在使用 SQL 数据库存储可公开访问的电影数据.该数据库在 Amazon RDS 单可用区数据库实例上运行.脚本每天以随机间隔运行查询,以记录已上映的新电影数量添加到数据库中.脚本必须在营业时间内报告最终总数.公司的开发团队注意到,当脚本运行时,数据库性能不足以完成开发任务.解决方案架构师必须推荐解决此问题的解决方案.哪个解决方案会以最少的运营开销满足这个要求吗? | C35: 将数据库实例修改为多可用区部署 | D35: 创建数据库的只读副本.将脚本配置为仅查询只读副本. | E35: 指示开发团队在每天结束时手动导出数据库中的条目 | F35: 使用 Amazon Elasticache 缓存脚本针对数据库运行的常见查询 | J35: B | K35: Elasti Cache 如果用于读取常见结果,该脚本正在寻找添加的新电影,只读副本将是最佳选择, | N35: Elasti Cache 如果用于读取常见结果,该脚本正在寻找添加的新电影,只读副本将是最佳选择,
A36: 32 | B36: 某公司有应用程序在VPC中的Amazon EC2实例上运行,其中一个应用程序需要调用Amazon S3 API来存储和读取对象.根据公司的安全规定,不允许来自应用程序的流量穿越互联网.哪种解决方案可以满足这些要求? | C36: 配置 S3 网关端点. | D36: 配置 S3 接口端点. | E36: 在私有子网中创建 S3 存储桶. | F36: 在与 EC2 实例相同的区域中创建一个 S3 存储桶. | J36: A | K36: 网关终端节点提供与 Amazon S3 和 DynamoDB 的可靠连接,而您的VPC 不需要互联网网关或 NAT 设备.它应该是选项A.https://docs.aws.amazon.com/AmazonS3/latest/userguide/privatelink-interface-endpoints.html#types-of-vpc-endpoints-for-s3 | N36: 网关终端节点提供与 Amazon S3 和 DynamoDB 的可靠连接,而您的VPC 不需要互联网网关或 NAT 设备.它应该是选项A.https://docs.aws.amazon.com/AmazonS3/latest/userguide/privatelink-interface-endpoints.html#types-of-vpc-endpoints-for-s3
A37: 33 | B37: 一家公司将敏感的用户信息存储在 Amazon S3 存储桶中,该公司希望从在 VPC 内的 Amazon EC2 实例上运行的应用程序层提供对该存储桶的安全访问.解决方案架构师应采取哪些步骤组合来完成此任务?(选择两个.) | C37: 为 VPC 内的 Amazon S3 配置 VPC 网关终端节点 | D37: 创建存储桶策略以将对象公开到 S3 存储桶 | E37: 创建存储桶策略,将访问限制为仅在 VPC 中运行的应用程序层 | F37: 使用 S3 访问策略创建 IAM 用户并将 IAM 凭证复制到 EC2 实例 | G37: 创建一个 NAT 实例并让 EC2 实例使用 NAT 实例访问 S3 存储桶 | J37: A,C | K37: https://aws.amazon.com/premiumsupport/knowledge-center/s3-private-connection-no-authentication/ | N37: https://aws.amazon.com/premiumsupport/knowledge-center/s3-private-connection-no-authentication/
A38: 34 | B38: 一家公司运行一个由 MySQL 数据库提供支持的本地应用程序,该公司正在将应用程序迁移到AWS 以提高应用程序的弹性和可用性.当前架构在正常操作期间显示数据库上的大量读取活动.公司的开发团队每 4 小时拉一次生产数据库的完整导出以填充暂存环境中的数据库.在此期间,用户会遇到不可接受的应用程序延迟.开发团队在程序完成之前无法使用暂存环境.A解决方案架构师必须推荐可缓解应用程序延迟问题的替代架构.替代架构还必须使开发团队能够继续使用暂存环境而不会延迟.哪种解决方案满足这些要求? | C38: 将 Amazon Aurora MySQL 与多可用区 Aurora 副本一起用于生产.通过实施使用 mysqldump 实用程序的备份和还原过程来填充暂存数据库. | D38: 使用 Amazon Aurora MySQL 和多可用区 Aurora 副本进行生产.使用数据库克隆按需创建临时数据库 | E38: 将 Amazon RDS for MySQL 与 Mufti AZ 部署和只读副本用于生产,将备用实例用于暂存数据库. | F38: 将 Amazon RDS for MySQL 与多可用区部署和只读副本用于生产,通过实施使用 mysqldump 实用程序的备份和还原过程来填充暂存数据库. | J38: B | K38: Amazon Aurora Fast Database Cloning is what is required here. https://aws.amazon.com/blogs/aws/amazon-aurora-fastdatabase-cloning/ | N38: Amazon Aurora Fast Database Cloning is what is required here. https://aws.amazon.com/blogs/aws/amazon-aurora-fastdatabase-cloning/
A39: 35 | B39: 一家公司正准备在 Amazon S3 中存储机密数据.出于合规性原因,必须对静态数据进行加密 必须记录加密密钥的使用以进行审计.必须每年轮换密钥.哪种解决方案满足这些要求并且在操作上最有效传出? | C39: 使用客户提供的密钥进行服务器端加密(SSE-C) | D39: 使用 Amazon S3 托管密钥的服务器端加密(SSE-S3) | E39: 使用 AWS KMS (SSE-KMS) 客户主密钥(CMK)手动轮换的服务器端加密 | F39: 使用 AWS KMS (SSE-KMS) 客户主密钥(CMK)进行服务器端加密并自动轮换 | J39: D | K39: https://docs.aws.amazon.com/kms/latest/developerguide/rotate-keys.html 当您为客户管理的密钥启用自动密钥轮换时,AWS KMS 每年都会为 KMS 密钥生成新的加密材料. AWS KMS 还永久保存 KMS 密钥的旧加密材料,因此可用于解密 KMS 密钥加密的数据.AWS KMS 中的密钥轮换是一种加密最佳实践,旨在透明且易于使用.AWS KMS 支持仅适用于客户管理的 CMK 的可选自动密钥轮换.启用和禁用密钥轮换.默认情况下,客户管理的 CMK 上禁用自动密钥轮换.启用(或重新启用)密钥轮换时,AWS KMS 自动轮换 CMK 365 天后启用日期和此后每 365 天. | N39: https://docs.aws.amazon.com/kms/latest/developerguide/rotate-keys.html 当您为客户管理的密钥启用自动密钥轮换时,AWS KMS 每年都会为 KMS 密钥生成新的加密材料. AWS KMS 还永久保存 KMS 密钥的旧加密材料,因此可用于解密 KMS 密钥加密的数据.AWS KMS 中的密钥轮换是一种加密最佳实践,旨在透明且易于使用.AWS KMS 支持仅适用于客户管理的 CMK 的可选自动密钥轮换.启用和禁用密钥轮换.默认情况下,客户管理的 CMK 上禁用自动密钥轮换.启用(或重新启用)密钥轮换时,AWS KMS 自动轮换 CMK 365 天后启用日期和此后每 365 天.
A40: 36 | B40: 一家自行车共享公司正在开发一种多层架构,以在高峰运营时间跟踪其自行车的位置,该公司希望在其现有的分析平台中使用这些数据点.解决方案架构师必须确定最可行的多层架构支持此架构的选项数据点必须可从 REST API 访问.哪个操作满足存储和检索位置数据的这些要求? | C40: 将 Amazon Athena 与 Amazon S3 结合使用 | D40: 将 Amazon API Gateway 与 AWS Lambda 结合使用 | E40: 将 Amazon QuickSight 与 Amazon Redshift 结合使用. | F40: 将 Amazon API Gateway 与 Amazon Kinesis Data Analytics 结合使用 | J40: B | K40: 需要 API 网关来获取数据,所以选项A和C不可用.“公司希望在其现有的分析平台中使用这些数据点”,因此无需添加 Kynesis.选项 D 也被淘汰了, 这给我们留下了选项 B 作为正确的选项. | N40: 需要 API 网关来获取数据,所以选项A和C不可用.“公司希望在其现有的分析平台中使用这些数据点”,因此无需添加 Kynesis.选项 D 也被淘汰了, 这给我们留下了选项 B 作为正确的选项.
A41: 37 | B41: 一家公司有一个汽车销售网站,该网站将其列表存储在 Amazon RDS 的数据库中,当汽车出售时,需要从网站上删除列表,并且必须将数据发送到多个目标系统.哪种设计应该是解决方案建筑师推荐? | C41: 创建在更新 Amazon RDS 上的数据库时触发的 AWS Lambda 函数,以将信息发送到 Amazon Simple Queue Service (Amazon SQS>队列以供目标使用 | D41: 创建在更新 Amazon RDS 上的数据库时触发的 AWS Lambda 函数,以将信息发送到 Amazon Simple Queue Service (Amazon | E41: 订阅 RDS 事件通知并将 Amazon Simple Queue Service (Amazon SQS) 队列发送到多个 Amazon Simple Notification Service (Amazon SNS) 主题使用 AWS Lambda 函数更新目标 | F41: 订阅 RDS 事件通知并将 Amazon Simple Notification Service (Amazon SNS) 主题扇出到多个 Amazon Simple Queue Service (Amazon SQS) 队列使用 AWS Lambda 函数更新目标 | J41: D | K41: https://docs.aws.amazon.com/lambda/latest/dg/services-rds.html https://docs.aws.amazon.com/lambda/latest/dg/withsns.html | N41: https://docs.aws.amazon.com/lambda/latest/dg/services-rds.html https://docs.aws.amazon.com/lambda/latest/dg/withsns.html
A42: 38 | B42: 公司需要将数据存储在 Amazon S3 中并且必须防止数据被更改.公司希望上传到 Amazon S3 的新对象在不特定的时间内保持不变,直到公司决定修改对象.仅公司 AWS账户中的特定用户可以拥有删除对象的能力.解决方案架构师应该怎么做才能满足这些要求? | C42: 创建 S3 Glacier 保险库 对对象应用一次写入.多次读取(WORM)保险库锁定策略. | D42: 创建启用 S3 对象锁定的 S3 存储桶启用版本控制.设置保留期为100年.使用治理模式作为新对象的S3 存储桶的默认保留模式. | E42: 创建 S3 存储桶.使用 AWS CloudTrail 跟踪修改对象的任何 S3 API 事件.收到通知后,从公司拥有的任何备份版本中恢复修改后的对象. | F42: 创建后用 S3 对象锁定的 S3 存储桶.启用版本控制.为对象添加合法保留.将 s3:PutObjectLegalHold 权限添加到需要删除对象的用户的 IAM 策略中. | J42: D | K42: A-否,因为“特定用户可以删除”. B- 不作为“非特定时间量”. C- 否,因为“防止数据被更改". D- 答案:“对象锁定合法保留操作使您能够对对象版本进行合法保留.与设置保留期一样,合法保留可防止对象版本被覆盖或删除.但是,合法保留不会“它有一个相关的保留期,并且在删除之前一直有效."https://docs.aws.amazon.com/AmazonS3/latest/userguide/batch-ops-legal-hold.html | N42: A-否,因为“特定用户可以删除”. B- 不作为“非特定时间量”. C- 否,因为“防止数据被更改". D- 答案:“对象锁定合法保留操作使您能够对对象版本进行合法保留.与设置保留期一样,合法保留可防止对象版本被覆盖或删除.但是,合法保留不会“它有一个相关的保留期,并且在删除之前一直有效."https://docs.aws.amazon.com/AmazonS3/latest/userguide/batch-ops-legal-hold.html
A43: 39 | B43: 一家社交媒体公司允许用户将图像上传到其网站.该网站在 Amazon EC2 实例上运行在上传请求期间,该网站将图像调整为标准尺寸并将调整后的图像存储在 Amazon S3 中.用户遇到上传缓慢的问题对网站的请求.公司需要减少应用程序内的耦合并提高网站性能.解决方案架构师必须设计最有效的图像上传流程.解决方案架构师应该采取哪些行动组合来满足这些要求?(选择两个.) | C43: 配置应用程序以将图像上传到 S3 Glacier. | D43: 配置 Web 服务器以将原始图像上传到 Amazon S3. | E43: 将应用程序配置为通过使用预签名 URL 将图像直接从每个用户的浏览器上传到 Amazon S3. | F43: 配置 S3 事件通知以在上传图像时调用 AWS Lambda 函数.使用该函数调整图像大小 | G43: 创建一个 Amazon EventBridge (Amazon CloudWatch Events)规则,该规则按计划调用 AWS Lambda 函数以调整上传图像的大小. | J43: B,D | K43: Event notifications - Trigger workflows that use Amazon Simple Notification Service (Amazon SNS), Amazon Simple Queue Service (Amazon SQS), and AWS Lambda when a change is made to your S3 resources.事件通知-当您的S3资源发生更改时,触发使用Amazon Simple Notification Service (Amazon SNS)、Amazon简单队列服务(AmazonSQS)和AWS Lambda的工作流。 https://docs.aws.amazon.com/AmazonS3/latest/userguide/Welcome.html | N43: Event notifications - Trigger workflows that use Amazon Simple Notification Service (Amazon SNS), Amazon Simple Queue Service (Amazon SQS), and AWS Lambda when a change is made to your S3 resources.事件通知-当您的S3资源发生更改时,触发使用Amazon Simple Notification Service (Amazon SNS)、Amazon简单队列服务(AmazonSQS)和AWS Lambda的工作流。 https://docs.aws.amazon.com/AmazonS3/latest/userguide/Welcome.html
A44: 40 | B44: 一家公司最近将消息处理系统迁移到 AWS.系统将消息接收到运行在 Amazon EC2 实例上的 ActiveMQ 队列中.消息由运行在Amazon EC2 上的消费者应用程序处理.消费者应用程序处理消息并将结果写入一个在 Amazon EC2 上运行的 MySQL 数据库.该公司希望此应用程序具有高可用性,具有两个操作复杂性 哪种架构具有 HGHEST 可用性? | C44: 将第二个 ActiveMQ 服务器添加到另一个可用区.在另一个可用区添加一个额外的消费者 EC2 实例.将 MySQL 数据库复制到另一个可用区. | D44: 将 Amazon MQ 与跨两个可用区配置的活动/备用代理一起使用.在另一个可用区中添加一个额外的消费者 EC2 实例.将 MySQL 数据库复制到另一个可用区. | E44: 使用跨两个可用区配置的活动/备用记录器的 Amazon MQ.在另一个可用区中添加一个额外的消费者 EC2 实例,使用后用了多可用区的 Amazon ROS to MySQL. | F44: 将 Amazon MQ 与跨两个可用区配置的活动/备用代理一起使用.d 为跨两个可用区的消费者 EC2 实例添加 Auto Scaling 组.使用启用了多可用区的 Amazon RDS for MySQL. | J44: D | K44: 答案是 D,表示“最高可用”,较少“操作复杂”.“启用了多可用区的 Amazon RDS for MySQL”选项不包括 A 和 B. "Auto Scaling组“比仅仅添加一个实例更可用,并且在发生事故时降低了操作复杂性(因为补救是自动化的)这不包括C.C和 D 可供选择基于 .. D over C since 已配置 | N44: 答案是 D,表示“最高可用”,较少“操作复杂”.“启用了多可用区的 Amazon RDS for MySQL”选项不包括 A 和 B. "Auto Scaling组“比仅仅添加一个实例更可用,并且在发生事故时降低了操作复杂性(因为补救是自动化的)这不包括C.C和 D 可供选择基于 .. D over C since 已配置
A45: 41 | B45: 一家公司在一组本地服务器上托管一个容器化的Web 应用程序,这些服务器处理传入的请求.请求的数量正在快速增长,本地服务器无法处理增加的请求数.公司想要移动应用程序以最少的代码更改和最少的开发工作量迁移到 AWS.哪种解决方案将以最少的运营开销满足这些要求? | C45: 使用 Amazon Elastic Container Service (Amazon ECS)上的 AWS Fargate 运行带有 Service Auto Scaling 的容器化 Web 应用程序.使用 Application Load Balancer 分发传入请求. | D45: 使用两个 Amazon EC2 实例来托管容器化的 Web 应用程序.使用应用程序负载均衡器来分发传入的请求. | E45: 将 AWS Lambda 与使用一种受支持语言的新代码一起使用.创建多个 Lambda 函数以支持负载,使用 Amazon API Gateway 作为 Lambda 函数的入口点. | F45: 使用 AWS ParallelCluster 等高性能计算(HPC)解决方案来建立能够以适当规模处理传入请求的HPC 集群. | J45: A | K45: 更少的操作开销意味着 A:Fargate(无 EC2),在 ECS上移动容器,自动扩展以实现增长和 ALB 以平衡消耗. B - 需要配置EC2. C- 需要添加代码(开发人员). D -似乎是最复杂的方法,例如重新设计应用程序以利用 HPC 平台. | N45: 更少的操作开销意味着 A:Fargate(无 EC2),在 ECS上移动容器,自动扩展以实现增长和 ALB 以平衡消耗. B - 需要配置EC2. C- 需要添加代码(开发人员). D -似乎是最复杂的方法,例如重新设计应用程序以利用 HPC 平台.
A46: 42 | B46: 一家公司使用 50 TB 的数据进行报告.该公司希望将这些数据从本地移动到 AWS 公司数据中心中的一个自定义应用程序每周运行一次数据转换作业.该公司计划暂停应用程序,直到数据传输已完成,需要尽快开始传输过程.数据中心没有任何可用的网络带宽来处理额外的工作负载.解决方案架构师必须传输数据并且必须配置转换作业以继续在 AWS 云中运行.哪种解决方案将以最少的运营开销满足这些要求? | C46: 使用 AWS DataSync 移动数据.使用 AWS Glue 创建自定义转换作业. | D46: 订购 AWS Snowcone 设备以移动数据.将转换应用程序部署到设备. | E46: 订购 AWS Snowball Edge Storage Optimized 设备.将数据复制到设备.使用 AWS Glue 创建自定义转换作业. | F46: 订购包含 Amazon EC2 计算的 AWS D.Snowball 边缘存储优化设备.将数据复制到设备.在 AWS 上创建一个新的EC2 实例以运行转换应用程序. | J46: C | K46: A-> 使用 AWS DataSync 移动数据.使用 AWS Glue 创建自定义转换作业. - 没有可用于 DataSync 的 BW,因此“尽快”将是数周/数月. B->订购 AWS Snowcone 设备以移动数据.将转换应用程序部署到设备. - Snowcone 将仅存储 14TB (SSD 配置) . C->订购 AWS Snowball 边缘存储优化设备.将数据复制到设备.使用 AWS Glue 创建自定义转换作业. - SnowBall 可以存储 80TB (ok),移动设备大约需要1周(比A快),AWS Glue 允许执行 ETL 作业.这就是答案. D->订购包含 Amazon EC2 计算的 AWS Snowball Edge Storage Optimized 设备.将数据复制到设备.在 AWS 上创建一个新的 EC2 实例以运行转换应用程序.- 与 C 相同,但ETL 作业需要 EC2 实例的部署/配置/维护,而 Glue 是无服务器的.这意味着 D比C具有更多的操作开销. | N46: A-> 使用 AWS DataSync 移动数据.使用 AWS Glue 创建自定义转换作业. - 没有可用于 DataSync 的 BW,因此“尽快”将是数周/数月. B->订购 AWS Snowcone 设备以移动数据.将转换应用程序部署到设备. - Snowcone 将仅存储 14TB (SSD 配置) . C->订购 AWS Snowball 边缘存储优化设备.将数据复制到设备.使用 AWS Glue 创建自定义转换作业. - SnowBall 可以存储 80TB (ok),移动设备大约需要1周(比A快),AWS Glue 允许执行 ETL 作业.这就是答案. D->订购包含 Amazon EC2 计算的 AWS Snowball Edge Storage Optimized 设备.将数据复制到设备.在 AWS 上创建一个新的 EC2 实例以运行转换应用程序.- 与 C 相同,但ETL 作业需要 EC2 实例的部署/配置/维护,而 Glue 是无服务器的.这意味着 D比C具有更多的操作开销.
A47: 43 | B47: 一家公司创建了一个图像分析应用程序,用户可以在其中上传照片并将相框添加到他们的图像中,用户上传图像和元数据以指示他们想要添加到图像中的相框.该应用程序使用单个 Amazon EC2实例和 Amazon DynamoDB 来存储元数据.应用程序变得越来越流行,用户数量也在增加.公司预计并发用户数量会根据一天中的时间和一周中的一天而有很大差异.公司必须确保应用程序可以扩展以满足不断增长的用户群的需求.哪种解决方案可以满足这些要求? | C47: 使用 AWS Lambda 处理照片.将照片和元数据存储在 DynamoDB 中. | D47: 使用 Amazon Kinesis Data Firehose 处理照片并存储照片和元数据. | E47: 使用 AWS Lambda 处理照片.将照片存储在 Amazon S3 中.保留 DynamoDB 以存储元数据. | F47: 将 EC2 实例的数量增加到三个.使用预置 IOPS SSD (io2) Amazon Elastic Block Store (Amazon EBS) 卷来存储照片和元数据. | J47: C | K47: 不要将图像存储在数据库中;) ... 正确答案应该是C | N47: 不要将图像存储在数据库中;) ... 正确答案应该是C
A48: 44 | B48: 一家医疗记录公司在 Amazon EC2 实例上托管应用程序.该应用程序处理存储在 Amazon S3 上的客户数据文件.EC2 实例托管在公共子网中.EC2 实例通过 Internet 访问 Amazon S3,但它们确实不需要任何其他网络访问.一项新要求要求文件传输的网络流量采用私有路由,而不是通过 Internet 发送.解决方案架构师应建议对网络架构进行哪些更改以满足此要求? | C48: 创建 NAT 网关.配置公有子网的路由表以通过 NAT 网关将流量发送到 Amazon S3. | D48: 为 EC2 实例配置安全组以限制出站流量,以便只允许到S3 前缀列表的流量. | E48: 将 EC2 实例移动到私有子网.为 Amazon S3 创建一个VPC终端节点,并将终端节点链接到私有子网的路由表 | F48: 从 VPC 中移除互联网网关.设置 AWS Direct Connect 连接,并通过 Direct Connect 连接将流量路由到 Amazon S3. | J48: C | K48: C is correct. There is no requirement for public access from internet. Application must be moved in Private subnet. This is a prerequisite in using VPC endpoints with S3 .https://aws.amazon.com/blogs/storage/managing-amazon-s3-access-with-vpcendpoints-and-s3-access-points/ | N48: C is correct. There is no requirement for public access from internet. Application must be moved in Private subnet. This is a prerequisite in using VPC endpoints with S3 .https://aws.amazon.com/blogs/storage/managing-amazon-s3-access-with-vpcendpoints-and-s3-access-points/
A49: 45 | B49: 一家公司为其公司网站使用流行的内容管理系统(CMS).但是,所需的修补和维护工作很繁重.该公司正在重新设计其网站并需要一个新的解决方案.该网站将每年更新四次,并且确实不需要任何可用的动态内容.解决方案必须提供高可扩展性和增强的安全性.哪种更改组合将以最少的运营开销满足这些要求?(选择两个.) | C49: 在网站前面配置Amazon CloudFront以使用HTTPS功能。 | D49: 在网站前部署AWS WAF Web ACL,提供HTTPS功能 | E49: 创建和部署 AWS Lambda 函数来管理和提供网站内容 | F49: 创建新网站和 Amazon S3 存储桶 在启用静态网站托管的 S3 存储桶上部署网站 | G49: 创建新网站.使用应用程序负载均衡器后面的 Amazon EC2 实例的 Auto Scaling 组部署网站. | J49: A,D | K49: A-> 我们可以将 CloudFront 配置为需要来自客户端的HTTPS(增强的安全性) https://docs.aws.amazon.com/AmazonCloudFront/latest/DeveloperGuide/using-https-viewers-to-cloudfront.html. D-> 在 S3 上存储静态网站提供可扩展性和更少的操作开销,然后配置应用程序 LB 和 EC2 实例(因此 E不可用). B已退出,因为 AWS WAF Web ACL 不提供 HTTPS 功能,而仅保护 HTTPS. | N49: A-> 我们可以将 CloudFront 配置为需要来自客户端的HTTPS(增强的安全性) https://docs.aws.amazon.com/AmazonCloudFront/latest/DeveloperGuide/using-https-viewers-to-cloudfront.html. D-> 在 S3 上存储静态网站提供可扩展性和更少的操作开销,然后配置应用程序 LB 和 EC2 实例(因此 E不可用). B已退出,因为 AWS WAF Web ACL 不提供 HTTPS 功能,而仅保护 HTTPS.
A50: 46 | B50: 一家公司将其应用程序日志存储在 Amazon CloudWatch Logs 日志组中,一项新政策要求该公司将所有应用程序日志近乎实时地存储在 Amazon OpenSearch Service (Amazon Elasticsearch Service)中.哪种解决方案将满足此要求最少的运营开销? | C50: 配置 CloudWatch Logs 订阅以将日志流式传输到 Amazon OpenSearch Service (Amazon Elasticsearch Service). | D50: 创建AWS Lambda函数.使用日志组调用函数将日志写入Amazon OpenSearch Service (Amazon Elasticsearch Service) . | E50: 创建 Amazon Kinesis Data Firehose 传输流.将日志组配置为传输流的源.将 Amazon OpenSearch Service (Amazon Elasticsearch Service)配置为传输流的目标. | F50: 在每台应用程序服务器上安装和配置 Amazon Kinesis Agent 以将日志传送到 Amazon Kinesis Data Streams.配置 Kinesis Data Streams 以将日志传送到 Amazon OpenSearch Service (Amazon Elasticsearch Service) | J50: A | K50: 您可以配置CloudWatch Logs日志组,以便通过CloudWatLogs订阅将其接收到的数据流式传输到您的Amazon OpenSearch 服务集群。 | N50: 您可以配置CloudWatch Logs日志组,以便通过CloudWatLogs订阅将其接收到的数据流式传输到您的Amazon OpenSearch 服务集群。
A51: 47 | B51: 一家公司正在构建一个基于 Web 的应用程序,该应用程序在多个可用区的 Amazon EC2 实例上运行.该 Web 应用程序将提供对总大小约 900 TB 的文本文档存储库的访问,该公司预计该 Web 应用程序将经历一段时间高需求.解决方案架构师必须确保文本文档的存储组件可以随时扩展以满足应用程序的需求.公司关心解决方案的总体成本,满足这些要求的存储解决方案成本最高-有效? | C51: Amazon Elastic Block Store (Amazon EBS) | D51: Amazon 弹性文件系统(Amazon EFS) | E51: Amazon Elasticsearch Service (Amazon ES) | F51: 亚马逊 S3 | J51: D | K51: Amazon S3 最便宜,可以从任何地方访问. | N51: Amazon S3 最便宜,可以从任何地方访问.
A52: 48 | B52: 一家公司正在使用 Amazon API Gateway 为其在 us-east-1 区域和 ap-southeast-2 区域的忠诚度俱乐部用户设计 REST API.解决方案架构师必须设计一种解决方案来保护这些 API Gateway 托管的 REST来自 SQL 注入和跨站点脚本攻击的跨多个帐户的 API.哪种解决方案能够以最少的管理工作量满足这些要求? | C52: 在两个区域中设置 AWS WAF将区域 Web ACL 与 API 阶段相关联. | D52: 在两个区域中设置 AWS Firewall Manager.集中配置 AWS WAF 规则. | E52: 在浴缸区域中设置 AWS Shield.将区域 Web ACL 与 API 阶段相关联. | F52: 在其中一个区域中设置 AWS Shield.将区域 Web ACL 与 API 阶段相关联. | J52: B | K52: If you want to use AWS WAF across accounts, accelerate WAF configuration, automate the protection of new resources, use Firewall Manager with AWS WAF | N52: If you want to use AWS WAF across accounts, accelerate WAF configuration, automate the protection of new resources, use Firewall Manager with AWS WAF
A53: 49 | B53: 一家公司在 us-west-2 区域的网络负载均衡器(NLB)后面的三个 Amazon EC2 实例上实施了自我管理的 DNS 解决方案.该公司的大多数用户位于美国和欧洲,该公司希望提高解决方案的性能和可用性.公司在 eu-west-1 区域启动和配置三个 EC2 实例,并将 EC2 实例添加为新 NLB 的目标.公司可以使用哪种解决方案将流量路由到所有EC2 实例? | C53: 创建 Amazon Route 53 地理定位路由策略以将请求路由到两个 NLB 之一.创建 Amazon CloudFront 分配.使用 Route 53 记录作为分配的来源. | D53: 在 AWS Global Accelerator 中创建标准加速器.在 us-west-2 和 eu-west-1 中创建终端节点组将两个 NLB 添加为终端节点组的终端节点. | E53: 将弹性 IP 地址附加到六个 EC2 实例.创建 Amazon Route 53 地理定位路由策略以将请求路由到六个 EC2 实例之一.创建 Amazon CloudFront 分配.使用 Route 53 记录作为分配的来源. | F53: 将两个 NLB 替换为两个 Application Load Balancer (ALB).创建 Amazon Route 53 延迟路由策略以将请求路由到两个 ALB 之一.创建 Amazon CloudFront 分配.使用 Route 53 记录作为分配的来源. | J53: B | K53: B 用于自我管理的 DNS 解决方案 | N53: B 用于自我管理的 DNS 解决方案
A54: 50 | B54: 一家公司在 AWS 上运行在线事务处理(OLTP)工作负载.此工作负载在多可用区部署中使用未加密的 Amazon RDS 数据库实例.每日数据库快照均从此实例中获取.解决方案架构师应如何确保数据库和快照总是在向前加密? | C54: 加密最新数据库快照的副本.通过恢复加密快照替换现有数据库实例 | D54: 创建一个新的加密 Amazon Elastic Block Store (Amazon EBS) 卷并将快照复制到它.在数据库实例上启用加密. | E54: 复制快照并使用 AWS Key Management Service (AWS KMS)启用加密.将加密的快照还原到现有数据库实例. | F54: 将快照复制到使用 AWS Key Management Service (AWS KMS)托管密钥(SSE-KMS)的服务器端加密进行加密的 Amazon S3 存储桶 | J54: A | K54: 您可以在创建 Amazon RDS 数据库实例时启用加密,但不能在创建后启用.但是,您可以通过创建数据库实例的快照,然后创建加密副本来为未加密的数据库实例添加加密快照.然后,您可以从加密快照中恢复数据库实例,以获取原始数据库实例的加密副本. https://docs.aws.amazon.com/prescriptive-guidance/latest/patterns/encrypt-an-existing-amazon-rds-for-postgresql-dbinstance.html | N54: 您可以在创建 Amazon RDS 数据库实例时启用加密,但不能在创建后启用.但是,您可以通过创建数据库实例的快照,然后创建加密副本来为未加密的数据库实例添加加密快照.然后,您可以从加密快照中恢复数据库实例,以获取原始数据库实例的加密副本. https://docs.aws.amazon.com/prescriptive-guidance/latest/patterns/encrypt-an-existing-amazon-rds-for-postgresql-dbinstance.html
A55: 51 | B55: 一家公司想要构建一个可扩展的密钥管理基础架构,以支持需要在其应用程序中加密数据的开发人员.解决方案架构师应该如何减少运营负担? | C55: 使用多重身份验证(MFA)来保护加密密钥. | D55: 使用 AWS Key Management Service (AWS KMS) 保护加密密钥 | E55: 使用 AWS Certificate Manager (ACM)创建.存储和分配加密密钥 | F55: 使用 IAM 策略限制具有访问权限的用户范围以保护加密密钥 | J55: B | K55: 如果您是需要使用非对称密钥对数据进行数字签名或验证的开发人员,您应该使用该服务来创建和管理您需要的私钥.如果您正在寻找可扩展的密钥管理基础架构来支持您的开发人员及其不断增长的应用程序,您应该使用它来降低您的许可成本和运营负担 .. https://aws.amazon.com/cn/kms/faqs/?nc1=h_ls | N55: 如果您是需要使用非对称密钥对数据进行数字签名或验证的开发人员,您应该使用该服务来创建和管理您需要的私钥.如果您正在寻找可扩展的密钥管理基础架构来支持您的开发人员及其不断增长的应用程序,您应该使用它来降低您的许可成本和运营负担 .. https://aws.amazon.com/cn/kms/faqs/?nc1=h_ls
A56: 52 | B56: 某公司有一个动态web应用托管在两个Amazon EC2实例上,该公司有自己的SSL证书,在每个实例上执行SSL终止.最近流量增加,运营团队确定SSL加密和解密导致 Web 服务器的计算能力达到最大极限,解决方案架构师应该如何提高应用程序的性能? | C56: 使用 AWS Certificate Manager (ACM)创建新的 SSL 证书,在每个实例上安装 ACM 证书. | D56: 创建 Amazon S3 存储桶将 SSL 证书迁移到 S3 存储桶.配置 EC2 实例以引用存储桶以终止 SSL. | E56: 创建另一个 EC2 实例作为代理服务器将 SSL 证书迁移到新实例并将其配置为直接连接到现有 EC2 实例 | F56: 将 SSL 证书导入 AWS Certificate Manager (ACM).使用 HTTPS 侦听器创建一个应用程序负载均衡器,该侦听器使用来自 ACM 的SSL 证书. | J56: D | K56: https://aws.amazon.com/certificate-manager/:“使用 AWS Certificate Manager,您可以快速请求证书,将其部署在 ACM 集成的 AWS 资源上,例如 Elastic Load Balancer.Amazon CloudFront 分配和API Gateway 上的 API,让 AWS Certificate Manager 处理证书续订. 它还使您能够为内部资源创建私有证书并集中管理证书生命周期.” | N56: https://aws.amazon.com/certificate-manager/:“使用 AWS Certificate Manager,您可以快速请求证书,将其部署在 ACM 集成的 AWS 资源上,例如 Elastic Load Balancer.Amazon CloudFront 分配和API Gateway 上的 API,让 AWS Certificate Manager 处理证书续订. 它还使您能够为内部资源创建私有证书并集中管理证书生命周期.”
A57: 53 | B57: 一家公司有一个高度动态的批处理作业,它使用许多 Amazon EC2 实例来完成它.该作业本质上是无状态的,可以在任何给定时间启动和停止而不会产生负面影响,通常总共需要60分钟以上完成.公司已请解决方案架构师设计符合工作要求的可扩展且具有成本效益的解决方案.解决方案架构师应该推荐什么? | C57: 实施 EC2 Spot 实例 | D57: 购买 EC2 预留实例 | E57: 实施 EC2 按需实例 | F57: 在AWS Lambda上实现处理 | J57: A | K57: Cant be implemented on Lambda because the timeout for Lambda is 15mins and the Job takes 60minutes to complete | N57: Cant be implemented on Lambda because the timeout for Lambda is 15mins and the Job takes 60minutes to complete
A58: 54 | B58: 一家公司在 AWS 上运行其两层电子商务网站.Web 层由一个负载均衡器组成,该负载均衡器将流量发送到 Amazon EC2 实例.数据库层使用 Amazon RDS 数据库实例.EC2 实例和 RDS 数据库实例不应暴露在公共互联网上.EC2 实例需要互联网访问才能通过第三方Web 服务完成订单的支付处理.应用程序必须具有高可用性.哪种配置选项组合可以满足这些要求?(选择两个.) | C58: 使用 Auto Scaling 组在私有子网中启动 EC2 实例.在私有子网中部署 RDS 多可用区数据库实例. | D58: 为 VPC 配置两个私有子网和两个跨两个可用区的 NAT 网关.在私有子网中部署应用程序负载均衡器. | E58: 使用 Auto Scaling 组跨两个可用区在公共子网中启动 EC2 实例.在私有子网中部署 RDS 多可用区数据库实例. | F58: 为 VPC 配置一个公有子网.一个私有子网和两个跨两个可用区的 NAT 网关.在公有子网中部署一个应用程序负载均衡器. | G58: 为 VPC 配置两个公有子网.两个私有子网和两个跨两个可用区的 NAT 网关.在公有子网中部署应用程序负载均衡器. | J58: A,E | K58: 在您开始之前:决定您将为 EC2 实例使用哪两个可用区.在每个可用区中使用至少一个公共子网配置您的虚拟私有云(VPC).这些公共子网用于配置负载均衡器.您可以改为在这些可用区的其他子网中启动您的EC2 实例. | N58: 在您开始之前:决定您将为 EC2 实例使用哪两个可用区.在每个可用区中使用至少一个公共子网配置您的虚拟私有云(VPC).这些公共子网用于配置负载均衡器.您可以改为在这些可用区的其他子网中启动您的EC2 实例.
A59: 55 | B59: 解决方案架构师需要实施解决方案以降低公司的存储成本.公司的所有数据都在 Amazon S3 标准存储类中,公司必须将所有数据保留至少25年.最近2年的数据必须高度可用且可立即检索.哪种解决方案将满足这些要求? | C59: 设置 S3 生命周期策略以立即将对象转换到 S3 Glacier Deep Archive. | D59: 设置 S3 生命周期策略以在 2 年后将对象转换到 S3 Glacier Deep Archive. | E59: 使用 S3 智能分层.激活存档选项以确保数据存档在 S3 Glacier Deep Archive 中. | F59: 设置 S3 生命周期策略以立即将对象转换到 S3 One Zone-Infrequent Access (S3 One Zone-IA)并在 2 年后转换到 S3 Glacier Deep Archive. | J59: B | K59: B is the only right answer. C does not indicate archiving after 2 years. If it did specify 2 years, then C would also be an option. | N59: B is the only right answer. C does not indicate archiving after 2 years. If it did specify 2 years, then C would also be an option.
A60: 56 | B60: 一家公司在 AWS 上运行其电子商务应用程序,每个新订单都作为消息发布在 RabbitMQ 队列中,该队列在单个可用区的 Amazon EC2 实例上运行,这些消息由运行在单独 EC2 上的不同应用程序处理实例.此应用程序将详细信息存储在另一个 EC2 实例上的 PostgreSQL 数据库中.所有 EC2 实例都在同一个可用区中.公司需要重新设计其架构以提供最高的可用性和最少的运营开销.解决方案架构师应该做什么怎样才能满足这些要求? | C60: 将队列迁移到 Amazon MQ 上的 RabbitMQ 实例的冗余对(活动/备用).创建多可用区 Auto Scaling 组(或托管应用程序的 EC2 实例.为 EC2 实例创建另一个多可用区 Auto Scaling 组)托管 PostgreSQL 数据库. | D60: 将队列迁移到 Amazon MQ 上的一对冗余 RabbitMQ 实例(活动/备用).为托管应用程序的 EC2 实例创建多可用区 Auto Scaling组.迁移数据库以在 Amazon 的多可用区部署上运行用于 PostgreSQL 的 RDS. | E60: 为托管 RabbitMQ 队列的 EC2 实例创建一个多可用区 Auto Scaling 组为托管应用程序的 EC2 实例创建另一个多可用区 Auto Scaling 组.迁移数据库以在 Amazon RDS fqjPostgreSQL 的多可用区部署上运行. | F60: 为托管 RabbitMQ 队列的 EC2 实例创建一个多可用区 Auto Scaling 组.为托管应用程序的 EC2 实例创建另一个多可用区 Auto Scaling 组.为托管应用程序的 EC2 实例创建第三个多可用区 Auto Scaling 组PostgreSQL 数据库. | J60: B | K60: 迁移到 Amazon MQ 减少了队列管理的开销.C和 D 被解雇. 在 A和 B 之间做出决定意味着决定选择EC2 的 AutoScaling 组或 Postgress 的 RDS(都是多可用区). RDS 选项对运营的影响较小,因为它以服务的形式提供所需的工具和软件.例如,考虑向数据库添加额外节点(如只读副本)的努力. https://docs.aws.amazon.com/amazon-mq/latest/developer-guide/active-standby-brokerdeployment.html https://aws.amazon.com/rds/postgresql/ | N60: 迁移到 Amazon MQ 减少了队列管理的开销.C和 D 被解雇. 在 A和 B 之间做出决定意味着决定选择EC2 的 AutoScaling 组或 Postgress 的 RDS(都是多可用区). RDS 选项对运营的影响较小,因为它以服务的形式提供所需的工具和软件.例如,考虑向数据库添加额外节点(如只读副本)的努力. https://docs.aws.amazon.com/amazon-mq/latest/developer-guide/active-standby-brokerdeployment.html https://aws.amazon.com/rds/postgresql/
A61: 57 | B61: 报告团队每天都会在 Amazon S3 存储桶中接收文件.报告团队每天在同一时间手动审查并将文件从这个初始 S3 存储桶复制到分析S3 存储桶,以便与 Amazon QuickSight 一起使用.其他团队正在启动将更多更大尺寸的文件发送到初始 S3 存储桶.报告团队希望在文件进入初始 S3 存储桶时自动移动文件分析 S3 存储桶.报告团队还希望使用 AWS Lambda 函数来运行模式匹配代码此外,报告团队希望将数据文件发送到 Amazon SageMaker Pipelines 中的管道.解决方案架构师应该如何以最少的运营开销满足这些要求? | C61: 创建 Lambda 函数以将文件复制到分析 S3 存储桶.为分析 S3 存储桶创建 S3 事件通知.将 Lambda 和 SageMaker Pipelines 配置为事件通知的目标.将 s30bjectCreated:Put 配置为事件类型. | D61: 创建 Lambda 函数以将文件复制到分析 S3 存储桶.配置分析 S3 存储桶以将事件通知发送到 Amazon EventBridge (Amazon CloudWatch Events).在 EventBridge (CloudWatch Events)中配置 ObjectCreated 规则.配置 Lambda 和 SageMaker 管道作为规则的目标. | E61: 配置 S3 存储桶之间的S3 复制.为分析 S3 存储桶创建 S3 事件通知.将 Lambda 和 SageMaker Pipelines 配置为事件通知的目标将 s30bjectCreated:Put 配置为事件类型. | F61: 配置 S3 存储桶之间的S3 复制.配置分析 S3 存储桶以将事件通知发送到 Amazon EventBridge (Amazon CloudWatch Events).在 EventBridge (CloudWatch Events)中配置 ObjectCreated 规则.将 Lambda 和 SageMaker Pipelines 配置为该规则的目标. | J61: D | K61: The files are getting large, less operational overhead - so will choose S3 replication. Event bridge is far more advanced than S3 event notification and they support multiple targets. S3 Event notification may not support Sagemaker. Also filtering and pattern matching available in Event bridge. So answer D. | N61: The files are getting large, less operational overhead - so will choose S3 replication. Event bridge is far more advanced than S3 event notification and they support multiple targets. S3 Event notification may not support Sagemaker. Also filtering and pattern matching available in Event bridge. So answer D.
A62: 58 | B62: 解决方案架构师需要帮助公司优化在 AWS 上运行应用程序的成本.应用程序将使用 Amazon EC2 实例.AWS Fargate 和 AWS Lambda 在架构内进行计算.EC2 实例将运行应用程序.EC2 的使用将是零星的和不可预测的.运行在EC2 实例上的工作负载随时可能中断.应用程序前端将运行在 Fargate 上,Lambda 将服务于 API 层.前端利用率和 API 层利用率在明年的过程中将是可预测的.哪种购买选项组合将为托管此应用程序提供最具成本效益的解决方案?(选择两个.) | C62: 将 Spot 实例用于数据摄取层 | D62: 为数据摄取层使用按需实例 | E62: 为前端和 API 层购买 1 年的 Compute Savings Plan. | F62: 为数据摄取层购买 1年的所有前期预留实例. | G62: 为前端和 API 层购买为期 1年的 EC2 实例 Savings Plan. | J62: A,C | K62: EC2 instance Savings Plan saves 72% while Compute Savings Plans saves 66%. But according to link, it says 'Compute Savings Plans provide the most flexibility and help to reduce your costs by up to 66%. These plans automatically apply to EC2 instance usage regardless of instance family, size, AZ, region, OS or tenancy, and also apply to Fargate and Lambda usage.' EC2 instance Savings Plans are not applied to Fargate or Lambda. E makes more sense than C. See https://aws.amazon.com/savingsplans/faq/, EC2 instance Savings Plan (up to 72% saving) costs less than Compute Savings Plan (up to 66% saving).EC2实例节省计划节省72%,而计算节省计划节省66%。但据link称,“计算节省计划提供了最大的灵活性,有助于将成本降低66%。这些计划自动适用于EC2实例的使用,而不考虑实例家族、大小、AZ、地区、操作系统或租赁,也适用于Fargate和Lambda的使用。“EC2实例节省计划不适用于Fargate或Lambda。 | N62: EC2 instance Savings Plan saves 72% while Compute Savings Plans saves 66%. But according to link, it says 'Compute Savings Plans provide the most flexibility and help to reduce your costs by up to 66%. These plans automatically apply to EC2 instance usage regardless of instance family, size, AZ, region, OS or tenancy, and also apply to Fargate and Lambda usage.' EC2 instance Savings Plans are not applied to Fargate or Lambda. E makes more sense than C. See https://aws.amazon.com/savingsplans/faq/, EC2 instance Savings Plan (up to 72% saving) costs less than Compute Savings Plan (up to 66% saving).EC2实例节省计划节省72%,而计算节省计划节省66%。但据link称,“计算节省计划提供了最大的灵活性,有助于将成本降低66%。这些计划自动适用于EC2实例的使用,而不考虑实例家族、大小、AZ、地区、操作系统或租赁,也适用于Fargate和Lambda的使用。“EC2实例节省计划不适用于Fargate或Lambda。
A63: 59 | B63: 一家公司运行一个基于 Web 的门户,为用户提供全球突发新闻.本地警报和天气更新.该巾户通过混合使用静态和动态内容为每个用户提供个性化视图.内容通过 API 通过 HTTPS 提供服务器在应用程序负载均衡器(ALB)后面的 Amazon EC2 实例上运行.公司希望巾户网站尽快向其全球用户提供此内容.解决方案架构师应如何设计应用程序以确保最少的所有用户的延迟? | C63: 在单个 AWS 区域中部署应用程序堆栈.使用 Amazon CloudFront 通过将 ALB 指定为源来提供所有静态和动态内容. | D63: 在两个 AWS 区域中部署应用程序堆栈.使用 Amazon Route 53 延迟路由策略在最近的区域中提供来自 ALB 的所有内容. | E63: 在单个 AWS 区域中部署应用程序堆栈.使用 Amazon CloudFront 提供静态内容,直接从 ALB 提供动态内容. | F63: 在两个 AWS 区域中部署应用程序堆栈.使用 Amazon Route 53 地理定位路由策略为最近区域中的 ALB 提供所有内容. | J63: A | K63: Amazon CloudFront 是一种 Web 服务,可以加快静态和动态 Web 内容的分发.https://aws.amazon.com/blogs/networking-and-content-delivery/deliver-your-apps-dynamic-content-使用-amazon-cloudfront-getting-started-template/ | N63: Amazon CloudFront 是一种 Web 服务,可以加快静态和动态 Web 内容的分发.https://aws.amazon.com/blogs/networking-and-content-delivery/deliver-your-apps-dynamic-content-使用-amazon-cloudfront-getting-started-template/
A64: 60 | B64: 一家游戏公司正在设计一个高可用性架构.该应用程序运行在修改后的 Linux 内核上,并且仅支持基于 UDP 的流量.该公司需要前端层来提供最佳的用户体验.该层必须具有低延迟,将流量路由到最近的边缘位置,并为进入应用程序端点提供静态 IP 地址.解决方案架构师应该如何满足这些要求? | C64: 配置 Amazon Route 53 以将请求转发到 Application Load Balancer.在 AWS Application Auto Scaling 中为应用程序使用 AWS Lambda. | D64: 配置 Amazon CloudFront 以将请求转发到网络负载均衡器.将 AWS Lambda 用于 AWS Application Auto Scaling 组中的应用程序. | E64: 配置 AWS Global Accelerator 以将请求转发到网络负载均衡器.为 EC2 Auto Scaling 组中的应用程序使用 Amazon EC2 实例. | F64: 配置 Amazon API Gateway 以将请求转发到应用程序负载均衡器.为 EC2 Auto Scaling 组中的应用程序使用 Amazon EC2 实例. | J64: C | K64: AWS Global Accelerator and Amazon CloudFront are separate services that use the AWS global network and its edge locations around the world. CloudFront improves performance for both cacheable content (such as images and videos) and dynamic content (such as API acceleration and dynamic site delivery). Global Accelerator improves performance for a wide range of applications over TCP or UDP by proxying packets at the edge to applications running in one or more AWS Regions. Global Accelerator is a good fit for non-HTTP use cases, such as gaming (UDP), loT (MQTT), or Voice over IP, as well as for HTTP use cases that specifically require static IP addresses or deterministic, fast regional failover. Both services integrate with AWS Shield for DDOS protection.AWS Global Accelerator和Amazon CloudFront是使用AWS全球网络及其在世界各地的边缘位置的独立服务。CloudFront提高了可缓存内容(如图像和视频)和动态内容(如API加速和动态站点交付)的性能。Global Accelerator通过将边缘的数据包代理到一个或多个AWS区域中运行的应用程序,提高了TCP或UDP上广泛应用程序的性能。Global Accelerator非常适合非HTTP用例,如游戏(UDP)、loT (MQTT) 或IP语音,以及特别需要静态IP地址或确定性快速区域故障切换的HTTP用例。这两种服务都与AWS Shield集成以提供DDoS保护。 | N64: AWS Global Accelerator and Amazon CloudFront are separate services that use the AWS global network and its edge locations around the world. CloudFront improves performance for both cacheable content (such as images and videos) and dynamic content (such as API acceleration and dynamic site delivery). Global Accelerator improves performance for a wide range of applications over TCP or UDP by proxying packets at the edge to applications running in one or more AWS Regions. Global Accelerator is a good fit for non-HTTP use cases, such as gaming (UDP), loT (MQTT), or Voice over IP, as well as for HTTP use cases that specifically require static IP addresses or deterministic, fast regional failover. Both services integrate with AWS Shield for DDOS protection.AWS Global Accelerator和Amazon CloudFront是使用AWS全球网络及其在世界各地的边缘位置的独立服务。CloudFront提高了可缓存内容(如图像和视频)和动态内容(如API加速和动态站点交付)的性能。Global Accelerator通过将边缘的数据包代理到一个或多个AWS区域中运行的应用程序,提高了TCP或UDP上广泛应用程序的性能。Global Accelerator非常适合非HTTP用例,如游戏(UDP)、loT (MQTT) 或IP语音,以及特别需要静态IP地址或确定性快速区域故障切换的HTTP用例。这两种服务都与AWS Shield集成以提供DDoS保护。
A65: 61 | B65: 一家公司希望将其现有的本地单体应用程序迁移到AWS.该公司希望保留尽可能多的前端代码和后端代码.但是,该公司希望将应用程序分解为更小的应用程序.不同的团队将管理每个应用程序.公司需要一个高度可扩展的解决方案,以最大限度地减少运营开销.哪种解决方案可以满足这些要求? | C65: 在 AWS Lambda 上托管应用程序将应用程序与 Amazon API Gateway 集成. | D65: 使用 AWS Amplify 托管应用程序.将应用程序连接到与 AWS Lambda 集成的 Amazon API Gateway API. | E65: 在 Amazon EC2 实例上托管应用程序.使用 Auto Scaling 组中的 EC2 实例作为目标设置应用程序负载均衡器, | F65: 在 Amazon Elastic Container Service (Amazon ECS)上托管应用程序设置以 Amazon ECS 为目标的应用程序负载均衡器. | J65: D | K65: https://aws.amazon.com/blogs/compute/microservice-delivery-with-amazon-ecs-and-application-load-balancers/ | N65: https://aws.amazon.com/blogs/compute/microservice-delivery-with-amazon-ecs-and-application-load-balancers/
A66: 62 | B66: 一家公司最近开始使用 Amazon Aurora 作为其全球电子商务应用程序的数据存储.当运行大型报告时,开发人员报告电子商务应用程序性能不佳 在查看 Amazon CloudWatch 中的指标后,解决方案架构师发现 ReadIOPS 和 CPUUtilization 指标月度报告运行时出现峰值.什么是最具成本效益的解决方案? | C66: 将月度报告迁移到 Amazon Redshift. | D66: 将月度报告迁移到 Aurora 副本 | E66: 将 Aurora 数据库迁移到更大的实例类 | F66: 增加 Aurora 实例的预置 IOPS | J66: B | K66: https://docs.aws.amazon.com/AmazonRDS/latest/AuroraUserGuide/Aurora.Replication.html#Aurora.Replication.Replicas Aurora 副本有两个主要用途.您可以向它们发出查询以扩展读取操作您的应用程序,您通常通过连接到集群的读取器终端节点来执行此操作.这样,Aurora 可以将只读连接的负载分散到集群中尽可能多的 Aurora 副本中.Aurora 副本还有助于提高可用性.如果集群中的写入器实例不可用,Aurora 会自动提升读取器实例之一以取代其作为新写入器的位置. https://docs.aws.amazon.com/AmazonRDS/latest/AuroraUserGuide/Aurora.Overview.html | N66: https://docs.aws.amazon.com/AmazonRDS/latest/AuroraUserGuide/Aurora.Replication.html#Aurora.Replication.Replicas Aurora 副本有两个主要用途.您可以向它们发出查询以扩展读取操作您的应用程序,您通常通过连接到集群的读取器终端节点来执行此操作.这样,Aurora 可以将只读连接的负载分散到集群中尽可能多的 Aurora 副本中.Aurora 副本还有助于提高可用性.如果集群中的写入器实例不可用,Aurora 会自动提升读取器实例之一以取代其作为新写入器的位置. https://docs.aws.amazon.com/AmazonRDS/latest/AuroraUserGuide/Aurora.Overview.html
A67: 63 | B67: 一家公司在单个 Amazon EC2 按需实例上托管网站分析应用程序.分析软件用 PHP 编写并使用 MySQL 数据库.分析软件.提供 PHP的 Web 服务器和数据库服务器都托管在 EC2 实例上,应用程序在繁忙时间显示出性能下降的迹象,并出现 5xx 错误.公司需要无缝扩展应用程序.哪种解决方案最经济高效地满足这些要求? | C67: 将数据库迁移到 Amazon RDS for MySQL 数据库实例.创建 Web 应用程序的 AMI.使用 AMI 启动第二个 EC2 按需实例.使用应用程序负载均衡器将负载分配到每个 EC2 实例. | D67: 将数据库迁移到 Amazon RDS for MySQL 数据库实例.创建 Web 应用程序的 AMI.使用 AMI 启动第二个 EC2 按需实例.使用 Amazon Route 53 加权路由在两个 EC2 实例之间分配负载. | E67: 将数据库迁移到 Amazon Aurora MySQL 数据库实例.创建 AWS Lambda 函数以停止 EC2 实例并更改实例类型.创建 Amazon CloudWatch 警报以在 CPU 利用率超过 75% 时调用 Lambda 函数. | F67: 将数据库迁移到 Amazon Aurora MySQL 数据库实例.创建 Web 应用程序的 AMI.将 AMI 应用到启动模板.使用启动模板创建 Auto Scaling 组.配置启动模板以使用 Spot 队列.附加一个应用程序负载均衡器到 Auto Scaling 组. | J67: D | K67: Agreed with D as Spot Fleet can leverage both spot+on-demand instances, it should be the most cost-effective. | N67: Agreed with D as Spot Fleet can leverage both spot+on-demand instances, it should be the most cost-effective.
A68: 64 | B68: 一家公司在应用程序负载均衡器后面的一组 Amazon EC2 按需实例上运行无状态 Web 应用程序.该应用程序在每个工作日 8 小时內使用量很大.应用程序在一夜之间的使用量适中且稳定周末的使用率很低.公司希望在不影响应用程序可用性的情况下最大限度地降低其EC2 成本.哪种解决方案可以满足这些要求? | C68: 对整个工作负载使用 Spot 实例. | D68: 将预留实例用于基线使用水平.将 Spot 实例用于应用程序所需的任何额外容量, | E68: 将按需实例用于基线使用水平.将 Spot 实例用于应用程序需要的任何额外容量, | F68: 将专用实例用于基线使用水平.将按需实例用于应用程序所需的任何额外容量. | J68: B | K68: They are currently using On Demand instances, so option C is out. A uses Spot instances which is not recommended for PROD and D uses Dedicated instances which are expensive. So option B should be the one. | N68: They are currently using On Demand instances, so option C is out. A uses Spot instances which is not recommended for PROD and D uses Dedicated instances which are expensive. So option B should be the one.
A69: 65 | B69: 某公司需要为一个关键应用保留应用日志文件10年,应用团队定期访问过去一个月的日志进行故障排除,但很少访问超过1个月的日志.应用生成超过10 TB的日志每月.哪种存储选项最经济高效地满足这些要求? | C69: 将 log 存储在 Amazon S3 中.使用 AWS Backup 将超过 1个月的日志移动到 S3 Glacier Deep Archive. | D69: 将日志存储在 Amazon S3 中.使用 S3 生命周期策略将超过1个月的日志移动到 S3 Glacier Deep Archive. | E69: 将日志存储在 Amazon CloudWatch Logs 中.使用 AWS Backup 将超过1个月的日志移动到 S3 Glacier Deep Archive. | F69: 将日志存储在 Amazon CloudWatch Logs 中.使用 Amazon S3 生命周期策略将超过1个月的日志移动到 S3 Glacier Deep Archive. | J69: B | K69: 您需要 S3 才能在一个月后存档日志.无法使用 CloudWatch Logs 来做到这一点. | N69: 您需要 S3 才能在一个月后存档日志.无法使用 CloudWatch Logs 来做到这一点.
A70: 66 | B70: 一家公司的数据摄取工作流程包括以下组件 :- 接收有关新数据交付通知的 Amazon Simple Notation Service (Amazon SNS) 主题 .处理和存储数据的 AWS Lambda 函数 摄取工作流程偶尔会失败因为网络连接问题.当任期发生时,除非公司手动重新运行作业,否则不会摄取相应的数据.解决方案架构师应该怎么做才能确保最终处理所有通知? | C70: 配置 Lambda 函数以跨多个可用区进行部署 | D70: 修改 Lambda 函数配置以增加函数的 CPU 和内存分配 | E70: 配置SNS主题的重试策略,增加重试次数和重试之间的等待时间 | F70: 将 Amazon Simple Queue Service (Amazon SQS) 队列配置为失败目标.修改 Lambda 函数以处理队列中的消息. | J70: D | K70: Option C could work but the max retries attempts is 23 days. After that messages are deleted. And you do not want that to happen! So, Option D. | N70: Option C could work but the max retries attempts is 23 days. After that messages are deleted. And you do not want that to happen! So, Option D.
A71: 67 | B71: 一家公司有一项产生事件数据的服务.该公司希望使用 AWS 在收到事件数据时对其进行处理.数据以特定顺序写入,在整个处理过程中必须保持该顺序,该公司希望实施一个解决方案最大限度地减少运营开销.解决方案架构师应该如何实现这一点? | C71: 创建一个 Amazon Simple Queue Service (Amazon SQS) FIFO 队列来保存消息.设置一个 AWS Lambda 函数来处理来自队列的消息. | D71: 创建一个 Amazon Simple Notification Service (Amazon SNS)主题以传递包含要处理的有效负载的通知.将 AWS Lambda 函数配置为订阅者. | E71: 创建一个 Amazon Simple Queue Service (Amazon SQS) 标准队列来保存消息.设置一个 AWS Lambda 函数来独立处理来自队列的消息. | F71: 创建一个 Amazon Simple Notification Service (Amazon SNS)主题以传递包含要处理的负载的通知.将 Amazon Simple QueueService (Amazon SQS)队列配置为订阅者. | J71: A | K71: 详细信息显示在以下网址:https://docs.aws.amazon.com/AWSSimpleQueueService/latest/SQSDeveloperGuide/FIFOqueues.html FIFO (先进先出)队列旨在增强之间的消息传递当操作和事件的顺序至关重要或不能容忍重复时的应用程序,可能使用FIFO 队列的情况示例包括:确保用户输入的命令以正确的顺序运行,显示通过以正确的顺序发送价格修改来获得正确的产品价格.防止学生在注册帐户之前注册课程. | N71: 详细信息显示在以下网址:https://docs.aws.amazon.com/AWSSimpleQueueService/latest/SQSDeveloperGuide/FIFOqueues.html FIFO (先进先出)队列旨在增强之间的消息传递当操作和事件的顺序至关重要或不能容忍重复时的应用程序,可能使用FIFO 队列的情况示例包括:确保用户输入的命令以正确的顺序运行,显示通过以正确的顺序发送价格修改来获得正确的产品价格.防止学生在注册帐户之前注册课程.
A72: 68 | B72: 一家公司正在将应用程序从本地服务器迁移到 Amazon EC2 实例.作为迁移设计要求的一部分,解决方案架构师必须实施基础设施指标警报.如果 CPU 利用率增加到超过50% 的时间很短,但是,如果 CPU 利用率增加到50%以上,同时磁盘上的读取 IOPS很高,公司需要尽快采取行动.解决方案架构师也必须降低误报.解决方案架构师应该怎么做才能满足这些要求? | C72: 尽可能创建 Amazon CloudWatch 复合警报. | D72: 创建 Amazon CloudWatch 控制面板以可视化指标并对问题做出快速反应. | E72: 创建 Amazon CloudWatch Synthetics 金丝雀以监控应用程序并发出警报. | F72: 尽可能创建具有多个指标阈值的单个 Amazon CloudWatch 指标警报. | J72: A | K72: 复合告警通过监控其他告警的状态来确定其状态.您可以 ** 使用复合警报来减少警报噪音 ** 例如,您可以创建一个复合警报,其中基础指标警报在满足特定条件时进入 ALARM.然后,您可以将复合警报设置为进入 ALARM,并在基础指标警报进入 ALARM 时向您发送通知,方法是配置基础指标警报从不采取行动.目前,复合告警可以采取以下动作: https://docs.aws.amazon.com/AmazonCloudWatch/latest/monitoring/Create_Composite_Alarm.html | N72: 复合告警通过监控其他告警的状态来确定其状态.您可以 ** 使用复合警报来减少警报噪音 ** 例如,您可以创建一个复合警报,其中基础指标警报在满足特定条件时进入 ALARM.然后,您可以将复合警报设置为进入 ALARM,并在基础指标警报进入 ALARM 时向您发送通知,方法是配置基础指标警报从不采取行动.目前,复合告警可以采取以下动作: https://docs.aws.amazon.com/AmazonCloudWatch/latest/monitoring/Create_Composite_Alarm.html
A73: 69 | B73: 某公司想将其本地数据中心迁移到AWS.根据公司的合规要求,该公司只能使用ap-northeast-3区域.公司管理员不允许将VPC连接到互联网.哪些解决方案会满足这些要求吗?(选择两个.) | C73: 使用 AWS Control Tower 实施数据驻留护栏以拒绝互联网访问并拒绝对除 ap-northeast-3 之外的所有 AWS 区域的访问. | D73: 使用 AWS WAF 中的规则来阻止互联网访问.在 AWS 账户设置中拒绝访问除 ap-northeast-3 之外的所有 AWS 区域. | E73: 使用 AWS Organizations 配置服务控制策略(SCPS),以防止 VPC 获得 Internet 访问权限.拒绝访问除 ap-northeast-3 之外的所有 AWS 区域. | F73: 为每个 VPC 中的网络 ACL 创建出站规则以拒绝来自 0.0.0.0/0 的所有流量.为每个用户创建 IAM 策略以防止使用除 ap-northeast3 之外的任何 AWS 区域. | G73: 使用 AWS Config 激活托管规则以检测和提醒互联网网关,并检测和提醒部署在 ap-northeast-3 之外的新资源. | J73: A,C | K73: https://docs.aws.amazon.com/organizations/latest/userguide/orgs_manage_policies_scps_examples_vpc.html#example_vpc_2 | N73: https://docs.aws.amazon.com/organizations/latest/userguide/orgs_manage_policies_scps_examples_vpc.html#example_vpc_2
A74: 70 | B74: 一家公司使用三层 Web 应用程序为新员工提供培训.该应用程序每天仅访问 12 小时.该公司正在使用 Amazon RDS for MySQL 数据库实例来存储信息并希望最大限度地降低成本.什么解决方案架构师应该做些什么来满足这些要求? | C74: 为 AWS Systems Manager Session Manager 配置 IAM 策略.为策略创建 IAM 角色.更新角色的信任关系.为数据库实例设置自动后动和停止. | D74: 创建一个 Amazon Elasticache for Redis 缓存集群,使用户能够在数据库实例停止时访问缓存中的数据.在数据库实例启动后使缓存失效. | E74: 启动一个 Amazon EC2 实例.创建一个授予对 Amazon RDS 访问权限的IAM 角色.将该角色附加到 EC2 实例.配置一个 cron 作业以按所需的计划启动和停止 EC2 实例. | F74: 创建 AWS Lambda 函数以启动和停止数据库实例.创建 Amazon EventBridge (Amazon CloudWatch Events)计划规则以调用Lambda 函数.将 Lambda 函数配置为规则的事件目标 | J74: D | K74: https://aws.amazon.com/blogs/database/schedule-amazon-rds-stop-and-start-using-aws-lambda/.It is option D. Option A could have been applicable had it been AWS Systems Manager State Manager & not AWS Systems Manager Session Manager | N74: https://aws.amazon.com/blogs/database/schedule-amazon-rds-stop-and-start-using-aws-lambda/.It is option D. Option A could have been applicable had it been AWS Systems Manager State Manager & not AWS Systems Manager Session Manager
A75: 71 | B75: 一家公司销售由流行歌曲剪辑创建的铃声,包含铃声的文件存储在 Amazon S3 Standard 中,大小至少为 128 KB.该公司拥有数百万个文件,但对于超过90天的铃声很少下载.公司需要节省存储费用,同时让用户可以随时访问最常访问的文件.公司应采取哪些措施以最具成本效益的方式满足这些要求? | C75: 为对象的初始存储层配置 S3 标准-不频繁访问 (S3 标准-IA) 存储。 | D75: 将文件移动到 S3 智能分层并配置它以在 90 天后将对象移动到较低的存储层。 | E75: 配置 S3 清单以管理对象并在 90 天后将它们移至 S3 标准-不频繁访问 (S3 Standard-IA)。 | F75: 实施2 生命周期答案在90 天后将对象从 2 标准移动到3 标准,不断敏访问(2 Standard-14) | J75: B | K75: B/D seems possible answer. But, I'll go with "B". In the following table, S3 Intelligent-Tiering seems not so expansive than S3 Standard. https://aws.amazon.com/s3/pricing/?nc1=h_ls And, in the question "128KB" size is talking about S3 Intelligent-Tiering stuff. | N75: B/D seems possible answer. But, I'll go with "B". In the following table, S3 Intelligent-Tiering seems not so expansive than S3 Standard. https://aws.amazon.com/s3/pricing/?nc1=h_ls And, in the question "128KB" size is talking about S3 Intelligent-Tiering stuff.
A76: 72 | B76: 公司需要将医学试验的结果保存到 Amazon S3 存储库.该存储库必须允许少数科学家添加新文件,并且必须限制所有其他用户只读访问.任何用户都不能修改或删除存储库中的任何文件.公司必须将存储库中的每个文件在其创建日期后至少保留1年.哪种解决方案将满足这些要求? | C76: 在治理模式下使用S3 Object Lock,合法持有1年 | D76: 在合规模式下使用 S3 对象锁定,保留期为365天. | E76: 使用 IAM 角色限制所有用户删除或更改 S3 存储桶中的对象使用 S3 存储桶策略仅允许 IAM 角色 | F76: 配置 S3 存储桶以在每次添加对象时调用 AWS Lambda 函数 | J76: B | K76: Reason: Compliance Mode. The key difference between Compliance Mode and Governance Mode is that there are NO users that can override the retention periods set or delete an object, and that also includes your AWS root account which has the highest privileges. | N76: Reason: Compliance Mode. The key difference between Compliance Mode and Governance Mode is that there are NO users that can override the retention periods set or delete an object, and that also includes your AWS root account which has the highest privileges.
A77: 73 | B77: 一家大型媒体公司在 AWS 上托管一个 Web 应用程序.该公司希望开始缓存机密媒体文件,以便世界各地的用户可以可靠地访问这些文件.内容存储在 Amazon S3 存储桶中.该公司必须交付快速获取内容,无论请求来自何处.哪种解决方案可以满足这些要求? | C77: 使用 AWS DataSync 将 53 仔储连接到 Web 应用程序. | D77: 部署 AWS Global Accelerator 以将 S3 存储桶连接到 Web 应用程序. | E77: 部署 Amazon CloudFront 以将 S3 存储桶连接到 CloudFront 边缘服务器. | F77: 使用 Amazon Simple Queue Service (Amazon SQS) 将 S3 存储桶连接到 Web 应用程序. | J77: C | K77: CloudFront 使用本地缓存提供响应,AWS 全球加速器代理请求并一直连接到应用程序以获得响应.https://docs.aws.amazon.com/AmazonCloudFront/latest/DeveloperGuide/private-content-restricting-access-to-s3.html#privatecontent-granting-permissions-to-oai | N77: CloudFront 使用本地缓存提供响应,AWS 全球加速器代理请求并一直连接到应用程序以获得响应.https://docs.aws.amazon.com/AmazonCloudFront/latest/DeveloperGuide/private-content-restricting-access-to-s3.html#privatecontent-granting-permissions-to-oai
A78: 74 | B78: 一家公司生产来自不同数据库的批量数据.该公司还从网络传感器和应用程序 API 生成实时流数据.该公司需要将所有数据整合到一个地方进行业务分析,该公司需要处理传入的数据然后将数据暂存到不同的 Amazon S3 存储桶中.团队稍后将运行一次性查询并将数据导入商业智能工具以显示关键绩效指标(KPI).哪种步骤组合将以最少的运营开销满足这些要求?(选择两个.) | C78: 使用 Amazon Athena 敌人一次性查询.使用 Amazon QuickSight 为 KPI 创建控制面板. | D78: 使用 Amazon Kinesis Data Analytics 进行一次性查询.使用 Amazon QuickSight 为 KPI 创建控制面板. | E78: 创建自定义 AWS Lambda 函数以将单个记录从 me 数据库移动到 Amazon Redshift 集群. | F78: 使用 AWS Glue 提取转换和 toad (ETL)作业将数据转换为 JSON 格式.将数据加载到多个 Amazon OpenSearch Service (Amazon Elasticsearch Service) 集群中. | G78: 使用 AWS Lake Formation 中的蓝图来识别可以摄取到数据湖中的数据.使用 AWS Glue 抓取源提取数据并将数据以 Apache Parquet 格式加载到 Amazon S3. | J78: A,E | K78: yeah AE makes sense, only E is working with S3 here and questions wants them to be in S3 | N78: yeah AE makes sense, only E is working with S3 here and questions wants them to be in S3
A79: 75 | B79: 一家游戏公司有一个显示分数的Web 应用程序.该应用程序在应用程序负载均衡器后面的 Amazon EC2 实例上运行.该应用程序将数据存储在 Amazon RDS for MySQL 数据库中.用户开始经历长时间的延迟和中断通过数据库读取性能.公司希望改善用户体验,同时尽量减少对应用程序架构的更改.解决方案架构师应该如何满足这些要求? | C79: 在数据库前使用 Amazon ElastiCache. | D79: 在应用程序和数据库之间使用 RDS Proxy. | E79: 将应用程序从 EC2 实例迁移到 AWS Lambda. | F79: 将数据库从 Amazon RDS for MySQL 迁移到 Amazon DynamoDB ssone | J79: A
A80: 76 | B80: 企业的备份数据总计 700 TB,并保存在其数据中心的网络附加存储(NAS)中.这些备份数据必须可供偶尔的监管查询使用,并保存七年.组织已选择将其备份数据从其本地数据中心迁移到 Amazon Web Services (AWS).必须在一个月内完成迁移,公司的公共互联网连接提供 500 Mbps 的专用数据传输容量.应该解决方案架构师如何确保以尽可能低的成本迁移和存储数据? | C80: 订购 AWS Snowball 设备以传输数据.使用生命周期策略将文件转换到 Amazon S3 Glacier Deep Archive. | D80: 在数据中心和 Amazon VPC 之间部署 VPN 连接.使用 AWS CLI 将数据从本地复制到 Amazon S3 Glacier. | E80: 提供 500 Mbps AWS Direct Connect 连接并将数据传输到 Amazon S3.使用生命周期策略将文件转换到 Amazon S3 Glacier Deep Archive. | F80: 使用 AWS DataSync 传输数据并在本地部署 DataSync 代理.使用 DataSync 任务将文件从本地 NAS 存储复制到 Amazon S3 Glacier. | J80: A
A81: 77 | B81: 如果公司的主网站不可用,公司希望将其用户定向到备份静态错误页面.主网站的 DNS 记录托管在 Amazon Route 53 中.域指向应用程序负载均衡器(ALB).公司需要一种能够最大限度地减少变更和基础设施开销的解决方案.哪种解决方案可以满足这些要求? | C81: 更新 Route 53 记录以使用延迟路由策略.将托管在 Amazon S3 存储桶中的静态错误页面添加到记录中,以便将流量发送到响应速度最快的终端节点. | D81: 设置 Route 53 主动-被动故障转移配置.当 Route 53 运行状况检查确定 ALB 终端节点运行状况不佳时,将流量定向到托管在 Amazon S3 存储桶中的静态错误页面, | E81: 使用 ALB 和托管静态错误页面作为终端节点的 Amazon EC2 实例设置 Route 53 主动-主动配置.配置 Route 53 以仅在 ALB 的运行状况检查失败时向实例发送请求. | F81: 更新 Route 53 记录以使用多值应答路由策略.创建运行状况检查.如果运行状况检查通过,则将流量引导至网站.如果运行状况检查未通过,则将流量引导至托管在 Amazon S3 中的静态错误页面经过. | J81: B
A82: 78 | B82: 一家公司招聘了一位新的云工程师,他不应该有权访问 CompanyConfidential Amazon S3 存储桶.该云工程师必须对名为 Admin Tools 的 S3 存储桶具有读写权限.哪种 IAM 策略可以满足这些标准? | J82: SKIP | K82: https://docs.amazonaws.cn/en_us/IAM/latest/UserGuide/reference_policies_examples_s3_rw-bucket.html | N82: https://docs.amazonaws.cn/en_us/IAM/latest/UserGuide/reference_policies_examples_s3_rw-bucket.html
A83: 79 | B83: 一名新员工加入公司担任部署工程师.部署工程师将使用 AWS CloudFormation 模板创建多个 AWS 资源.解决方案架构师希望部署工程师在遵循最小权限原则的同时执行工作活动.哪些步骤解决方案架构师应该联合起来实现这个目标吗?(选择两个.) | C83: 让部署工程师使用 AWS 账户屋顶用户凭证来执行 AWS CloudFormation 堆栈操作. | D83: 为部署工程师创建一个新的IAM 用户并将IAM 用户添加到附加了 PowerUsers IAM 策略的组中. | E83: 为部署工程师创建一个新的 IAM 用户并将 IAM用户添加到附加了管理/访问 IAM 策略的组. | F83: 为部署工程师创建一个新的 IAM 用户,并将IAM用户添加到具有仅允许 AWS CloudFormation 操作的 IAM 策略的组. | G83: 为部署工程师创建一个 IAM角色,以使用 Dial IAM 角色明确定义特定于 AWS CloudFormation 堆栈和启动堆栈的权限. | J83: D,E | K83: Option A talks about using root user credentials which don't make any sense.Question states about least privileges' which is not the case in B and C.https://docs.aws.amazon.com/IAM/latest/UserGuide/id_roles.html https://docs.aws.amazon.com/IAM/latest/UserGuide/id_users.html | N83: Option A talks about using root user credentials which don't make any sense.Question states about least privileges' which is not the case in B and C.https://docs.aws.amazon.com/IAM/latest/UserGuide/id_roles.html https://docs.aws.amazon.com/IAM/latest/UserGuide/id_users.html
A84: 80 | B84: 一家公司在 AWS 上运行高性能计算(HPC)工作负载.工作负载需要低延迟网络性能和高网络吞吐量以及紧密耦合的节点到节点通信.Amazon EC2 实例的大小适合计算和存储容量,并使用默认选项启动.解决方案架构师应该提出什么建议来提高工作负载的性能? | C84: 在启动 Amazon EC2 实例时选择一个集群置放群组. | D84: 在启动 Amazon EC2 实例时选择专用实例租赁. | E84: 在启动 Amazon EC2 实例时选择 Elastic Inference 加速器. | F84: 在启动 Amazon EC2 实例时选择所需的容量预留. | J84: A | K84: https://docs.aws.amazon.com/AWSCloudFormation/latest/UserGuide/aws-resource-ec2-placementgroup.html 集群置放群组是单个可用区内的实例的逻辑分组,受益于低网络延迟,高网络吞吐量. | N84: https://docs.aws.amazon.com/AWSCloudFormation/latest/UserGuide/aws-resource-ec2-placementgroup.html 集群置放群组是单个可用区内的实例的逻辑分组,受益于低网络延迟,高网络吞吐量.
A85: 81 | B85: 一家公司希望使用 AWS 云使现有应用程序具有高可用性和弹性.该应用程序的当前版本驻留在公司的数据中心.该应用程序最近在数据库服务器因意外断电而崩溃后出现数据丢失.公司需要一个避免任何单点故障的解决方案.该解决方案必须使应用程序能够扩展以满足用户需求.哪种解决方案可以满足这些要求? | C85: 使用跨多个可用区的 Auto Scaling 组中的 Amazon EC2 实例部署应用程序服务器.在多可用区配置中使用 Amazon RDS 数据库实例. | D85: 在单个可用区的 Auto Scaling 组中使用 Amazon EC2 实例部署应用程序服务器.在 EC2 实例上部署数据库.启用 EC2 Auto Recovery. | E85: 使用跨多个可用区的 Auto Scaling 组中的 Amazon EC2 实例部署应用程序服务器.在单个可用区中使用具有只读副本的 Amazon RDS 数据库实例.如果主数据库实例是主数据库实例,则提升只读副本以替换主数据库实例数据库实例失败. | F85: 使用 Auto Scaling 组中的 Amazon EC2 实例跨多个可用区部署应用程序服务器.在 EC2 实例上跨多个可用区部署主数据库服务器和辅助数据库服务器.使用 Amazon Elastic Block Store (Amazon EBS) Multi-Attach 创建实例之间的共享存储. | J85: A | K85: 正确答案是A.通过在多个可用性区域的“自动缩放”组中使用Amazon EC2实例来部署应用程序服务器。在Multi-AZ配置中使用Amazon RDS DB实例。为了使现有应用程序具有高可用性和弹性,同时避免任何单点故障,并使应用程序能够扩展以满足用户需求,最佳解决方案是在多个可用区的自动扩展组中使用Amazon EC2实例部署应用程序服务器,并在多AZ配置中使用Amazon RDS DB实例。通过在Multi-AZ配置中使用Amazon RDS DB实例,可以在多个可用区之间自动复制数据库,确保数据库具有高可用性,并能够承受单个可用区的故障。这提供了容错性并避免了任何单点故障。 | N85: 正确答案是A.通过在多个可用性区域的“自动缩放”组中使用Amazon EC2实例来部署应用程序服务器。在Multi-AZ配置中使用Amazon RDS DB实例。为了使现有应用程序具有高可用性和弹性,同时避免任何单点故障,并使应用程序能够扩展以满足用户需求,最佳解决方案是在多个可用区的自动扩展组中使用Amazon EC2实例部署应用程序服务器,并在多AZ配置中使用Amazon RDS DB实例。通过在Multi-AZ配置中使用Amazon RDS DB实例,可以在多个可用区之间自动复制数据库,确保数据库具有高可用性,并能够承受单个可用区的故障。这提供了容错性并避免了任何单点故障。
A86: 82 | B86: 一家公司想要在作为 AWS 云中 Auto Scaling 组一部分的 Amazon EC2 实例上运行游戏应用程序.该应用程序将使用 UDP 数据包传输数据.该公司希望确保该应用程序可以横向扩展和横向扩展随着流量的增加和减少.解决方案架构师应该做什么来满足这些要求? | C86: 将网络负载均衡器附加到 Auto Scaling 组 | D86: 将 Application Load Balancer 附加到 Auto Scaling 组. | E86: 使用加权策略部署 Amazon Route 53 记录集以适当地路由流量 | F86: 部署一个配置了端口转发的 NAT 实例到 Auto Scaling 组中的 EC2 实例. | J86: A
A87: 83 | B87: 一家公司正在为托管在AWS云中的游戏应用程序设计共享存储解决方案。该公司需要能够使用SMB客户端访问数据。必须对解决方案进行全面管理。哪种AWS解决方案符合这些要求? | C87: 创建一个AWS数据同步任务,该任务将数据共享为可挂载的文件系统。将文件系统装载到应用程序服务器。 | D87: 创建一个AmazonEC2 Windows实例。在实例上安装并配置Windows文件共享角色。将应用程序服务器连接到文件共享。 | E87: 为Windows文件服务器创建一个Amazon FSx文件系统。将文件系统连接到原始服务器。将应用程序服务器连接到文件系统。 | F87: 创建一个AmazonS3存储桶。为应用程序分配IAM角色以授予对S3存储桶的访问权限。将S3存储桶安装到应用程序服务器。 | J87: C | K87: Amazon FSx for Windows File Server提供了一个完全管理的本机Windows文件系统,可以使用行业标准SMB协议进行访问。这允许像游戏应用程序这样的Windows客户端直接访问文件数据?FSx for Windows File Server可处理耗时的文件系统管理任务,如资源调配、设置、维护、文件共享管理、备份、安全和软件修补,从而减少操作开销?FSx for Windows File Server支持对性能敏感的工作负载所需的高文件系统吞吐量、IOPS和一致的低延迟。这使其适用于游戏应用程序?文件系统可以直接连接到EC2实例,为游戏服务器提供高性能的共享存储解决方案。选项a-DataSync用于数据传输,而不是提供共享文件系统。它无法安装或直接访问。选项B-自我管理的EC2文件共享需要手动安装、配置和维护Windows文件系统和共享。这需要大量的运营开销。选项D-AmazonS3是对象存储,而不是本机文件系统。S3中的数据需要转换/格式化以提供文件共享访问,这增加了复杂性。S3不能直接安装或提供FSx的性能。 | N87: Amazon FSx for Windows File Server提供了一个完全管理的本机Windows文件系统,可以使用行业标准SMB协议进行访问。这允许像游戏应用程序这样的Windows客户端直接访问文件数据?FSx for Windows File Server可处理耗时的文件系统管理任务,如资源调配、设置、维护、文件共享管理、备份、安全和软件修补,从而减少操作开销?FSx for Windows File Server支持对性能敏感的工作负载所需的高文件系统吞吐量、IOPS和一致的低延迟。这使其适用于游戏应用程序?文件系统可以直接连接到EC2实例,为游戏服务器提供高性能的共享存储解决方案。选项a-DataSync用于数据传输,而不是提供共享文件系统。它无法安装或直接访问。选项B-自我管理的EC2文件共享需要手动安装、配置和维护Windows文件系统和共享。这需要大量的运营开销。选项D-AmazonS3是对象存储,而不是本机文件系统。S3中的数据需要转换/格式化以提供文件共享访问,这增加了复杂性。S3不能直接安装或提供FSx的性能。
A88: 84 | B88: 一家公司在 Amazon EC2 实例和 Amazon RDS 上托管一个两层应用程序.应用程序的需求因一天中的时间而异.下班后和周末负载最小.EC2 实例在 EC2 Auto Scaling 组中运行最少配置两个实例,最多配置五个实例,应用程序必须始终可用,但公司关心整体成本.哪种解决方案最经济高效地满足可用性要求? | C88: 使用所有 EC2 Spot 实例.在不使用时停止 RDS 数据库. | D88: 购买 EC2 实例节省计划以涵盖五个 EC2 实例.购买 RDS 预留数据库实例 | E88: 购买两个 EC2 预留实例.根据需要使用最多三个额外的 EC2 Spot 实例.在不使用时停止 RDS 数据库. | F88: 购买 EC2 实例节省计划以涵盖两个 EC2 实例.根据需要使用最多三个额外的 EC2 按需实例.购买 RDS 预留数据库实例. | J88: D
A89: 85 | B89: 一家公司有一个电子商务结账工作流程,该工作流程将订单写入数据库并调用服务来处理付款.用户在结账过程中遇到超时,当用户重新提交结账表单时,会为相同的需求创建多个唯一订单事务.解决方案架构师应如何重构此工作流程以防止创建多个订单? | C89: 配置 Web 应用程序以向 Amazon Kinesis Data Firehose 发送订单消息.设置支付服务以从 Kinesis Data Firehose 检索消息并处理订单. | D89: 在 AWS CloudTrail 中创建规则,根据记录的应用程序路径请求调用 AWS Lambda 函数.使用 Lambda 查询数据库,调用支付服务,并传入订单信息. | E89: 将订单存储在数据库中.向 Amazon Simple Notification Service (Amazon SNS)发送包含订单号的消息.将支付服务设置为轮询Amazon SNS.检索消息并处理订单. | F89: 将订单存储在数据库中,将包含订单号的消息发送到 Amazon Simple Queue Service (Amazon SQS) FIFO 队列.设置支付服务以检索消息并处理订单.从队列中删除消息. | J89: D | K89: This approach ensures that the order creation and payment processing steps are separate and atomic. By sending the order information to an SQS FIFO queue, the payment service can process the order one at a time and in the order they were received. If the payment service is unable to process an order, it can be retried later, preventing the creation of multiple orders. The deletion of the message from the queue after it is processed will prevent the same message from being processed multiple times. It's worth noting that FIFO queues guarantee that messages are processed in the order they are received, and prevent duplicates.这种方法确保了订单创建和支付处理步骤是独立的和原子的。通过将订单信息发送到SQS FIFO队列,支付服务可以按照收到订单的顺序一次处理一个订单。如果支付服务无法处理订单,可以稍后重试,以防止创建多个订单。处理完消息后从队列中删除消息将防止同一消息被多次处理。值得注意的是,FIFO队列保证消息按照接收顺序进行处理,并防止重复。 | N89: This approach ensures that the order creation and payment processing steps are separate and atomic. By sending the order information to an SQS FIFO queue, the payment service can process the order one at a time and in the order they were received. If the payment service is unable to process an order, it can be retried later, preventing the creation of multiple orders. The deletion of the message from the queue after it is processed will prevent the same message from being processed multiple times. It's worth noting that FIFO queues guarantee that messages are processed in the order they are received, and prevent duplicates.这种方法确保了订单创建和支付处理步骤是独立的和原子的。通过将订单信息发送到SQS FIFO队列,支付服务可以按照收到订单的顺序一次处理一个订单。如果支付服务无法处理订单,可以稍后重试,以防止创建多个订单。处理完消息后从队列中删除消息将防止同一消息被多次处理。值得注意的是,FIFO队列保证消息按照接收顺序进行处理,并防止重复。
A90: 86 | B90: 一家公司正计划构建一个高性能计算(HPC)工作负载即服务解决方案,该解决方案托管在 AWS 上,一组 16个 AmazonEC2Ltnux实例需要尽可能低的节点到节点通信延迟.这些实例还需要一个用于高性能存储的共享块设备卷.哪种解决方案可以满足这些要求? | C90: 使用集群置放群组.使用 Amazon EBS Multi-Attach 将单个预置 IOPS SSD Amazon Elastic Block Store (Amazon EBS) 卷附加到所有实例. | D90: 使用集群放置组。通过使用Amazon Elastic file System (Amazon EFS) 创建跨实例的共享文件系统。 | E90: 使用分区放置组。通过使用Amazon Elastic file System (Amazon EFS) 创建跨实例的共享文件系统。 | F90: 使用分散的置放群组.使用 Amazon EBS 多重连接将单个预置 IOPS SSD Amazon Elastic Block Store (Amazon EBS)卷附加到所有实例. | J90: A | K90: https://docs.aws.amazon.com/AWSEC2/latest/UserGuide/ebs-volumes-multi.html | N90: https://docs.aws.amazon.com/AWSEC2/latest/UserGuide/ebs-volumes-multi.html
A91: 87 | B91: 一家公司有一个事件驱动的应用程序,该应用程序每分钟调用 AWS Lambda 函数多达 800 次,运行时间各不相同.Lambda 函数访问存储在 Amazon Aurora MySQL OB 集群中的数据.公司注意到连接超时是用户活动增加 数据库没有显示过载的迹象.CPU.内存和磁盘访问指标都很低.哪种解决方案可以以最少的操作开销解决此问题? | C91: 调整 Aurora MySQL 节点的大小以处理更多连接.在 Lambda 函数中配置重试逻辑以尝试连接到数据库. | D91: 设置 Amazon Elasticache to Redls 以缓存来自数据库的常用读取项目.配置 Lambda 函数以连接到 Elasticache 进行读取. | E91: 添加一个 Aurora 副本作为读取器节点.配置 Lambda 函数以连接到 OB集群的读取器端点,而不是连接到写入器端点. | F91: 使用 Amazon ROS 代理创建代理.将数据库集群设置为目标数据库.配置 Lambda 函数以连接到代理而不是数据库集群. | J91: D
A92: 88 | B92: 一家公司正在本地构建一个容器化应用程序,并决定将应用程序迁移到 AWS.部署 li后,该应用程序将很快拥有数千名用户.该公司不确定如何大规模管理容器的部署.该公司需要将容器化应用程序部署在一个高度可用的架构中,从而最大限度地减少运营开销.哪种解决方案可以满足这些要求? | C92: 将容器映像存储在 Amazon Elastic Container Registry (Amazon ECR) 存储库中.使用具有 AWS Fargate 启动类型的 Amazon Elastic Container Service (Amazon ECS) 集群来运行容器.使用目标跟踪根据需求自动扩展. | D92: 将容器映像存储在 Amazon Elastic Container Registry (Amazon ECR) 存储库中.使用具有 Amazon EC2 启动类型的 Amazon Elastic Container Service (Amazon ECS)集群来运行容器.使用目标跟踪根据需求自动扩展. | E92: 将容器映像存储在在 Amazon EC2 实例上运行的存储库中.在跨多个可用区的 EC2 实例上运行容器.监控 Amazon CloudWatch 中的平均 CPU 利用率.根据需要启动新的 EC2 实例. | F92: 创建包含容器映像的 Amazon EC2 Amazon 系统映像(AMI).在 Auto Scaling 组中跨多个可用区启动 EC2 实例.使用 Amazon CloudWatch 警报在超出平均 CPU 利用率阈值时横向扩展 EC2 实例. | J92: A
A93: 89 | B93: 某公司的应用程序出现性能问题.应用程序陈旧,需要在 Amazon EC2 实例上完成 m-memory 任务.该公司使用 AWS CloudFormation 部署基础设施并使用 M5 EC2 Instance 系列.随着流量的增加,应用程序性能下降.当用户尝试访问应用程序时,用户报告延迟.哪种解决方案将以最有效的操作方式解决这些问题? | C93: 将 EC2 实例替换为在 Auto Scaling 组中运行的 T3 EC2 实例.使用 AWS 管理控制台进行更改. | D93: 修改 CloudFormation 模板以在 Auto Scaling 组中运行 EC2 实例.在需要增加时手动增加 Auto Scaling 组的所需容量和最大容量. | E93: 修改 CloudFormation 模板.将 EC2 实例替换为 R5 EC2 实例.使用 Amazon CloudWatch 内置 EC2 内存指标来跟踪应用程序性能以进行未来容量规划. | F93: 修改 CloudFormation 模板.将 EC2 实例替换为 R5 EC2 实例.在 EC2 实例上部署 Amazon CloudWatch 代理,以生成自定义应用程序延迟指标以用于未来的容量规划. | J93: D | K93: EC2 do not provide by default memory metrics to CloudWatch and require the CloudWatch Agent to be installed on the monitored instances : https://aws.amazon.com/premiumsupport/knowledge-center/cloudwatch-memory-metrics-ec2/ | N93: EC2 do not provide by default memory metrics to CloudWatch and require the CloudWatch Agent to be installed on the monitored instances : https://aws.amazon.com/premiumsupport/knowledge-center/cloudwatch-memory-metrics-ec2/
A94: 90 | B94: 一家电子商务公司有一个使用 Amazon API Gateway 和 AWS Lambda 函数的订单处理应用程序.该应用程序将数据存储在 Amazon Aurora PostgreSQL 数据库中.在最近的一次销售活动中,客户订单突然激增.一些客户经历超时并且应用程序没有处理这些客户的订单.解决方案架构师确定由于大量打开的连接,数据库的CPU 利用率和内存利用率很高.解决方案架构师需要防止超时错误,同时进行对应用程序的更改最少.哪种解决方案可以满足这些要求? | C94: 为 Lambda 函数配置预置并发.将数据库修改为多个 AWS 区域中的全局数据库. | D94: 使用 Amazon RDS Proxy 为数据库创建代理.修改 Lambda 函数以使用 RDS Proxy 端点而不是数据库端点. | E94: 为不同 AWS 区域中的数据库创建只读副本.使用 API Gateway 中的查询字符串参数将流量路由到只读副本. | F94: 使用 AWS Database.Migration Service (AWS DMS)将数据从 Aurora PostgreSQL 迁移到 Amazon DynamoDB.修改 Lambda 函数以使用 OynamoDB 表. | J94: B | K94: When there is surge in traffic, no of concurrent lambda functions increased which results in more read and write connections on Aurora.当流量激增时,并发lambda函数的数量不会增加,这会导致Aurora上有更多的读写连接。 | N94: When there is surge in traffic, no of concurrent lambda functions increased which results in more read and write connections on Aurora.当流量激增时,并发lambda函数的数量不会增加,这会导致Aurora上有更多的读写连接。
A95: 91 | B95: 一家公司在应用程序负载均衡器后面的 Amazon EC2 实例上运行一个全球 Web 应用程序,该应用程序将数据存储在 Amazon Aurora 中.该公司需要创建一个灾难恢复解决方案,并且可以容忍长达30分钟的停机时间和潜在的数据丢失,当主要基础设施健康时,解决方案不需要处理负载,解决方案架构师应该做什么来满足这些要求? | C95: 使用所需的基础设施元素部署应用程序.使用 Amazon Route 53 配置主动-被动故障转移,在第二个 AWS 区域中创建 Aurora 副本. | D95: 在第二个 AWS 区域中托管应用程序的缩减部署.使用 Amazon Route 53 配置主动-主动故障转移,在第二个区域中创建 Aurora 副本. | E95: 在第二个 AWS 区域中复制主要基础设施.使用 Amazon Route 53 配置主动-主动故障转移.创建从最新快照恢复的 Aurora 数据库. | F95: 使用 AWS Backup 备份数据.使用备份在第二个 AWS 区域中创建所需的基础设施.使用 Amazon Route 53 配置主动-被动故障转移.在第二个区域中创建 Aurora 第二个主实例. | J95: A | K95: The answer is A. 1. 'The solution does not need to handle the load when the primary infrastructure is healthy.' -- >BCD out. Because we don't need the second infra over there. We can only use route53 active-passive failover to redirect traffic to other healthy resource when the primary resource are unhealthy. 2. We must use aurora read replica --- > perfect for rds failover. So C, D out.答案是A。“当主基础结构正常时,解决方案不需要处理负载。” -- >BCD out。因为我们不需要那里的第二个基础设施。当主资源不健康时,我们只能使用route53主动-被动故障转移将流量重定向到其他健康资源。2.我们必须使用极光读取副本 --- >非常适合rds故障切换。所以C,D出局。 | N95: The answer is A. 1. 'The solution does not need to handle the load when the primary infrastructure is healthy.' -- >BCD out. Because we don't need the second infra over there. We can only use route53 active-passive failover to redirect traffic to other healthy resource when the primary resource are unhealthy. 2. We must use aurora read replica --- > perfect for rds failover. So C, D out.答案是A。“当主基础结构正常时,解决方案不需要处理负载。” -- >BCD out。因为我们不需要那里的第二个基础设施。当主资源不健康时,我们只能使用route53主动-被动故障转移将流量重定向到其他健康资源。2.我们必须使用极光读取副本 --- >非常适合rds故障切换。所以C,D出局。
A96: 92 | B96: 一家公司想要衡量其最近的营销活动的有效性.该公司对销售数据的 csv 文件执行批处理,并将结果每小时存储一次 Amazon S3存储桶.S3 双 PB 的对象.该公司运行一个-在 Amazon Athena 中进行时间查询以确定哪些产品在特定区域的特定日期最受欢迎 查询有时会失败或需要比预期更长的时间才能完成.解决方案架构师应采取哪些措施来提高查询性能和可靠性?(选择两个.) | C96: 将 S3 对象大小减少到 126 MB 以下 | D96: 在 Amazon S3 中按日期和区域对数据进行分区 | E96: 将文件作为大型单个对象存储在 Amazon S3 中. | F96: 使用 Amazon Kinosis Data Analytics 将查询作为批处理操作的一部分运行 | G96: 使用 AWS duo 提取.转换和加载(ETL)流程将 csv 文件转换为 Apache Parquet 格式. | J96: C,E
A97: 93 | B97: 一家公司在 us-east-1 区域内的三个独立 VPC 中运行多个业务应用程序.这些应用程序必须能够在VPC 之间进行通信,这些应用程序还必须能够每天一致地将数百到千兆字节的数据发送到一个在单个本地数据中心中运行的对延迟敏感的应用程序.解决方案架构师需要设计一种网络连接解决方案,以最大限度地提高成本效益.哪种解决方案能够满足这些要求? | C97: 配置三个从数据中心到 AWS 的 AWS Site-to-Site VPN 连接.通过为每个 VPC 配置一个 VPN 连接来建立连接. | D97: 在每个 VPC 中启动第三方虚拟网络设备.在数据中心和每个虚拟设备之间建立 iPsec VPN 隧道. | E97: 在 us-east-1 中设置从数据中心到 Direct Connect 网关的三个 AWS Direct Connect 连接.通过将每个VPC 配置为使用其中一个 Direct Connect 连接来建立连接. | F97: 设置一个从数据中心到 AWS 的 AWS Direct Connect 连接.创建一个中转网关,并将每个 VPC 附加到中转网关.在 Direct Connect连接和中转网关之间建立连接. | J97: D | K97: https://docs.aws.amazon.com/whitepapers/latest/aws-vpc-connectivity-options/aws-direct-connect-aws-transit-gateway.html | N97: https://docs.aws.amazon.com/whitepapers/latest/aws-vpc-connectivity-options/aws-direct-connect-aws-transit-gateway.html
A98: 94 | B98: 在线照片应用程序让用户上传照片和执行图像编辑操作.该应用程序提供免费和付费两种服务 付费用户提交的照片在免费用户提交的照片之前被处理 照片上传到 Amazon S3 并且工作信息是发送到 Amazon SQS.解决方案架构师应该推荐哪种配置? | C98: 使用一个 SQS FIFO 队列.为付费照片分配更高的优先级,以便首先处理它们 | D98: 使用两个SQS FIFO队列:一个用于付费,一个用于免费.设置免费队列使用短轮询,付费队列使用长轮询 | E98: 使用两个 SQS 标准队列,一个用于付费,一个用于免费.配置 Amazon EC2 实例以优先轮询付费队列而不是免费队列. | F98: 使用一个 SQS 标准队列.将付费照片的可见性超时设置为零.配置 Amazon EC2 实例以优先考虑可见性设置,以便首先处理付费照片 | J98: C | K98: 优先级:使用单独的队列来提供工作的优先级. | N98: 优先级:使用单独的队列来提供工作的优先级.
A99: 95 | B99: 一家公司在 AWS 上托管其产品信息网页.现有解决方案在 Auto Scaling 组中的 Application Load Balancer 后面使用多个 AmazonEC2 实例.该网站还使用自定义 DNS 名称,并且仅使用专用 SSL 证书与 HTTPS 通信.该公司正在计划推出新产品,并希望确保来自世界各地的用户在新网站上获得最佳体验.解决方案架构师应该如何满足这些要求? | C99: 重新设计应用程序以使用 Amazon CloudFront | D99: 重新设计应用程序以使用 AWS Elastic Beanstalk | E99: 重新设计应用程序以使用网络负载均衡器. | F99: 重新设计应用程序以使用 Amazon S3 静态网站托管 | J99: A | K99: 因为 CloudFront 可以帮助为全球用户提供最佳体验.CloudFront 与 ALB 无缝集成,并提供使用自定义 DNS 和 SSL 证书的选项. | N99: 因为 CloudFront 可以帮助为全球用户提供最佳体验.CloudFront 与 ALB 无缝集成,并提供使用自定义 DNS 和 SSL 证书的选项.
A100: 96 | B100: 一家公司在本地存储了150 TB 的存档图像数据,需要在下个月内转移到 AWS 云.该公司当前的网络连接仅允许在夜间为此目的上传高达 100 Mbps 的数据.什么是移动这些数据并满足迁移截止日期的最具成本效益的机制? | C100: 使用 AWS Snowmobile 将数据传送到 AWS. | D100: 订购多个 AWS Snowball 设备以将数据发送到 AWS. | E100: 启用 Amazon S3 Transfer Acceleration 并安全上传数据. | F100: 创建 Amazon S3 VPC 终端节点并建立 VPN 以上传数据 | J100: B | K100: eg.6 hrs night 6 hrs*60min/hr=360 min 360 min*60 sec/min=21600 sec 100 Mbps*21600 s=2160000Mb or 2160 Gb or 2.1 TB can only be done 所以,对于 150 TB,我们可以使用 2 X Snowball Edge Storage Optimized devices.Snowball Edge Storage Optimized 设备的大小=80 TB Snowball Edge Compute Optimized 设备的大小=40 TB Snowcone 的大小=8 TB Snowmobile 的大小=100 PB(1 PB=1000 TB) Q:我应该如何在雪地摩托和雪球之间进行选择?要在单个位置迁移10PB 或更多的大型数据集,您应该使用Snowmobile.对于小于 10PB 或分布在多个位置的数据集,您应该使用 Snowball.此外,您应该评估网络主干中的可用带宽量.如果您有一个具有数百 Gb/s 备用吞吐量的高速骨干网,那么您可以使用 Snowmobile 一次性迁移所有大型数据集.如果您的骨干网带宽有限,您应该考虑使用多个 Snowball 来迁移数据逐渐地. | N100: eg.6 hrs night 6 hrs*60min/hr=360 min 360 min*60 sec/min=21600 sec 100 Mbps*21600 s=2160000Mb or 2160 Gb or 2.1 TB can only be done 所以,对于 150 TB,我们可以使用 2 X Snowball Edge Storage Optimized devices.Snowball Edge Storage Optimized 设备的大小=80 TB Snowball Edge Compute Optimized 设备的大小=40 TB Snowcone 的大小=8 TB Snowmobile 的大小=100 PB(1 PB=1000 TB) Q:我应该如何在雪地摩托和雪球之间进行选择?要在单个位置迁移10PB 或更多的大型数据集,您应该使用Snowmobile.对于小于 10PB 或分布在多个位置的数据集,您应该使用 Snowball.此外,您应该评估网络主干中的可用带宽量.如果您有一个具有数百 Gb/s 备用吞吐量的高速骨干网,那么您可以使用 Snowmobile 一次性迁移所有大型数据集.如果您的骨干网带宽有限,您应该考虑使用多个 Snowball 来迁移数据逐渐地.
A101: 97 | B101: 一家公司使用七个 Amazon EC2 实例在 AWS 上托管其 Web 应用程序.该公司要求返回所有健康 EC2 实例的 IP 地址以响应 DNS查询.应使用哪种策略来满足此要求? | C101: 简单的路由策略 | D101: 延迟路由策略 | E101: 多值路由策略 | F101: 地理位置路由策略 | J101: C | K101: https://aws.amazon.com/premiumsupport/knowledge-center/multivalue-versus-simple-policies/"使用多值应答路由策略来帮助跨多个资源分配DNS响应.例如,当使用多值应答路由时您希望将您的路由记录与 Route 53 运行状况检查相关联.” https://docs.aws.amazon.com/Route53/latest/DeveloperGuide/routing-policy.html#routing-policy-multivalue | N101: https://aws.amazon.com/premiumsupport/knowledge-center/multivalue-versus-simple-policies/"使用多值应答路由策略来帮助跨多个资源分配DNS响应.例如,当使用多值应答路由时您希望将您的路由记录与 Route 53 运行状况检查相关联.” https://docs.aws.amazon.com/Route53/latest/DeveloperGuide/routing-policy.html#routing-policy-multivalue
A102: 98 | B102: 一家公司想要使用 AWS Systems Manager 来管理一个队列 Amazon EC2 实例.根据公司的安全要求,没有 EC2 实例可以访问互联网.解决方案架构师需要设计从 EC2 实例到 Systems Manager 的网络连接,同时履行此安全义务.哪种解决方案将满足这些要求? | C102: 将 EC2 实例部署到没有到 Internet 的路由的私有子网中. | D102: 为 Systems Manager 配置接口 VPC 终端节点.更新路由以使用终端节点. | E102: 将 NAT 网关部署到公共子网中,为私有子网配置到 NAT 网关的默认路由, | F102: 部署互联网网关.配置网络 ACL 以拒绝到除 Systems Manager 之外的所有目的地的流量. | J102: B | K102: VPC 对等连接 VPC 接口终端节点可以通过区域内和区域间 VPC 对等连接访问.VPC 网关终端节点连接不能扩展到 VPC.VPC 对等连接另一端的资源在您的VPC 无法使用网关端点与网关端点服务中的资源进行通信.参考:https://docs.aws.amazon.com/systemsmanager/latest/userguide/setup-create-vpc.html | N102: VPC 对等连接 VPC 接口终端节点可以通过区域内和区域间 VPC 对等连接访问.VPC 网关终端节点连接不能扩展到 VPC.VPC 对等连接另一端的资源在您的VPC 无法使用网关端点与网关端点服务中的资源进行通信.参考:https://docs.aws.amazon.com/systemsmanager/latest/userguide/setup-create-vpc.html
A103: 99 | B103: 一家公司需要在 AWS 上构建报告解决方案.该解决方案必须支持数据分析师对数据运行的 SQL 查询.数据分析师每天将运行少于10 个查询该公司每天生成3 GB 的新数据本地关系数据库.需要将这些数据传输到 AWS 以执行报告任务.解决方案架构师应该推荐什么来以最低的成本满足这些要求? | C103: 使用 AWS Database Migration Service (AWS DMS) 将数据从本地数据库复制到 Amazon S3.使用 Amazon Athena 查询数据. | D103: 使用 Amazon Kinesis Data Firehose 传输流将数据传输到 Amazon Elasticsearch Service (Amazon ES) 集群中在 Amazon ES 中运行查询. | E103: 从本地数据库导出数据的每日副本.使用 AWS Storage Gateway 文件网关将导出的数据存储并复制到 Amazon S3.使用 Amazon EMR 集群查询数据. | F103: 使用 AVS Database MIgration service (AVVS UIS)从本地震性及利共小车到 Amazon KeasnITT 果中.使用 Amazon Redshift 集群查询数据. | J103: A | K103: S3 cheaper than Redshift anyday. And Redshift use case is generally for high data volume(Petabyte scales) of data. Here we are talking about few gigs only. Also, Athena is serverless and you don't pay for infrastructure. You only pay for the query that you do.S3每天都比Redshift便宜。Redshift的用例通常用于高数据量(PB级)的数据。这里我们只讨论几场演出。此外,Athena是无服务器的,您不需要支付基础设施费用。您只需为所做的查询付费。 | N103: S3 cheaper than Redshift anyday. And Redshift use case is generally for high data volume(Petabyte scales) of data. Here we are talking about few gigs only. Also, Athena is serverless and you don't pay for infrastructure. You only pay for the query that you do.S3每天都比Redshift便宜。Redshift的用例通常用于高数据量(PB级)的数据。这里我们只讨论几场演出。此外,Athena是无服务器的,您不需要支付基础设施费用。您只需为所做的查询付费。
...

Sheet 1-100
A1: 📘 AWS-SAA-C03 顺序刷题（1-100）
A2: 在每题「你的答案」输入 A 或 C,D（英文逗号）后，才会显示：结果 / 正确答案 / 解析，并自动对选项标色（绿=正确，红=你选错）。
A3: {=_xlfn.LET(_xlpm.ans,SUMPRODUCT(($A$4:$A$1304="你的答案")*($B$4:$B$1304<>"")),_xlpm.corr,SUMPRODUCT(($A$4:$A$1304="结果")*($B$4:$B$1304="✅正确")),_xlpm.total,COUNTIF($A$4:$A$1304,"题目 *"),_xlpm.rate,IF(_xlpm.ans=0,0,_xlpm.corr/_xlpm.ans),"📊 进度：已作答 "&_xlpm.ans&"/"&_xlpm.total&" | 正确 "&_xlpm.corr&" | 正确率 "&TEXT(_xlpm.rate,"0.0%"))} -> 📊 进度：已作答 0/100 | 正确 0 | 正确率 0.0%
A4: 题目 1： | B4: 一家公司有一个托管在 AWS 上的网站该网站位于应用程序负载均衡器(ALB)的后面,该应用程序负载均衡器(ALB)配置为分别处理 HTTP 和 HTTPS.该公司希望将所有请求转发到该网站,以便这些请求将使用 HTTPS.什么解决方案架构师应该做些什么来满足这个要求? | D4: {=_xlfn.LET(_xlpm.v,INDEX($B:$B, 4 + INT((ROW()-4)/13)*13 + 8), IF(_xlpm.v=0,"",_xlpm.v))} | F4: =1 -> 1 | G4: =_xlfn.XLOOKUP($F4,题库数据!$A$5:$A$104,题库数据!$J$5:$J$104,"") -> C | H4: =_xlfn.LET(_xlpm.v,_xlfn.XLOOKUP(F4,题库数据!$A$5:$A$104,题库数据!$K$5:$K$104,""),IF(OR(_xlpm.v="",_xlpm.v=0),"",_xlpm.v)) -> Cant be implemented on Lambda because the timeout for Lambda is 15mins and the Job takes 60minutes to complete
D5: {=_xlfn.LET(_xlpm.v,INDEX($B:$B, 4 + INT((ROW()-4)/13)*13 + 8), IF(_xlpm.v=0,"",_xlpm.v))} | F5: =1 -> 1 | G5: =_xlfn.XLOOKUP($F5,题库数据!$A$5:$A$104,题库数据!$J$5:$J$104,"") -> C | H5: =_xlfn.LET(_xlpm.v,_xlfn.XLOOKUP(F5,题库数据!$A$5:$A$104,题库数据!$K$5:$K$104,""),IF(OR(_xlpm.v="",_xlpm.v=0),"",_xlpm.v)) -> Cant be implemented on Lambda because the timeout for Lambda is 15mins and the Job takes 60minutes to complete
A6: A: | B6: =_xlfn.XLOOKUP($F6,题库[题号],题库[选项A]) -> 更新 ALB 的网络 ACL 以仅接受 HTTPS 流量 | D6: {=_xlfn.LET(_xlpm.v,INDEX($B:$B, 4 + INT((ROW()-4)/13)*13 + 8), IF(_xlpm.v=0,"",_xlpm.v))} | F6: =1 -> 1 | G6: =_xlfn.XLOOKUP($F6,题库数据!$A$5:$A$104,题库数据!$J$5:$J$104,"") -> C | H6: =_xlfn.LET(_xlpm.v,_xlfn.XLOOKUP(F6,题库数据!$A$5:$A$104,题库数据!$K$5:$K$104,""),IF(OR(_xlpm.v="",_xlpm.v=0),"",_xlpm.v)) -> Cant be implemented on Lambda because the timeout for Lambda is 15mins and the Job takes 60minutes to complete
A7: B: | B7: =_xlfn.XLOOKUP($F7,题库[题号],题库[选项B]) -> 创建一个规则,将 URL 中的 HTTP 替换为 HTTPS. | D7: {=_xlfn.LET(_xlpm.v,INDEX($B:$B, 4 + INT((ROW()-4)/13)*13 + 8), IF(_xlpm.v=0,"",_xlpm.v))} | F7: =1 -> 1 | G7: =_xlfn.XLOOKUP($F7,题库数据!$A$5:$A$104,题库数据!$J$5:$J$104,"") -> C | H7: =_xlfn.LET(_xlpm.v,_xlfn.XLOOKUP(F7,题库数据!$A$5:$A$104,题库数据!$K$5:$K$104,""),IF(OR(_xlpm.v="",_xlpm.v=0),"",_xlpm.v)) -> Cant be implemented on Lambda because the timeout for Lambda is 15mins and the Job takes 60minutes to complete
A8: C: | B8: =_xlfn.XLOOKUP($F8,题库[题号],题库[选项C]) -> 在 ALB 上创建一个监听器规则,将 HTTP 流量重定向到 HTTPS. | D8: {=_xlfn.LET(_xlpm.v,INDEX($B:$B, 4 + INT((ROW()-4)/13)*13 + 8), IF(_xlpm.v=0,"",_xlpm.v))} | F8: =1 -> 1 | G8: =_xlfn.XLOOKUP($F8,题库数据!$A$5:$A$104,题库数据!$J$5:$J$104,"") -> C | H8: =_xlfn.LET(_xlpm.v,_xlfn.XLOOKUP(F8,题库数据!$A$5:$A$104,题库数据!$K$5:$K$104,""),IF(OR(_xlpm.v="",_xlpm.v=0),"",_xlpm.v)) -> Cant be implemented on Lambda because the timeout for Lambda is 15mins and the Job takes 60minutes to complete
A9: D: | B9: =_xlfn.XLOOKUP($F9,题库[题号],题库[选项D]) -> 将 ALB 替换为配置为使用服务器名称指示(SNI)的网络负载均衡器. | D9: {=_xlfn.LET(_xlpm.v,INDEX($B:$B, 4 + INT((ROW()-4)/13)*13 + 8), IF(_xlpm.v=0,"",_xlpm.v))} | F9: =1 -> 1 | G9: =_xlfn.XLOOKUP($F9,题库数据!$A$5:$A$104,题库数据!$J$5:$J$104,"") -> C | H9: =_xlfn.LET(_xlpm.v,_xlfn.XLOOKUP(F9,题库数据!$A$5:$A$104,题库数据!$K$5:$K$104,""),IF(OR(_xlpm.v="",_xlpm.v=0),"",_xlpm.v)) -> Cant be implemented on Lambda because the timeout for Lambda is 15mins and the Job takes 60minutes to complete
B10: =_xlfn.LET(_xlpm.v,_xlfn.XLOOKUP($F10,题库[题号],题库[选项E],""),IF(OR(_xlpm.v="",_xlpm.v=0),"",_xlpm.v)) | D10: {=_xlfn.LET(_xlpm.v,INDEX($B:$B, 4 + INT((ROW()-4)/13)*13 + 8), IF(_xlpm.v=0,"",_xlpm.v))} | F10: =1 -> 1 | G10: =_xlfn.XLOOKUP($F10,题库数据!$A$5:$A$104,题库数据!$J$5:$J$104,"") -> C | H10: =_xlfn.LET(_xlpm.v,_xlfn.XLOOKUP(F10,题库数据!$A$5:$A$104,题库数据!$K$5:$K$104,""),IF(OR(_xlpm.v="",_xlpm.v=0),"",_xlpm.v)) -> Cant be implemented on Lambda because the timeout for Lambda is 15mins and the Job takes 60minutes to complete
B11: =_xlfn.LET(_xlpm.v,_xlfn.XLOOKUP($F11,题库[题号],题库[选项F],""),IF(OR(_xlpm.v="",_xlpm.v=0),"",_xlpm.v)) | D11: {=_xlfn.LET(_xlpm.v,INDEX($B:$B, 4 + INT((ROW()-4)/13)*13 + 8), IF(_xlpm.v=0,"",_xlpm.v))} | F11: =1 -> 1 | G11: =_xlfn.XLOOKUP($F11,题库数据!$A$5:$A$104,题库数据!$J$5:$J$104,"") -> C | H11: =_xlfn.LET(_xlpm.v,_xlfn.XLOOKUP(F11,题库数据!$A$5:$A$104,题库数据!$K$5:$K$104,""),IF(OR(_xlpm.v="",_xlpm.v=0),"",_xlpm.v)) -> Cant be implemented on Lambda because the timeout for Lambda is 15mins and the Job takes 60minutes to complete
A12: 你的答案 | D12: {=_xlfn.LET(_xlpm.v,INDEX($B:$B, 4 + INT((ROW()-4)/13)*13 + 8), IF(_xlpm.v=0,"",_xlpm.v))} | F12: =1 -> 1 | G12: =_xlfn.XLOOKUP($F12,题库数据!$A$5:$A$104,题库数据!$J$5:$J$104,"") -> C | H12: =_xlfn.LET(_xlpm.v,_xlfn.XLOOKUP(F12,题库数据!$A$5:$A$104,题库数据!$K$5:$K$104,""),IF(OR(_xlpm.v="",_xlpm.v=0),"",_xlpm.v)) -> Cant be implemented on Lambda because the timeout for Lambda is 15mins and the Job takes 60minutes to complete
A13: 结果 | B13: =_xlfn.LET(_xlpm.inp,$B$12,_xlpm.nInp,_xlfn.LET(_xlpm.raw,UPPER(TRIM($B$12)),_xlpm.clean,SUBSTITUTE(SUBSTITUTE(SUBSTITUTE(SUBSTITUTE(SUBSTITUTE(_xlpm.raw,"，",","),"、",","),"；",",")," ",""),",",""),_xlfn.TEXTJOIN(",",TRUE,IF(ISNUMBER(SEARCH("A",_xlpm.clean)),"A",""),IF(ISNUMBER(SEARCH("B",_xlpm.clean)),"B",""),IF(ISNUMBER(SEARCH("C",_xlpm.clean)),"C",""),IF(ISNUMBER(SEARCH("D",_xlpm.clean)),"D",""),IF(ISNUMBER(SEARCH("E",_xlpm.clean)),"E",""),IF(ISNUMBER(SEARCH("F",_xlpm.clean)),"F",""))),_xlpm.nStd,_xlfn.LET(_xlpm.raw,UPPER(TRIM($G$4)),_xlpm.clean,SUBSTITUTE(SUBSTITUTE(SUBSTITUTE(SUBSTITUTE(SUBSTITUTE(_xlpm.raw,"，",","),"、",","),"；",",")," ",""),",",""),_xlfn.TEXTJOIN(",",TRUE,IF(ISNUMBER(SEARCH("A",_xlpm.clean)),"A",""),IF(ISNUMBER(SEARCH("B",_xlpm.clean)),"B",""),IF(ISNUMBER(SEARCH("C",_xlpm.clean)),"C",""),IF(ISNUMBER(SEARCH("D",_xlpm.clean)),"D",""),IF(ISNUMBER(SEARCH("E",_xlpm.clean)),"E",""),IF(ISNUMBER(SEARCH("F",_xlpm.clean)),"F",""))),IF(LEN(TRIM(_xlpm.inp))=0,"",IF(AND(_xlpm.nInp<>"",_xlpm.nStd<>"",_xlpm.nInp=_xlpm.nStd),"✅正确","❌错误"))) | D13: {=_xlfn.LET(_xlpm.v,INDEX($B:$B, 4 + INT((ROW()-4)/13)*13 + 8), IF(_xlpm.v=0,"",_xlpm.v))} | F13: =1 -> 1 | G13: =_xlfn.XLOOKUP($F13,题库数据!$A$5:$A$104,题库数据!$J$5:$J$104,"") -> C | H13: =_xlfn.LET(_xlpm.v,_xlfn.XLOOKUP(F13,题库数据!$A$5:$A$104,题库数据!$K$5:$K$104,""),IF(OR(_xlpm.v="",_xlpm.v=0),"",_xlpm.v)) -> Cant be implemented on Lambda because the timeout for Lambda is 15mins and the Job takes 60minutes to complete
A14: 正确答案 | B14: =_xlfn.LET(_xlpm.inp,$B$12,_xlpm.nStd,_xlfn.LET(_xlpm.raw,UPPER(TRIM($G$4)),_xlpm.clean,SUBSTITUTE(SUBSTITUTE(SUBSTITUTE(SUBSTITUTE(SUBSTITUTE(_xlpm.raw,"，",","),"、",","),"；",",")," ",""),",",""),_xlfn.TEXTJOIN(",",TRUE,IF(ISNUMBER(SEARCH("A",_xlpm.clean)),"A",""),IF(ISNUMBER(SEARCH("B",_xlpm.clean)),"B",""),IF(ISNUMBER(SEARCH("C",_xlpm.clean)),"C",""),IF(ISNUMBER(SEARCH("D",_xlpm.clean)),"D",""),IF(ISNUMBER(SEARCH("E",_xlpm.clean)),"E",""),IF(ISNUMBER(SEARCH("F",_xlpm.clean)),"F",""))),IF(OR(LEN(TRIM(_xlpm.inp))=0,_xlpm.nStd=""),"",_xlpm.nStd)) | D14: {=_xlfn.LET(_xlpm.v,INDEX($B:$B, 4 + INT((ROW()-4)/13)*13 + 8), IF(_xlpm.v=0,"",_xlpm.v))} | F14: =1 -> 1 | G14: =_xlfn.XLOOKUP($F14,题库数据!$A$5:$A$104,题库数据!$J$5:$J$104,"") -> C | H14: =_xlfn.LET(_xlpm.v,_xlfn.XLOOKUP(F14,题库数据!$A$5:$A$104,题库数据!$K$5:$K$104,""),IF(OR(_xlpm.v="",_xlpm.v=0),"",_xlpm.v)) -> Cant be implemented on Lambda because the timeout for Lambda is 15mins and the Job takes 60minutes to complete
A15: 解析 | B15: =_xlfn.LET(_xlpm.inp,$B$12,_xlpm.p,$H$4,IF(OR(LEN(TRIM(_xlpm.inp))=0,LEN(TRIM(_xlpm.p))=0,_xlpm.p=0),"",_xlpm.p)) | D15: {=_xlfn.LET(_xlpm.v,INDEX($B:$B, 4 + INT((ROW()-4)/13)*13 + 8), IF(_xlpm.v=0,"",_xlpm.v))} | F15: =1 -> 1 | G15: =_xlfn.XLOOKUP($F15,题库数据!$A$5:$A$104,题库数据!$J$5:$J$104,"") -> C | H15: =_xlfn.LET(_xlpm.v,_xlfn.XLOOKUP(F15,题库数据!$A$5:$A$104,题库数据!$K$5:$K$104,""),IF(OR(_xlpm.v="",_xlpm.v=0),"",_xlpm.v)) -> Cant be implemented on Lambda because the timeout for Lambda is 15mins and the Job takes 60minutes to complete
D16: {=_xlfn.LET(_xlpm.v,INDEX($B:$B, 4 + INT((ROW()-4)/13)*13 + 8), IF(_xlpm.v=0,"",_xlpm.v))} | F16: =1 -> 1 | G16: =_xlfn.XLOOKUP($F16,题库数据!$A$5:$A$104,题库数据!$J$5:$J$104,"") -> C | H16: =_xlfn.LET(_xlpm.v,_xlfn.XLOOKUP(F16,题库数据!$A$5:$A$104,题库数据!$K$5:$K$104,""),IF(OR(_xlpm.v="",_xlpm.v=0),"",_xlpm.v)) -> Cant be implemented on Lambda because the timeout for Lambda is 15mins and the Job takes 60minutes to complete
A17: 题目 2： | B17: 一家公司正在 AWS 上开发一个两层 Web 应用程序,该公司的开发人员已将该应用程序部署在直接连接到后端 Amazon RDS 数据库的 Amazon EC2 实例上.该公司不得在应用程序中硬编码数据库凭证.该公司还必须实施定期自动轮换数据库凭据的解决方案.哪种解决方案能够以最少的运营开销满足这些要求? | D17: {=_xlfn.LET(_xlpm.v,INDEX($B:$B, 4 + INT((ROW()-4)/13)*13 + 8), IF(_xlpm.v=0,"",_xlpm.v))} | F17: =2 -> 2 | G17: =_xlfn.XLOOKUP($F17,题库数据!$A$5:$A$104,题库数据!$J$5:$J$104,"") -> C | H17: =_xlfn.LET(_xlpm.v,_xlfn.XLOOKUP(F17,题库数据!$A$5:$A$104,题库数据!$K$5:$K$104,""),IF(OR(_xlpm.v="",_xlpm.v=0),"",_xlpm.v)) -> AWS Secrets Manager 是比 SSM Parameter store 更新的服务. https://docs.aws.amazon.com/secretsmanager/latest/userguide/create_database_secret.html
D18: {=_xlfn.LET(_xlpm.v,INDEX($B:$B, 4 + INT((ROW()-4)/13)*13 + 8), IF(_xlpm.v=0,"",_xlpm.v))} | F18: =2 -> 2 | G18: =_xlfn.XLOOKUP($F18,题库数据!$A$5:$A$104,题库数据!$J$5:$J$104,"") -> C | H18: =_xlfn.LET(_xlpm.v,_xlfn.XLOOKUP(F18,题库数据!$A$5:$A$104,题库数据!$K$5:$K$104,""),IF(OR(_xlpm.v="",_xlpm.v=0),"",_xlpm.v)) -> AWS Secrets Manager 是比 SSM Parameter store 更新的服务. https://docs.aws.amazon.com/secretsmanager/latest/userguide/create_database_secret.html
A19: A: | B19: =_xlfn.XLOOKUP($F19,题库[题号],题库[选项A]) -> 将数据库凭证存储在实例元数据中.使用 Amazon EventBridge (Amazon CloudWatch Events)规则运行计划的 AWS Lambda 函数,该函数同时更新 RDS 凭证和实例元数据. | D19: {=_xlfn.LET(_xlpm.v,INDEX($B:$B, 4 + INT((ROW()-4)/13)*13 + 8), IF(_xlpm.v=0,"",_xlpm.v))} | F19: =2 -> 2 | G19: =_xlfn.XLOOKUP($F19,题库数据!$A$5:$A$104,题库数据!$J$5:$J$104,"") -> C | H19: =_xlfn.LET(_xlpm.v,_xlfn.XLOOKUP(F19,题库数据!$A$5:$A$104,题库数据!$K$5:$K$104,""),IF(OR(_xlpm.v="",_xlpm.v=0),"",_xlpm.v)) -> AWS Secrets Manager 是比 SSM Parameter store 更新的服务. https://docs.aws.amazon.com/secretsmanager/latest/userguide/create_database_secret.html
A20: B: | B20: =_xlfn.XLOOKUP($F20,题库[题号],题库[选项B]) -> 将数据库凭证存储在加密 Amazon S3 存储桶中的配置文件中.使用 Amazon EventBridge (Amazon CloudWatch Events)规则运行计划的 AWS Lambda 函数,该函数同时更新 RDS 凭证和配置文件中的凭证.使用 S3 版本控制确保能够回退到以前的值. | D20: {=_xlfn.LET(_xlpm.v,INDEX($B:$B, 4 + INT((ROW()-4)/13)*13 + 8), IF(_xlpm.v=0,"",_xlpm.v))} | F20: =2 -> 2 | G20: =_xlfn.XLOOKUP($F20,题库数据!$A$5:$A$104,题库数据!$J$5:$J$104,"") -> C | H20: =_xlfn.LET(_xlpm.v,_xlfn.XLOOKUP(F20,题库数据!$A$5:$A$104,题库数据!$K$5:$K$104,""),IF(OR(_xlpm.v="",_xlpm.v=0),"",_xlpm.v)) -> AWS Secrets Manager 是比 SSM Parameter store 更新的服务. https://docs.aws.amazon.com/secretsmanager/latest/userguide/create_database_secret.html
A21: C: | B21: =_xlfn.XLOOKUP($F21,题库[题号],题库[选项C]) -> 将数据库凭证作为秘密存储在 AWS Secrets Manager 中.打开秘密的自动轮换.将所需的权限附加到EC2 角色以授予对秘密的访问权限. | D21: {=_xlfn.LET(_xlpm.v,INDEX($B:$B, 4 + INT((ROW()-4)/13)*13 + 8), IF(_xlpm.v=0,"",_xlpm.v))} | F21: =2 -> 2 | G21: =_xlfn.XLOOKUP($F21,题库数据!$A$5:$A$104,题库数据!$J$5:$J$104,"") -> C | H21: =_xlfn.LET(_xlpm.v,_xlfn.XLOOKUP(F21,题库数据!$A$5:$A$104,题库数据!$K$5:$K$104,""),IF(OR(_xlpm.v="",_xlpm.v=0),"",_xlpm.v)) -> AWS Secrets Manager 是比 SSM Parameter store 更新的服务. https://docs.aws.amazon.com/secretsmanager/latest/userguide/create_database_secret.html
A22: D: | B22: =_xlfn.XLOOKUP($F22,题库[题号],题库[选项D]) -> 将数据库凭证作为加密参数存储在 AWS Systems Manager Parameter Store 中.为加密参数启用自动轮换.将所需权限附加到 EC2 角色以授予对加密参数的访问权限. | D22: {=_xlfn.LET(_xlpm.v,INDEX($B:$B, 4 + INT((ROW()-4)/13)*13 + 8), IF(_xlpm.v=0,"",_xlpm.v))} | F22: =2 -> 2 | G22: =_xlfn.XLOOKUP($F22,题库数据!$A$5:$A$104,题库数据!$J$5:$J$104,"") -> C | H22: =_xlfn.LET(_xlpm.v,_xlfn.XLOOKUP(F22,题库数据!$A$5:$A$104,题库数据!$K$5:$K$104,""),IF(OR(_xlpm.v="",_xlpm.v=0),"",_xlpm.v)) -> AWS Secrets Manager 是比 SSM Parameter store 更新的服务. https://docs.aws.amazon.com/secretsmanager/latest/userguide/create_database_secret.html
B23: =_xlfn.LET(_xlpm.v,_xlfn.XLOOKUP($F23,题库[题号],题库[选项E],""),IF(OR(_xlpm.v="",_xlpm.v=0),"",_xlpm.v)) | D23: {=_xlfn.LET(_xlpm.v,INDEX($B:$B, 4 + INT((ROW()-4)/13)*13 + 8), IF(_xlpm.v=0,"",_xlpm.v))} | F23: =2 -> 2 | G23: =_xlfn.XLOOKUP($F23,题库数据!$A$5:$A$104,题库数据!$J$5:$J$104,"") -> C | H23: =_xlfn.LET(_xlpm.v,_xlfn.XLOOKUP(F23,题库数据!$A$5:$A$104,题库数据!$K$5:$K$104,""),IF(OR(_xlpm.v="",_xlpm.v=0),"",_xlpm.v)) -> AWS Secrets Manager 是比 SSM Parameter store 更新的服务. https://docs.aws.amazon.com/secretsmanager/latest/userguide/create_database_secret.html
B24: =_xlfn.LET(_xlpm.v,_xlfn.XLOOKUP($F24,题库[题号],题库[选项F],""),IF(OR(_xlpm.v="",_xlpm.v=0),"",_xlpm.v)) | D24: {=_xlfn.LET(_xlpm.v,INDEX($B:$B, 4 + INT((ROW()-4)/13)*13 + 8), IF(_xlpm.v=0,"",_xlpm.v))} | F24: =2 -> 2 | G24: =_xlfn.XLOOKUP($F24,题库数据!$A$5:$A$104,题库数据!$J$5:$J$104,"") -> C | H24: =_xlfn.LET(_xlpm.v,_xlfn.XLOOKUP(F24,题库数据!$A$5:$A$104,题库数据!$K$5:$K$104,""),IF(OR(_xlpm.v="",_xlpm.v=0),"",_xlpm.v)) -> AWS Secrets Manager 是比 SSM Parameter store 更新的服务. https://docs.aws.amazon.com/secretsmanager/latest/userguide/create_database_secret.html
A25: 你的答案 | D25: {=_xlfn.LET(_xlpm.v,INDEX($B:$B, 4 + INT((ROW()-4)/13)*13 + 8), IF(_xlpm.v=0,"",_xlpm.v))} | F25: =2 -> 2 | G25: =_xlfn.XLOOKUP($F25,题库数据!$A$5:$A$104,题库数据!$J$5:$J$104,"") -> C | H25: =_xlfn.LET(_xlpm.v,_xlfn.XLOOKUP(F25,题库数据!$A$5:$A$104,题库数据!$K$5:$K$104,""),IF(OR(_xlpm.v="",_xlpm.v=0),"",_xlpm.v)) -> AWS Secrets Manager 是比 SSM Parameter store 更新的服务. https://docs.aws.amazon.com/secretsmanager/latest/userguide/create_database_secret.html
A26: 结果 | B26: =_xlfn.LET(_xlpm.inp,$B$25,_xlpm.nInp,_xlfn.LET(_xlpm.raw,UPPER(TRIM($B$25)),_xlpm.clean,SUBSTITUTE(SUBSTITUTE(SUBSTITUTE(SUBSTITUTE(SUBSTITUTE(_xlpm.raw,"，",","),"、",","),"；",",")," ",""),",",""),_xlfn.TEXTJOIN(",",TRUE,IF(ISNUMBER(SEARCH("A",_xlpm.clean)),"A",""),IF(ISNUMBER(SEARCH("B",_xlpm.clean)),"B",""),IF(ISNUMBER(SEARCH("C",_xlpm.clean)),"C",""),IF(ISNUMBER(SEARCH("D",_xlpm.clean)),"D",""),IF(ISNUMBER(SEARCH("E",_xlpm.clean)),"E",""),IF(ISNUMBER(SEARCH("F",_xlpm.clean)),"F",""))),_xlpm.nStd,_xlfn.LET(_xlpm.raw,UPPER(TRIM($G$17)),_xlpm.clean,SUBSTITUTE(SUBSTITUTE(SUBSTITUTE(SUBSTITUTE(SUBSTITUTE(_xlpm.raw,"，",","),"、",","),"；",",")," ",""),",",""),_xlfn.TEXTJOIN(",",TRUE,IF(ISNUMBER(SEARCH("A",_xlpm.clean)),"A",""),IF(ISNUMBER(SEARCH("B",_xlpm.clean)),"B",""),IF(ISNUMBER(SEARCH("C",_xlpm.clean)),"C",""),IF(ISNUMBER(SEARCH("D",_xlpm.clean)),"D",""),IF(ISNUMBER(SEARCH("E",_xlpm.clean)),"E",""),IF(ISNUMBER(SEARCH("F",_xlpm.clean)),"F",""))),IF(LEN(TRIM(_xlpm.inp))=0,"",IF(AND(_xlpm.nInp<>"",_xlpm.nStd<>"",_xlpm.nInp=_xlpm.nStd),"✅正确","❌错误"))) | D26: {=_xlfn.LET(_xlpm.v,INDEX($B:$B, 4 + INT((ROW()-4)/13)*13 + 8), IF(_xlpm.v=0,"",_xlpm.v))} | F26: =2 -> 2 | G26: =_xlfn.XLOOKUP($F26,题库数据!$A$5:$A$104,题库数据!$J$5:$J$104,"") -> C | H26: =_xlfn.LET(_xlpm.v,_xlfn.XLOOKUP(F26,题库数据!$A$5:$A$104,题库数据!$K$5:$K$104,""),IF(OR(_xlpm.v="",_xlpm.v=0),"",_xlpm.v)) -> AWS Secrets Manager 是比 SSM Parameter store 更新的服务. https://docs.aws.amazon.com/secretsmanager/latest/userguide/create_database_secret.html
A27: 正确答案 | B27: =_xlfn.LET(_xlpm.inp,$B$25,_xlpm.nStd,_xlfn.LET(_xlpm.raw,UPPER(TRIM($G$17)),_xlpm.clean,SUBSTITUTE(SUBSTITUTE(SUBSTITUTE(SUBSTITUTE(SUBSTITUTE(_xlpm.raw,"，",","),"、",","),"；",",")," ",""),",",""),_xlfn.TEXTJOIN(",",TRUE,IF(ISNUMBER(SEARCH("A",_xlpm.clean)),"A",""),IF(ISNUMBER(SEARCH("B",_xlpm.clean)),"B",""),IF(ISNUMBER(SEARCH("C",_xlpm.clean)),"C",""),IF(ISNUMBER(SEARCH("D",_xlpm.clean)),"D",""),IF(ISNUMBER(SEARCH("E",_xlpm.clean)),"E",""),IF(ISNUMBER(SEARCH("F",_xlpm.clean)),"F",""))),IF(OR(LEN(TRIM(_xlpm.inp))=0,_xlpm.nStd=""),"",_xlpm.nStd)) | D27: {=_xlfn.LET(_xlpm.v,INDEX($B:$B, 4 + INT((ROW()-4)/13)*13 + 8), IF(_xlpm.v=0,"",_xlpm.v))} | F27: =2 -> 2 | G27: =_xlfn.XLOOKUP($F27,题库数据!$A$5:$A$104,题库数据!$J$5:$J$104,"") -> C | H27: =_xlfn.LET(_xlpm.v,_xlfn.XLOOKUP(F27,题库数据!$A$5:$A$104,题库数据!$K$5:$K$104,""),IF(OR(_xlpm.v="",_xlpm.v=0),"",_xlpm.v)) -> AWS Secrets Manager 是比 SSM Parameter store 更新的服务. https://docs.aws.amazon.com/secretsmanager/latest/userguide/create_database_secret.html
A28: 解析 | B28: =_xlfn.LET(_xlpm.inp,$B$25,_xlpm.p,$H$17,IF(OR(LEN(TRIM(_xlpm.inp))=0,LEN(TRIM(_xlpm.p))=0,_xlpm.p=0),"",_xlpm.p)) | D28: {=_xlfn.LET(_xlpm.v,INDEX($B:$B, 4 + INT((ROW()-4)/13)*13 + 8), IF(_xlpm.v=0,"",_xlpm.v))} | F28: =2 -> 2 | G28: =_xlfn.XLOOKUP($F28,题库数据!$A$5:$A$104,题库数据!$J$5:$J$104,"") -> C | H28: =_xlfn.LET(_xlpm.v,_xlfn.XLOOKUP(F28,题库数据!$A$5:$A$104,题库数据!$K$5:$K$104,""),IF(OR(_xlpm.v="",_xlpm.v=0),"",_xlpm.v)) -> AWS Secrets Manager 是比 SSM Parameter store 更新的服务. https://docs.aws.amazon.com/secretsmanager/latest/userguide/create_database_secret.html
D29: {=_xlfn.LET(_xlpm.v,INDEX($B:$B, 4 + INT((ROW()-4)/13)*13 + 8), IF(_xlpm.v=0,"",_xlpm.v))} | F29: =2 -> 2 | G29: =_xlfn.XLOOKUP($F29,题库数据!$A$5:$A$104,题库数据!$J$5:$J$104,"") -> C | H29: =_xlfn.LET(_xlpm.v,_xlfn.XLOOKUP(F29,题库数据!$A$5:$A$104,题库数据!$K$5:$K$104,""),IF(OR(_xlpm.v="",_xlpm.v=0),"",_xlpm.v)) -> AWS Secrets Manager 是比 SSM Parameter store 更新的服务. https://docs.aws.amazon.com/secretsmanager/latest/userguide/create_database_secret.html
A30: 题目 3： | B30: 一家公司正在向 AWS 部署一个新的公共 Web 应用程序.该应用程序将在 Application Load Balancer (ALB)之后运行,该应用程序需要在边缘使用由外部证书颁发机构颁发的 SSL/TLS 证书进行加密(CA).证书必须在证书到期之前每年轮换.解决方案架构师应该做什么来满足这些要求? | D30: {=_xlfn.LET(_xlpm.v,INDEX($B:$B, 4 + INT((ROW()-4)/13)*13 + 8), IF(_xlpm.v=0,"",_xlpm.v))} | F30: =3 -> 3 | G30: =_xlfn.XLOOKUP($F30,题库数据!$A$5:$A$104,题库数据!$J$5:$J$104,"") -> D | H30: =_xlfn.LET(_xlpm.v,_xlfn.XLOOKUP(F30,题库数据!$A$5:$A$104,题库数据!$K$5:$K$104,""),IF(OR(_xlpm.v="",_xlpm.v=0),"",_xlpm.v)) -> It's a third-party certificate, hence AWS cannot manage renewal automatically. The closest thing you can do is to send a notification to renew the 3rd party certificate.
D31: {=_xlfn.LET(_xlpm.v,INDEX($B:$B, 4 + INT((ROW()-4)/13)*13 + 8), IF(_xlpm.v=0,"",_xlpm.v))} | F31: =3 -> 3 | G31: =_xlfn.XLOOKUP($F31,题库数据!$A$5:$A$104,题库数据!$J$5:$J$104,"") -> D | H31: =_xlfn.LET(_xlpm.v,_xlfn.XLOOKUP(F31,题库数据!$A$5:$A$104,题库数据!$K$5:$K$104,""),IF(OR(_xlpm.v="",_xlpm.v=0),"",_xlpm.v)) -> It's a third-party certificate, hence AWS cannot manage renewal automatically. The closest thing you can do is to send a notification to renew the 3rd party certificate.
A32: A: | B32: =_xlfn.XLOOKUP($F32,题库[题号],题库[选项A]) -> 使用 AWS Certificate Manager (ACM) 颁发 SSL/TLS 证书.将证书应用到 ALB.使用托管续订功能自动轮换证书. | D32: {=_xlfn.LET(_xlpm.v,INDEX($B:$B, 4 + INT((ROW()-4)/13)*13 + 8), IF(_xlpm.v=0,"",_xlpm.v))} | F32: =3 -> 3 | G32: =_xlfn.XLOOKUP($F32,题库数据!$A$5:$A$104,题库数据!$J$5:$J$104,"") -> D | H32: =_xlfn.LET(_xlpm.v,_xlfn.XLOOKUP(F32,题库数据!$A$5:$A$104,题库数据!$K$5:$K$104,""),IF(OR(_xlpm.v="",_xlpm.v=0),"",_xlpm.v)) -> It's a third-party certificate, hence AWS cannot manage renewal automatically. The closest thing you can do is to send a notification to renew the 3rd party certificate.
A33: B: | B33: =_xlfn.XLOOKUP($F33,题库[题号],题库[选项B]) -> 使用 AWS Certificate Manager (ACM)颁发 SSL/TLS 证书.从证书中导入密钥材料.将证书应用到 ALB.使用托管续订功能自动轮换证书. | D33: {=_xlfn.LET(_xlpm.v,INDEX($B:$B, 4 + INT((ROW()-4)/13)*13 + 8), IF(_xlpm.v=0,"",_xlpm.v))} | F33: =3 -> 3 | G33: =_xlfn.XLOOKUP($F33,题库数据!$A$5:$A$104,题库数据!$J$5:$J$104,"") -> D | H33: =_xlfn.LET(_xlpm.v,_xlfn.XLOOKUP(F33,题库数据!$A$5:$A$104,题库数据!$K$5:$K$104,""),IF(OR(_xlpm.v="",_xlpm.v=0),"",_xlpm.v)) -> It's a third-party certificate, hence AWS cannot manage renewal automatically. The closest thing you can do is to send a notification to renew the 3rd party certificate.
A34: C: | B34: =_xlfn.XLOOKUP($F34,题库[题号],题库[选项C]) -> 使用 AWS Certificate Manager (ACM) 私有证书颁发机构从根 CA 颁发 SSL/TLS 证书.将证书应用到 ALB.使用托管续订功能自动轮换证书. | D34: {=_xlfn.LET(_xlpm.v,INDEX($B:$B, 4 + INT((ROW()-4)/13)*13 + 8), IF(_xlpm.v=0,"",_xlpm.v))} | F34: =3 -> 3 | G34: =_xlfn.XLOOKUP($F34,题库数据!$A$5:$A$104,题库数据!$J$5:$J$104,"") -> D | H34: =_xlfn.LET(_xlpm.v,_xlfn.XLOOKUP(F34,题库数据!$A$5:$A$104,题库数据!$K$5:$K$104,""),IF(OR(_xlpm.v="",_xlpm.v=0),"",_xlpm.v)) -> It's a third-party certificate, hence AWS cannot manage renewal automatically. The closest thing you can do is to send a notification to renew the 3rd party certificate.
A35: D: | B35: =_xlfn.XLOOKUP($F35,题库[题号],题库[选项D]) -> 使用 AWS Certificate Manager (ACM) 导入 SSL/TLS 证书.将证书应用到 ALB.使用 Amazon EventBridge (Amazon CloudWatch Events)在证书即将到期时发送通知.手动轮换证书. | D35: {=_xlfn.LET(_xlpm.v,INDEX($B:$B, 4 + INT((ROW()-4)/13)*13 + 8), IF(_xlpm.v=0,"",_xlpm.v))} | F35: =3 -> 3 | G35: =_xlfn.XLOOKUP($F35,题库数据!$A$5:$A$104,题库数据!$J$5:$J$104,"") -> D | H35: =_xlfn.LET(_xlpm.v,_xlfn.XLOOKUP(F35,题库数据!$A$5:$A$104,题库数据!$K$5:$K$104,""),IF(OR(_xlpm.v="",_xlpm.v=0),"",_xlpm.v)) -> It's a third-party certificate, hence AWS cannot manage renewal automatically. The closest thing you can do is to send a notification to renew the 3rd party certificate.
B36: =_xlfn.LET(_xlpm.v,_xlfn.XLOOKUP($F36,题库[题号],题库[选项E],""),IF(OR(_xlpm.v="",_xlpm.v=0),"",_xlpm.v)) | D36: {=_xlfn.LET(_xlpm.v,INDEX($B:$B, 4 + INT((ROW()-4)/13)*13 + 8), IF(_xlpm.v=0,"",_xlpm.v))} | F36: =3 -> 3 | G36: =_xlfn.XLOOKUP($F36,题库数据!$A$5:$A$104,题库数据!$J$5:$J$104,"") -> D | H36: =_xlfn.LET(_xlpm.v,_xlfn.XLOOKUP(F36,题库数据!$A$5:$A$104,题库数据!$K$5:$K$104,""),IF(OR(_xlpm.v="",_xlpm.v=0),"",_xlpm.v)) -> It's a third-party certificate, hence AWS cannot manage renewal automatically. The closest thing you can do is to send a notification to renew the 3rd party certificate.
B37: =_xlfn.LET(_xlpm.v,_xlfn.XLOOKUP($F37,题库[题号],题库[选项F],""),IF(OR(_xlpm.v="",_xlpm.v=0),"",_xlpm.v)) | D37: {=_xlfn.LET(_xlpm.v,INDEX($B:$B, 4 + INT((ROW()-4)/13)*13 + 8), IF(_xlpm.v=0,"",_xlpm.v))} | F37: =3 -> 3 | G37: =_xlfn.XLOOKUP($F37,题库数据!$A$5:$A$104,题库数据!$J$5:$J$104,"") -> D | H37: =_xlfn.LET(_xlpm.v,_xlfn.XLOOKUP(F37,题库数据!$A$5:$A$104,题库数据!$K$5:$K$104,""),IF(OR(_xlpm.v="",_xlpm.v=0),"",_xlpm.v)) -> It's a third-party certificate, hence AWS cannot manage renewal automatically. The closest thing you can do is to send a notification to renew the 3rd party certificate.
A38: 你的答案 | D38: {=_xlfn.LET(_xlpm.v,INDEX($B:$B, 4 + INT((ROW()-4)/13)*13 + 8), IF(_xlpm.v=0,"",_xlpm.v))} | F38: =3 -> 3 | G38: =_xlfn.XLOOKUP($F38,题库数据!$A$5:$A$104,题库数据!$J$5:$J$104,"") -> D | H38: =_xlfn.LET(_xlpm.v,_xlfn.XLOOKUP(F38,题库数据!$A$5:$A$104,题库数据!$K$5:$K$104,""),IF(OR(_xlpm.v="",_xlpm.v=0),"",_xlpm.v)) -> It's a third-party certificate, hence AWS cannot manage renewal automatically. The closest thing you can do is to send a notification to renew the 3rd party certificate.
A39: 结果 | B39: =_xlfn.LET(_xlpm.inp,$B$38,_xlpm.nInp,_xlfn.LET(_xlpm.raw,UPPER(TRIM($B$38)),_xlpm.clean,SUBSTITUTE(SUBSTITUTE(SUBSTITUTE(SUBSTITUTE(SUBSTITUTE(_xlpm.raw,"，",","),"、",","),"；",",")," ",""),",",""),_xlfn.TEXTJOIN(",",TRUE,IF(ISNUMBER(SEARCH("A",_xlpm.clean)),"A",""),IF(ISNUMBER(SEARCH("B",_xlpm.clean)),"B",""),IF(ISNUMBER(SEARCH("C",_xlpm.clean)),"C",""),IF(ISNUMBER(SEARCH("D",_xlpm.clean)),"D",""),IF(ISNUMBER(SEARCH("E",_xlpm.clean)),"E",""),IF(ISNUMBER(SEARCH("F",_xlpm.clean)),"F",""))),_xlpm.nStd,_xlfn.LET(_xlpm.raw,UPPER(TRIM($G$30)),_xlpm.clean,SUBSTITUTE(SUBSTITUTE(SUBSTITUTE(SUBSTITUTE(SUBSTITUTE(_xlpm.raw,"，",","),"、",","),"；",",")," ",""),",",""),_xlfn.TEXTJOIN(",",TRUE,IF(ISNUMBER(SEARCH("A",_xlpm.clean)),"A",""),IF(ISNUMBER(SEARCH("B",_xlpm.clean)),"B",""),IF(ISNUMBER(SEARCH("C",_xlpm.clean)),"C",""),IF(ISNUMBER(SEARCH("D",_xlpm.clean)),"D",""),IF(ISNUMBER(SEARCH("E",_xlpm.clean)),"E",""),IF(ISNUMBER(SEARCH("F",_xlpm.clean)),"F",""))),IF(LEN(TRIM(_xlpm.inp))=0,"",IF(AND(_xlpm.nInp<>"",_xlpm.nStd<>"",_xlpm.nInp=_xlpm.nStd),"✅正确","❌错误"))) | D39: {=_xlfn.LET(_xlpm.v,INDEX($B:$B, 4 + INT((ROW()-4)/13)*13 + 8), IF(_xlpm.v=0,"",_xlpm.v))} | F39: =3 -> 3 | G39: =_xlfn.XLOOKUP($F39,题库数据!$A$5:$A$104,题库数据!$J$5:$J$104,"") -> D | H39: =_xlfn.LET(_xlpm.v,_xlfn.XLOOKUP(F39,题库数据!$A$5:$A$104,题库数据!$K$5:$K$104,""),IF(OR(_xlpm.v="",_xlpm.v=0),"",_xlpm.v)) -> It's a third-party certificate, hence AWS cannot manage renewal automatically. The closest thing you can do is to send a notification to renew the 3rd party certificate.
A40: 正确答案 | B40: =_xlfn.LET(_xlpm.inp,$B$38,_xlpm.nStd,_xlfn.LET(_xlpm.raw,UPPER(TRIM($G$30)),_xlpm.clean,SUBSTITUTE(SUBSTITUTE(SUBSTITUTE(SUBSTITUTE(SUBSTITUTE(_xlpm.raw,"，",","),"、",","),"；",",")," ",""),",",""),_xlfn.TEXTJOIN(",",TRUE,IF(ISNUMBER(SEARCH("A",_xlpm.clean)),"A",""),IF(ISNUMBER(SEARCH("B",_xlpm.clean)),"B",""),IF(ISNUMBER(SEARCH("C",_xlpm.clean)),"C",""),IF(ISNUMBER(SEARCH("D",_xlpm.clean)),"D",""),IF(ISNUMBER(SEARCH("E",_xlpm.clean)),"E",""),IF(ISNUMBER(SEARCH("F",_xlpm.clean)),"F",""))),IF(OR(LEN(TRIM(_xlpm.inp))=0,_xlpm.nStd=""),"",_xlpm.nStd)) | D40: {=_xlfn.LET(_xlpm.v,INDEX($B:$B, 4 + INT((ROW()-4)/13)*13 + 8), IF(_xlpm.v=0,"",_xlpm.v))} | F40: =3 -> 3 | G40: =_xlfn.XLOOKUP($F40,题库数据!$A$5:$A$104,题库数据!$J$5:$J$104,"") -> D | H40: =_xlfn.LET(_xlpm.v,_xlfn.XLOOKUP(F40,题库数据!$A$5:$A$104,题库数据!$K$5:$K$104,""),IF(OR(_xlpm.v="",_xlpm.v=0),"",_xlpm.v)) -> It's a third-party certificate, hence AWS cannot manage renewal automatically. The closest thing you can do is to send a notification to renew the 3rd party certificate.
A41: 解析 | B41: =_xlfn.LET(_xlpm.inp,$B$38,_xlpm.p,$H$30,IF(OR(LEN(TRIM(_xlpm.inp))=0,LEN(TRIM(_xlpm.p))=0,_xlpm.p=0),"",_xlpm.p)) | D41: {=_xlfn.LET(_xlpm.v,INDEX($B:$B, 4 + INT((ROW()-4)/13)*13 + 8), IF(_xlpm.v=0,"",_xlpm.v))} | F41: =3 -> 3 | G41: =_xlfn.XLOOKUP($F41,题库数据!$A$5:$A$104,题库数据!$J$5:$J$104,"") -> D | H41: =_xlfn.LET(_xlpm.v,_xlfn.XLOOKUP(F41,题库数据!$A$5:$A$104,题库数据!$K$5:$K$104,""),IF(OR(_xlpm.v="",_xlpm.v=0),"",_xlpm.v)) -> It's a third-party certificate, hence AWS cannot manage renewal automatically. The closest thing you can do is to send a notification to renew the 3rd party certificate.
D42: {=_xlfn.LET(_xlpm.v,INDEX($B:$B, 4 + INT((ROW()-4)/13)*13 + 8), IF(_xlpm.v=0,"",_xlpm.v))} | F42: =3 -> 3 | G42: =_xlfn.XLOOKUP($F42,题库数据!$A$5:$A$104,题库数据!$J$5:$J$104,"") -> D | H42: =_xlfn.LET(_xlpm.v,_xlfn.XLOOKUP(F42,题库数据!$A$5:$A$104,题库数据!$K$5:$K$104,""),IF(OR(_xlpm.v="",_xlpm.v=0),"",_xlpm.v)) -> It's a third-party certificate, hence AWS cannot manage renewal automatically. The closest thing you can do is to send a notification to renew the 3rd party certificate.
A43: 题目 4： | B43: 一家公司在 AWS 上运行其基础设施,并拥有700.000 名注册用户,用于 res 文档管理应用程序,该公司打算创建一个将大型 pdf 文件转换为 jpg Imago 文件的产品 .. pdf 文件的平均大小为5 MB.公司需要存储原始文件和转换后的文件,解决方案架构师必须设计一个可扩展的解决方案,以适应随着时间的推移而迅速增长的需求.哪种解决方案最经济高效地满足这些要求? | D43: {=_xlfn.LET(_xlpm.v,INDEX($B:$B, 4 + INT((ROW()-4)/13)*13 + 8), IF(_xlpm.v=0,"",_xlpm.v))} | F43: =4 -> 4 | G43: =_xlfn.XLOOKUP($F43,题库数据!$A$5:$A$104,题库数据!$J$5:$J$104,"") -> A | H43: =_xlfn.LET(_xlpm.v,_xlfn.XLOOKUP(F43,题库数据!$A$5:$A$104,题库数据!$K$5:$K$104,""),IF(OR(_xlpm.v="",_xlpm.v=0),"",_xlpm.v)) -> This solution will meet the company's requirements in a cost-effective manner because it uses a serverless architecture with AWS Lambda to convert the files and store them in S3. The Lambda function will automatically scale to meet the demand for file conversions and S3 will automatically scale to store the original and converted files as needed.该解决方案将以经济高效的方式满足公司的要求,因为它使用了带有AWS Lambda的无服务器架构来转换文件并将其存储在S3中。Lambda功能将自动缩放以满足文件转换的需求,S3将根据需要自动缩放以存储原始文件和转换后的文件。
D44: {=_xlfn.LET(_xlpm.v,INDEX($B:$B, 4 + INT((ROW()-4)/13)*13 + 8), IF(_xlpm.v=0,"",_xlpm.v))} | F44: =4 -> 4 | G44: =_xlfn.XLOOKUP($F44,题库数据!$A$5:$A$104,题库数据!$J$5:$J$104,"") -> A | H44: =_xlfn.LET(_xlpm.v,_xlfn.XLOOKUP(F44,题库数据!$A$5:$A$104,题库数据!$K$5:$K$104,""),IF(OR(_xlpm.v="",_xlpm.v=0),"",_xlpm.v)) -> This solution will meet the company's requirements in a cost-effective manner because it uses a serverless architecture with AWS Lambda to convert the files and store them in S3. The Lambda function will automatically scale to meet the demand for file conversions and S3 will automatically scale to store the original and converted files as needed.该解决方案将以经济高效的方式满足公司的要求,因为它使用了带有AWS Lambda的无服务器架构来转换文件并将其存储在S3中。Lambda功能将自动缩放以满足文件转换的需求,S3将根据需要自动缩放以存储原始文件和转换后的文件。
A45: A: | B45: =_xlfn.XLOOKUP($F45,题库[题号],题库[选项A]) -> 将 pdf 文件保存到 Amazon S3.配置 S3 PUT 事件以调用 AWS Lambda 函数将文件转换为 jpg 格式并将它们存储回 Amazon S3. | D45: {=_xlfn.LET(_xlpm.v,INDEX($B:$B, 4 + INT((ROW()-4)/13)*13 + 8), IF(_xlpm.v=0,"",_xlpm.v))} | F45: =4 -> 4 | G45: =_xlfn.XLOOKUP($F45,题库数据!$A$5:$A$104,题库数据!$J$5:$J$104,"") -> A | H45: =_xlfn.LET(_xlpm.v,_xlfn.XLOOKUP(F45,题库数据!$A$5:$A$104,题库数据!$K$5:$K$104,""),IF(OR(_xlpm.v="",_xlpm.v=0),"",_xlpm.v)) -> This solution will meet the company's requirements in a cost-effective manner because it uses a serverless architecture with AWS Lambda to convert the files and store them in S3. The Lambda function will automatically scale to meet the demand for file conversions and S3 will automatically scale to store the original and converted files as needed.该解决方案将以经济高效的方式满足公司的要求,因为它使用了带有AWS Lambda的无服务器架构来转换文件并将其存储在S3中。Lambda功能将自动缩放以满足文件转换的需求,S3将根据需要自动缩放以存储原始文件和转换后的文件。
A46: B: | B46: =_xlfn.XLOOKUP($F46,题库[题号],题库[选项B]) -> 将 pdf 文件保存到 Amazon DynamoDB.使用 DynamoDB Streams 功能调用 AWS Lambda 函数将文件转换为 jpg 格式并将它们存储在 DynamoDB 中. | D46: {=_xlfn.LET(_xlpm.v,INDEX($B:$B, 4 + INT((ROW()-4)/13)*13 + 8), IF(_xlpm.v=0,"",_xlpm.v))} | F46: =4 -> 4 | G46: =_xlfn.XLOOKUP($F46,题库数据!$A$5:$A$104,题库数据!$J$5:$J$104,"") -> A | H46: =_xlfn.LET(_xlpm.v,_xlfn.XLOOKUP(F46,题库数据!$A$5:$A$104,题库数据!$K$5:$K$104,""),IF(OR(_xlpm.v="",_xlpm.v=0),"",_xlpm.v)) -> This solution will meet the company's requirements in a cost-effective manner because it uses a serverless architecture with AWS Lambda to convert the files and store them in S3. The Lambda function will automatically scale to meet the demand for file conversions and S3 will automatically scale to store the original and converted files as needed.该解决方案将以经济高效的方式满足公司的要求,因为它使用了带有AWS Lambda的无服务器架构来转换文件并将其存储在S3中。Lambda功能将自动缩放以满足文件转换的需求,S3将根据需要自动缩放以存储原始文件和转换后的文件。
A47: C: | B47: =_xlfn.XLOOKUP($F47,题库[题号],题库[选项C]) -> 将 .pdf 文件上传到包含 Amazon EC2 实例的 AWS Elastic Beanstalk 应用程序.Amazon Elastic Block Store (Amazon EBS) 存储和 Auto Scaling 组.在 EC2 实例中使用程序将文件转换为 jpg 格式保存.EBS 商店中的 pdf 文件和 .jpg 文件. | D47: {=_xlfn.LET(_xlpm.v,INDEX($B:$B, 4 + INT((ROW()-4)/13)*13 + 8), IF(_xlpm.v=0,"",_xlpm.v))} | F47: =4 -> 4 | G47: =_xlfn.XLOOKUP($F47,题库数据!$A$5:$A$104,题库数据!$J$5:$J$104,"") -> A | H47: =_xlfn.LET(_xlpm.v,_xlfn.XLOOKUP(F47,题库数据!$A$5:$A$104,题库数据!$K$5:$K$104,""),IF(OR(_xlpm.v="",_xlpm.v=0),"",_xlpm.v)) -> This solution will meet the company's requirements in a cost-effective manner because it uses a serverless architecture with AWS Lambda to convert the files and store them in S3. The Lambda function will automatically scale to meet the demand for file conversions and S3 will automatically scale to store the original and converted files as needed.该解决方案将以经济高效的方式满足公司的要求,因为它使用了带有AWS Lambda的无服务器架构来转换文件并将其存储在S3中。Lambda功能将自动缩放以满足文件转换的需求,S3将根据需要自动缩放以存储原始文件和转换后的文件。
A48: D: | B48: =_xlfn.XLOOKUP($F48,题库[题号],题库[选项D]) -> 将 .pdf 文件上传到包含 Amazon EC2 实例.Amazon Elastic File System (Amazon EFS) 存储和 Auto Scaling 组的 AWS Elastic Beanstalk 应用程序.使用 EC2 实例中的程序将文件转换为 jpg 格式保存EBS 商店中的 pdf 文件和 jpg 文件. | D48: {=_xlfn.LET(_xlpm.v,INDEX($B:$B, 4 + INT((ROW()-4)/13)*13 + 8), IF(_xlpm.v=0,"",_xlpm.v))} | F48: =4 -> 4 | G48: =_xlfn.XLOOKUP($F48,题库数据!$A$5:$A$104,题库数据!$J$5:$J$104,"") -> A | H48: =_xlfn.LET(_xlpm.v,_xlfn.XLOOKUP(F48,题库数据!$A$5:$A$104,题库数据!$K$5:$K$104,""),IF(OR(_xlpm.v="",_xlpm.v=0),"",_xlpm.v)) -> This solution will meet the company's requirements in a cost-effective manner because it uses a serverless architecture with AWS Lambda to convert the files and store them in S3. The Lambda function will automatically scale to meet the demand for file conversions and S3 will automatically scale to store the original and converted files as needed.该解决方案将以经济高效的方式满足公司的要求,因为它使用了带有AWS Lambda的无服务器架构来转换文件并将其存储在S3中。Lambda功能将自动缩放以满足文件转换的需求,S3将根据需要自动缩放以存储原始文件和转换后的文件。
B49: =_xlfn.LET(_xlpm.v,_xlfn.XLOOKUP($F49,题库[题号],题库[选项E],""),IF(OR(_xlpm.v="",_xlpm.v=0),"",_xlpm.v)) | D49: {=_xlfn.LET(_xlpm.v,INDEX($B:$B, 4 + INT((ROW()-4)/13)*13 + 8), IF(_xlpm.v=0,"",_xlpm.v))} | F49: =4 -> 4 | G49: =_xlfn.XLOOKUP($F49,题库数据!$A$5:$A$104,题库数据!$J$5:$J$104,"") -> A | H49: =_xlfn.LET(_xlpm.v,_xlfn.XLOOKUP(F49,题库数据!$A$5:$A$104,题库数据!$K$5:$K$104,""),IF(OR(_xlpm.v="",_xlpm.v=0),"",_xlpm.v)) -> This solution will meet the company's requirements in a cost-effective manner because it uses a serverless architecture with AWS Lambda to convert the files and store them in S3. The Lambda function will automatically scale to meet the demand for file conversions and S3 will automatically scale to store the original and converted files as needed.该解决方案将以经济高效的方式满足公司的要求,因为它使用了带有AWS Lambda的无服务器架构来转换文件并将其存储在S3中。Lambda功能将自动缩放以满足文件转换的需求,S3将根据需要自动缩放以存储原始文件和转换后的文件。
B50: =_xlfn.LET(_xlpm.v,_xlfn.XLOOKUP($F50,题库[题号],题库[选项F],""),IF(OR(_xlpm.v="",_xlpm.v=0),"",_xlpm.v)) | D50: {=_xlfn.LET(_xlpm.v,INDEX($B:$B, 4 + INT((ROW()-4)/13)*13 + 8), IF(_xlpm.v=0,"",_xlpm.v))} | F50: =4 -> 4 | G50: =_xlfn.XLOOKUP($F50,题库数据!$A$5:$A$104,题库数据!$J$5:$J$104,"") -> A | H50: =_xlfn.LET(_xlpm.v,_xlfn.XLOOKUP(F50,题库数据!$A$5:$A$104,题库数据!$K$5:$K$104,""),IF(OR(_xlpm.v="",_xlpm.v=0),"",_xlpm.v)) -> This solution will meet the company's requirements in a cost-effective manner because it uses a serverless architecture with AWS Lambda to convert the files and store them in S3. The Lambda function will automatically scale to meet the demand for file conversions and S3 will automatically scale to store the original and converted files as needed.该解决方案将以经济高效的方式满足公司的要求,因为它使用了带有AWS Lambda的无服务器架构来转换文件并将其存储在S3中。Lambda功能将自动缩放以满足文件转换的需求,S3将根据需要自动缩放以存储原始文件和转换后的文件。
A51: 你的答案 | D51: {=_xlfn.LET(_xlpm.v,INDEX($B:$B, 4 + INT((ROW()-4)/13)*13 + 8), IF(_xlpm.v=0,"",_xlpm.v))} | F51: =4 -> 4 | G51: =_xlfn.XLOOKUP($F51,题库数据!$A$5:$A$104,题库数据!$J$5:$J$104,"") -> A | H51: =_xlfn.LET(_xlpm.v,_xlfn.XLOOKUP(F51,题库数据!$A$5:$A$104,题库数据!$K$5:$K$104,""),IF(OR(_xlpm.v="",_xlpm.v=0),"",_xlpm.v)) -> This solution will meet the company's requirements in a cost-effective manner because it uses a serverless architecture with AWS Lambda to convert the files and store them in S3. The Lambda function will automatically scale to meet the demand for file conversions and S3 will automatically scale to store the original and converted files as needed.该解决方案将以经济高效的方式满足公司的要求,因为它使用了带有AWS Lambda的无服务器架构来转换文件并将其存储在S3中。Lambda功能将自动缩放以满足文件转换的需求,S3将根据需要自动缩放以存储原始文件和转换后的文件。
A52: 结果 | B52: =_xlfn.LET(_xlpm.inp,$B$51,_xlpm.nInp,_xlfn.LET(_xlpm.raw,UPPER(TRIM($B$51)),_xlpm.clean,SUBSTITUTE(SUBSTITUTE(SUBSTITUTE(SUBSTITUTE(SUBSTITUTE(_xlpm.raw,"，",","),"、",","),"；",",")," ",""),",",""),_xlfn.TEXTJOIN(",",TRUE,IF(ISNUMBER(SEARCH("A",_xlpm.clean)),"A",""),IF(ISNUMBER(SEARCH("B",_xlpm.clean)),"B",""),IF(ISNUMBER(SEARCH("C",_xlpm.clean)),"C",""),IF(ISNUMBER(SEARCH("D",_xlpm.clean)),"D",""),IF(ISNUMBER(SEARCH("E",_xlpm.clean)),"E",""),IF(ISNUMBER(SEARCH("F",_xlpm.clean)),"F",""))),_xlpm.nStd,_xlfn.LET(_xlpm.raw,UPPER(TRIM($G$43)),_xlpm.clean,SUBSTITUTE(SUBSTITUTE(SUBSTITUTE(SUBSTITUTE(SUBSTITUTE(_xlpm.raw,"，",","),"、",","),"；",",")," ",""),",",""),_xlfn.TEXTJOIN(",",TRUE,IF(ISNUMBER(SEARCH("A",_xlpm.clean)),"A",""),IF(ISNUMBER(SEARCH("B",_xlpm.clean)),"B",""),IF(ISNUMBER(SEARCH("C",_xlpm.clean)),"C",""),IF(ISNUMBER(SEARCH("D",_xlpm.clean)),"D",""),IF(ISNUMBER(SEARCH("E",_xlpm.clean)),"E",""),IF(ISNUMBER(SEARCH("F",_xlpm.clean)),"F",""))),IF(LEN(TRIM(_xlpm.inp))=0,"",IF(AND(_xlpm.nInp<>"",_xlpm.nStd<>"",_xlpm.nInp=_xlpm.nStd),"✅正确","❌错误"))) | D52: {=_xlfn.LET(_xlpm.v,INDEX($B:$B, 4 + INT((ROW()-4)/13)*13 + 8), IF(_xlpm.v=0,"",_xlpm.v))} | F52: =4 -> 4 | G52: =_xlfn.XLOOKUP($F52,题库数据!$A$5:$A$104,题库数据!$J$5:$J$104,"") -> A | H52: =_xlfn.LET(_xlpm.v,_xlfn.XLOOKUP(F52,题库数据!$A$5:$A$104,题库数据!$K$5:$K$104,""),IF(OR(_xlpm.v="",_xlpm.v=0),"",_xlpm.v)) -> This solution will meet the company's requirements in a cost-effective manner because it uses a serverless architecture with AWS Lambda to convert the files and store them in S3. The Lambda function will automatically scale to meet the demand for file conversions and S3 will automatically scale to store the original and converted files as needed.该解决方案将以经济高效的方式满足公司的要求,因为它使用了带有AWS Lambda的无服务器架构来转换文件并将其存储在S3中。Lambda功能将自动缩放以满足文件转换的需求,S3将根据需要自动缩放以存储原始文件和转换后的文件。
A53: 正确答案 | B53: =_xlfn.LET(_xlpm.inp,$B$51,_xlpm.nStd,_xlfn.LET(_xlpm.raw,UPPER(TRIM($G$43)),_xlpm.clean,SUBSTITUTE(SUBSTITUTE(SUBSTITUTE(SUBSTITUTE(SUBSTITUTE(_xlpm.raw,"，",","),"、",","),"；",",")," ",""),",",""),_xlfn.TEXTJOIN(",",TRUE,IF(ISNUMBER(SEARCH("A",_xlpm.clean)),"A",""),IF(ISNUMBER(SEARCH("B",_xlpm.clean)),"B",""),IF(ISNUMBER(SEARCH("C",_xlpm.clean)),"C",""),IF(ISNUMBER(SEARCH("D",_xlpm.clean)),"D",""),IF(ISNUMBER(SEARCH("E",_xlpm.clean)),"E",""),IF(ISNUMBER(SEARCH("F",_xlpm.clean)),"F",""))),IF(OR(LEN(TRIM(_xlpm.inp))=0,_xlpm.nStd=""),"",_xlpm.nStd)) | D53: {=_xlfn.LET(_xlpm.v,INDEX($B:$B, 4 + INT((ROW()-4)/13)*13 + 8), IF(_xlpm.v=0,"",_xlpm.v))} | F53: =4 -> 4 | G53: =_xlfn.XLOOKUP($F53,题库数据!$A$5:$A$104,题库数据!$J$5:$J$104,"") -> A | H53: =_xlfn.LET(_xlpm.v,_xlfn.XLOOKUP(F53,题库数据!$A$5:$A$104,题库数据!$K$5:$K$104,""),IF(OR(_xlpm.v="",_xlpm.v=0),"",_xlpm.v)) -> This solution will meet the company's requirements in a cost-effective manner because it uses a serverless architecture with AWS Lambda to convert the files and store them in S3. The Lambda function will automatically scale to meet the demand for file conversions and S3 will automatically scale to store the original and converted files as needed.该解决方案将以经济高效的方式满足公司的要求,因为它使用了带有AWS Lambda的无服务器架构来转换文件并将其存储在S3中。Lambda功能将自动缩放以满足文件转换的需求,S3将根据需要自动缩放以存储原始文件和转换后的文件。
A54: 解析 | B54: =_xlfn.LET(_xlpm.inp,$B$51,_xlpm.p,$H$43,IF(OR(LEN(TRIM(_xlpm.inp))=0,LEN(TRIM(_xlpm.p))=0,_xlpm.p=0),"",_xlpm.p)) | D54: {=_xlfn.LET(_xlpm.v,INDEX($B:$B, 4 + INT((ROW()-4)/13)*13 + 8), IF(_xlpm.v=0,"",_xlpm.v))} | F54: =4 -> 4 | G54: =_xlfn.XLOOKUP($F54,题库数据!$A$5:$A$104,题库数据!$J$5:$J$104,"") -> A | H54: =_xlfn.LET(_xlpm.v,_xlfn.XLOOKUP(F54,题库数据!$A$5:$A$104,题库数据!$K$5:$K$104,""),IF(OR(_xlpm.v="",_xlpm.v=0),"",_xlpm.v)) -> This solution will meet the company's requirements in a cost-effective manner because it uses a serverless architecture with AWS Lambda to convert the files and store them in S3. The Lambda function will automatically scale to meet the demand for file conversions and S3 will automatically scale to store the original and converted files as needed.该解决方案将以经济高效的方式满足公司的要求,因为它使用了带有AWS Lambda的无服务器架构来转换文件并将其存储在S3中。Lambda功能将自动缩放以满足文件转换的需求,S3将根据需要自动缩放以存储原始文件和转换后的文件。
D55: {=_xlfn.LET(_xlpm.v,INDEX($B:$B, 4 + INT((ROW()-4)/13)*13 + 8), IF(_xlpm.v=0,"",_xlpm.v))} | F55: =4 -> 4 | G55: =_xlfn.XLOOKUP($F55,题库数据!$A$5:$A$104,题库数据!$J$5:$J$104,"") -> A | H55: =_xlfn.LET(_xlpm.v,_xlfn.XLOOKUP(F55,题库数据!$A$5:$A$104,题库数据!$K$5:$K$104,""),IF(OR(_xlpm.v="",_xlpm.v=0),"",_xlpm.v)) -> This solution will meet the company's requirements in a cost-effective manner because it uses a serverless architecture with AWS Lambda to convert the files and store them in S3. The Lambda function will automatically scale to meet the demand for file conversions and S3 will automatically scale to store the original and converted files as needed.该解决方案将以经济高效的方式满足公司的要求,因为它使用了带有AWS Lambda的无服务器架构来转换文件并将其存储在S3中。Lambda功能将自动缩放以满足文件转换的需求,S3将根据需要自动缩放以存储原始文件和转换后的文件。
A56: 题目 5： | B56: 一家公司在本地运行的 Windows 文件服务器上拥有超过5 TB 的文件数据用户和应用程序每天与数据进行交互该公司正在将其 Windows 工作负载转移到 AWS.随着公司继续这一过程,该公司需要访问以最小的延迟连接到AWS 和本地文件存储.公司需要一种解决方案,最大限度地减少运营开销,并且不需要对现有文件访问模式进行重大更改.公司使用 AWS Site-to-Site VPN 连接来连接到 AWS.解决方案架构师应该怎么做才能满足这些要求? | D56: {=_xlfn.LET(_xlpm.v,INDEX($B:$B, 4 + INT((ROW()-4)/13)*13 + 8), IF(_xlpm.v=0,"",_xlpm.v))} | F56: =5 -> 5 | G56: =_xlfn.XLOOKUP($F56,题库数据!$A$5:$A$104,题库数据!$J$5:$J$104,"") -> D | H56: =_xlfn.LET(_xlpm.v,_xlfn.XLOOKUP(F56,题库数据!$A$5:$A$104,题库数据!$K$5:$K$104,""),IF(OR(_xlpm.v="",_xlpm.v=0),"",_xlpm.v))
D57: {=_xlfn.LET(_xlpm.v,INDEX($B:$B, 4 + INT((ROW()-4)/13)*13 + 8), IF(_xlpm.v=0,"",_xlpm.v))} | F57: =5 -> 5 | G57: =_xlfn.XLOOKUP($F57,题库数据!$A$5:$A$104,题库数据!$J$5:$J$104,"") -> D | H57: =_xlfn.LET(_xlpm.v,_xlfn.XLOOKUP(F57,题库数据!$A$5:$A$104,题库数据!$K$5:$K$104,""),IF(OR(_xlpm.v="",_xlpm.v=0),"",_xlpm.v))
A58: A: | B58: =_xlfn.XLOOKUP($F58,题库[题号],题库[选项A]) -> 在 AWS 上部署和配置 Amazon FSx for Windows File Server.将本地文件数据移动到 FSx for Windows File Server.重新配置工作负载以在 AWS 上使用 FSx for Windows File Server. | D58: {=_xlfn.LET(_xlpm.v,INDEX($B:$B, 4 + INT((ROW()-4)/13)*13 + 8), IF(_xlpm.v=0,"",_xlpm.v))} | F58: =5 -> 5 | G58: =_xlfn.XLOOKUP($F58,题库数据!$A$5:$A$104,题库数据!$J$5:$J$104,"") -> D | H58: =_xlfn.LET(_xlpm.v,_xlfn.XLOOKUP(F58,题库数据!$A$5:$A$104,题库数据!$K$5:$K$104,""),IF(OR(_xlpm.v="",_xlpm.v=0),"",_xlpm.v))
A59: B: | B59: =_xlfn.XLOOKUP($F59,题库[题号],题库[选项B]) -> 在本地部署和配置 Amazon S3 文件网关.将本地文件数据移动到 S3 文件网关,重新配置本地工作负载和云工作负载以使用 S3 文件网关 | D59: {=_xlfn.LET(_xlpm.v,INDEX($B:$B, 4 + INT((ROW()-4)/13)*13 + 8), IF(_xlpm.v=0,"",_xlpm.v))} | F59: =5 -> 5 | G59: =_xlfn.XLOOKUP($F59,题库数据!$A$5:$A$104,题库数据!$J$5:$J$104,"") -> D | H59: =_xlfn.LET(_xlpm.v,_xlfn.XLOOKUP(F59,题库数据!$A$5:$A$104,题库数据!$K$5:$K$104,""),IF(OR(_xlpm.v="",_xlpm.v=0),"",_xlpm.v))
A60: C: | B60: =_xlfn.XLOOKUP($F60,题库[题号],题库[选项C]) -> 在本地部署和配置 Amazon S3 文件网关.将本地文件数据移动到 Amazon S3.重新配置工作负载以直接使用 Amazon S3 或 S3 文件网关,具体取决于每个工作负载的位置. | D60: {=_xlfn.LET(_xlpm.v,INDEX($B:$B, 4 + INT((ROW()-4)/13)*13 + 8), IF(_xlpm.v=0,"",_xlpm.v))} | F60: =5 -> 5 | G60: =_xlfn.XLOOKUP($F60,题库数据!$A$5:$A$104,题库数据!$J$5:$J$104,"") -> D | H60: =_xlfn.LET(_xlpm.v,_xlfn.XLOOKUP(F60,题库数据!$A$5:$A$104,题库数据!$K$5:$K$104,""),IF(OR(_xlpm.v="",_xlpm.v=0),"",_xlpm.v))
A61: D: | B61: =_xlfn.XLOOKUP($F61,题库[题号],题库[选项D]) -> 在 AWS 上部署和配置 Amazon FSx for Windows File Server.在本地部署和配置 Amazon FSx 文件网关.将本地文件数据移动到 FSx 文件网关.配置云工作负载以使用 FSx for Windows File Server AWS.配置本地工作负载以使用 FSx 文件网关. | D61: {=_xlfn.LET(_xlpm.v,INDEX($B:$B, 4 + INT((ROW()-4)/13)*13 + 8), IF(_xlpm.v=0,"",_xlpm.v))} | F61: =5 -> 5 | G61: =_xlfn.XLOOKUP($F61,题库数据!$A$5:$A$104,题库数据!$J$5:$J$104,"") -> D | H61: =_xlfn.LET(_xlpm.v,_xlfn.XLOOKUP(F61,题库数据!$A$5:$A$104,题库数据!$K$5:$K$104,""),IF(OR(_xlpm.v="",_xlpm.v=0),"",_xlpm.v))
B62: =_xlfn.LET(_xlpm.v,_xlfn.XLOOKUP($F62,题库[题号],题库[选项E],""),IF(OR(_xlpm.v="",_xlpm.v=0),"",_xlpm.v)) | D62: {=_xlfn.LET(_xlpm.v,INDEX($B:$B, 4 + INT((ROW()-4)/13)*13 + 8), IF(_xlpm.v=0,"",_xlpm.v))} | F62: =5 -> 5 | G62: =_xlfn.XLOOKUP($F62,题库数据!$A$5:$A$104,题库数据!$J$5:$J$104,"") -> D | H62: =_xlfn.LET(_xlpm.v,_xlfn.XLOOKUP(F62,题库数据!$A$5:$A$104,题库数据!$K$5:$K$104,""),IF(OR(_xlpm.v="",_xlpm.v=0),"",_xlpm.v))
B63: =_xlfn.LET(_xlpm.v,_xlfn.XLOOKUP($F63,题库[题号],题库[选项F],""),IF(OR(_xlpm.v="",_xlpm.v=0),"",_xlpm.v)) | D63: {=_xlfn.LET(_xlpm.v,INDEX($B:$B, 4 + INT((ROW()-4)/13)*13 + 8), IF(_xlpm.v=0,"",_xlpm.v))} | F63: =5 -> 5 | G63: =_xlfn.XLOOKUP($F63,题库数据!$A$5:$A$104,题库数据!$J$5:$J$104,"") -> D | H63: =_xlfn.LET(_xlpm.v,_xlfn.XLOOKUP(F63,题库数据!$A$5:$A$104,题库数据!$K$5:$K$104,""),IF(OR(_xlpm.v="",_xlpm.v=0),"",_xlpm.v))
A64: 你的答案 | D64: {=_xlfn.LET(_xlpm.v,INDEX($B:$B, 4 + INT((ROW()-4)/13)*13 + 8), IF(_xlpm.v=0,"",_xlpm.v))} | F64: =5 -> 5 | G64: =_xlfn.XLOOKUP($F64,题库数据!$A$5:$A$104,题库数据!$J$5:$J$104,"") -> D | H64: =_xlfn.LET(_xlpm.v,_xlfn.XLOOKUP(F64,题库数据!$A$5:$A$104,题库数据!$K$5:$K$104,""),IF(OR(_xlpm.v="",_xlpm.v=0),"",_xlpm.v))
A65: 结果 | B65: =_xlfn.LET(_xlpm.inp,$B$64,_xlpm.nInp,_xlfn.LET(_xlpm.raw,UPPER(TRIM($B$64)),_xlpm.clean,SUBSTITUTE(SUBSTITUTE(SUBSTITUTE(SUBSTITUTE(SUBSTITUTE(_xlpm.raw,"，",","),"、",","),"；",",")," ",""),",",""),_xlfn.TEXTJOIN(",",TRUE,IF(ISNUMBER(SEARCH("A",_xlpm.clean)),"A",""),IF(ISNUMBER(SEARCH("B",_xlpm.clean)),"B",""),IF(ISNUMBER(SEARCH("C",_xlpm.clean)),"C",""),IF(ISNUMBER(SEARCH("D",_xlpm.clean)),"D",""),IF(ISNUMBER(SEARCH("E",_xlpm.clean)),"E",""),IF(ISNUMBER(SEARCH("F",_xlpm.clean)),"F",""))),_xlpm.nStd,_xlfn.LET(_xlpm.raw,UPPER(TRIM($G$56)),_xlpm.clean,SUBSTITUTE(SUBSTITUTE(SUBSTITUTE(SUBSTITUTE(SUBSTITUTE(_xlpm.raw,"，",","),"、",","),"；",",")," ",""),",",""),_xlfn.TEXTJOIN(",",TRUE,IF(ISNUMBER(SEARCH("A",_xlpm.clean)),"A",""),IF(ISNUMBER(SEARCH("B",_xlpm.clean)),"B",""),IF(ISNUMBER(SEARCH("C",_xlpm.clean)),"C",""),IF(ISNUMBER(SEARCH("D",_xlpm.clean)),"D",""),IF(ISNUMBER(SEARCH("E",_xlpm.clean)),"E",""),IF(ISNUMBER(SEARCH("F",_xlpm.clean)),"F",""))),IF(LEN(TRIM(_xlpm.inp))=0,"",IF(AND(_xlpm.nInp<>"",_xlpm.nStd<>"",_xlpm.nInp=_xlpm.nStd),"✅正确","❌错误"))) | D65: {=_xlfn.LET(_xlpm.v,INDEX($B:$B, 4 + INT((ROW()-4)/13)*13 + 8), IF(_xlpm.v=0,"",_xlpm.v))} | F65: =5 -> 5 | G65: =_xlfn.XLOOKUP($F65,题库数据!$A$5:$A$104,题库数据!$J$5:$J$104,"") -> D | H65: =_xlfn.LET(_xlpm.v,_xlfn.XLOOKUP(F65,题库数据!$A$5:$A$104,题库数据!$K$5:$K$104,""),IF(OR(_xlpm.v="",_xlpm.v=0),"",_xlpm.v))
A66: 正确答案 | B66: =_xlfn.LET(_xlpm.inp,$B$64,_xlpm.nStd,_xlfn.LET(_xlpm.raw,UPPER(TRIM($G$56)),_xlpm.clean,SUBSTITUTE(SUBSTITUTE(SUBSTITUTE(SUBSTITUTE(SUBSTITUTE(_xlpm.raw,"，",","),"、",","),"；",",")," ",""),",",""),_xlfn.TEXTJOIN(",",TRUE,IF(ISNUMBER(SEARCH("A",_xlpm.clean)),"A",""),IF(ISNUMBER(SEARCH("B",_xlpm.clean)),"B",""),IF(ISNUMBER(SEARCH("C",_xlpm.clean)),"C",""),IF(ISNUMBER(SEARCH("D",_xlpm.clean)),"D",""),IF(ISNUMBER(SEARCH("E",_xlpm.clean)),"E",""),IF(ISNUMBER(SEARCH("F",_xlpm.clean)),"F",""))),IF(OR(LEN(TRIM(_xlpm.inp))=0,_xlpm.nStd=""),"",_xlpm.nStd)) | D66: {=_xlfn.LET(_xlpm.v,INDEX($B:$B, 4 + INT((ROW()-4)/13)*13 + 8), IF(_xlpm.v=0,"",_xlpm.v))} | F66: =5 -> 5 | G66: =_xlfn.XLOOKUP($F66,题库数据!$A$5:$A$104,题库数据!$J$5:$J$104,"") -> D | H66: =_xlfn.LET(_xlpm.v,_xlfn.XLOOKUP(F66,题库数据!$A$5:$A$104,题库数据!$K$5:$K$104,""),IF(OR(_xlpm.v="",_xlpm.v=0),"",_xlpm.v))
A67: 解析 | B67: =_xlfn.LET(_xlpm.inp,$B$64,_xlpm.p,$H$56,IF(OR(LEN(TRIM(_xlpm.inp))=0,LEN(TRIM(_xlpm.p))=0,_xlpm.p=0),"",_xlpm.p)) | D67: {=_xlfn.LET(_xlpm.v,INDEX($B:$B, 4 + INT((ROW()-4)/13)*13 + 8), IF(_xlpm.v=0,"",_xlpm.v))} | F67: =5 -> 5 | G67: =_xlfn.XLOOKUP($F67,题库数据!$A$5:$A$104,题库数据!$J$5:$J$104,"") -> D | H67: =_xlfn.LET(_xlpm.v,_xlfn.XLOOKUP(F67,题库数据!$A$5:$A$104,题库数据!$K$5:$K$104,""),IF(OR(_xlpm.v="",_xlpm.v=0),"",_xlpm.v))
D68: {=_xlfn.LET(_xlpm.v,INDEX($B:$B, 4 + INT((ROW()-4)/13)*13 + 8), IF(_xlpm.v=0,"",_xlpm.v))} | F68: =5 -> 5 | G68: =_xlfn.XLOOKUP($F68,题库数据!$A$5:$A$104,题库数据!$J$5:$J$104,"") -> D | H68: =_xlfn.LET(_xlpm.v,_xlfn.XLOOKUP(F68,题库数据!$A$5:$A$104,题库数据!$K$5:$K$104,""),IF(OR(_xlpm.v="",_xlpm.v=0),"",_xlpm.v))
A69: 题目 6： | B69: 一家医院最近使用Amazon API Gateway 和AWS Lambda 部署了一个RESTful API.该医院使用API Gateway 和Lambda 上传PDF 格式和JPEG 格式的报告.医院需要修改Lambda 代码以识别受保护的健康信息(PHI)在报告中.哪种解决方案将以最少的运营开销满足这些要求? | D69: {=_xlfn.LET(_xlpm.v,INDEX($B:$B, 4 + INT((ROW()-4)/13)*13 + 8), IF(_xlpm.v=0,"",_xlpm.v))} | F69: =6 -> 6 | G69: =_xlfn.XLOOKUP($F69,题库数据!$A$5:$A$104,题库数据!$J$5:$J$104,"") -> C | H69: =_xlfn.LET(_xlpm.v,_xlfn.XLOOKUP(F69,题库数据!$A$5:$A$104,题库数据!$K$5:$K$104,""),IF(OR(_xlpm.v="",_xlpm.v=0),"",_xlpm.v)) -> Textract and Comprehend 符合 HIPPA.https://aws.amazon.com/blogs/machine-learning/amazon-textract-is-now-hipaaeligible/
D70: {=_xlfn.LET(_xlpm.v,INDEX($B:$B, 4 + INT((ROW()-4)/13)*13 + 8), IF(_xlpm.v=0,"",_xlpm.v))} | F70: =6 -> 6 | G70: =_xlfn.XLOOKUP($F70,题库数据!$A$5:$A$104,题库数据!$J$5:$J$104,"") -> C | H70: =_xlfn.LET(_xlpm.v,_xlfn.XLOOKUP(F70,题库数据!$A$5:$A$104,题库数据!$K$5:$K$104,""),IF(OR(_xlpm.v="",_xlpm.v=0),"",_xlpm.v)) -> Textract and Comprehend 符合 HIPPA.https://aws.amazon.com/blogs/machine-learning/amazon-textract-is-now-hipaaeligible/
A71: A: | B71: =_xlfn.XLOOKUP($F71,题库[题号],题库[选项A]) -> 使用现有的 Python 库从报告中提取文本并从提取的文本中识别 PHI. | D71: {=_xlfn.LET(_xlpm.v,INDEX($B:$B, 4 + INT((ROW()-4)/13)*13 + 8), IF(_xlpm.v=0,"",_xlpm.v))} | F71: =6 -> 6 | G71: =_xlfn.XLOOKUP($F71,题库数据!$A$5:$A$104,题库数据!$J$5:$J$104,"") -> C | H71: =_xlfn.LET(_xlpm.v,_xlfn.XLOOKUP(F71,题库数据!$A$5:$A$104,题库数据!$K$5:$K$104,""),IF(OR(_xlpm.v="",_xlpm.v=0),"",_xlpm.v)) -> Textract and Comprehend 符合 HIPPA.https://aws.amazon.com/blogs/machine-learning/amazon-textract-is-now-hipaaeligible/
A72: B: | B72: =_xlfn.XLOOKUP($F72,题库[题号],题库[选项B]) -> 使用 Amazon Textract 从报告中提取文本.使用 Amazon SageMaker 从提取的文本中识别 PHI. | D72: {=_xlfn.LET(_xlpm.v,INDEX($B:$B, 4 + INT((ROW()-4)/13)*13 + 8), IF(_xlpm.v=0,"",_xlpm.v))} | F72: =6 -> 6 | G72: =_xlfn.XLOOKUP($F72,题库数据!$A$5:$A$104,题库数据!$J$5:$J$104,"") -> C | H72: =_xlfn.LET(_xlpm.v,_xlfn.XLOOKUP(F72,题库数据!$A$5:$A$104,题库数据!$K$5:$K$104,""),IF(OR(_xlpm.v="",_xlpm.v=0),"",_xlpm.v)) -> Textract and Comprehend 符合 HIPPA.https://aws.amazon.com/blogs/machine-learning/amazon-textract-is-now-hipaaeligible/
A73: C: | B73: =_xlfn.XLOOKUP($F73,题库[题号],题库[选项C]) -> 使用 Amazon Textract 从报告中提取文本.使用 Amazon Comprehend Medical 从提取的文本中识别 PHI. | D73: {=_xlfn.LET(_xlpm.v,INDEX($B:$B, 4 + INT((ROW()-4)/13)*13 + 8), IF(_xlpm.v=0,"",_xlpm.v))} | F73: =6 -> 6 | G73: =_xlfn.XLOOKUP($F73,题库数据!$A$5:$A$104,题库数据!$J$5:$J$104,"") -> C | H73: =_xlfn.LET(_xlpm.v,_xlfn.XLOOKUP(F73,题库数据!$A$5:$A$104,题库数据!$K$5:$K$104,""),IF(OR(_xlpm.v="",_xlpm.v=0),"",_xlpm.v)) -> Textract and Comprehend 符合 HIPPA.https://aws.amazon.com/blogs/machine-learning/amazon-textract-is-now-hipaaeligible/
A74: D: | B74: =_xlfn.XLOOKUP($F74,题库[题号],题库[选项D]) -> 使用 Amazon Rekognition 从报告中提取文本.使用 Amazon Comprehend Medical 从提取的文本中识别 PHI. | D74: {=_xlfn.LET(_xlpm.v,INDEX($B:$B, 4 + INT((ROW()-4)/13)*13 + 8), IF(_xlpm.v=0,"",_xlpm.v))} | F74: =6 -> 6 | G74: =_xlfn.XLOOKUP($F74,题库数据!$A$5:$A$104,题库数据!$J$5:$J$104,"") -> C | H74: =_xlfn.LET(_xlpm.v,_xlfn.XLOOKUP(F74,题库数据!$A$5:$A$104,题库数据!$K$5:$K$104,""),IF(OR(_xlpm.v="",_xlpm.v=0),"",_xlpm.v)) -> Textract and Comprehend 符合 HIPPA.https://aws.amazon.com/blogs/machine-learning/amazon-textract-is-now-hipaaeligible/
B75: =_xlfn.LET(_xlpm.v,_xlfn.XLOOKUP($F75,题库[题号],题库[选项E],""),IF(OR(_xlpm.v="",_xlpm.v=0),"",_xlpm.v)) | D75: {=_xlfn.LET(_xlpm.v,INDEX($B:$B, 4 + INT((ROW()-4)/13)*13 + 8), IF(_xlpm.v=0,"",_xlpm.v))} | F75: =6 -> 6 | G75: =_xlfn.XLOOKUP($F75,题库数据!$A$5:$A$104,题库数据!$J$5:$J$104,"") -> C | H75: =_xlfn.LET(_xlpm.v,_xlfn.XLOOKUP(F75,题库数据!$A$5:$A$104,题库数据!$K$5:$K$104,""),IF(OR(_xlpm.v="",_xlpm.v=0),"",_xlpm.v)) -> Textract and Comprehend 符合 HIPPA.https://aws.amazon.com/blogs/machine-learning/amazon-textract-is-now-hipaaeligible/
B76: =_xlfn.LET(_xlpm.v,_xlfn.XLOOKUP($F76,题库[题号],题库[选项F],""),IF(OR(_xlpm.v="",_xlpm.v=0),"",_xlpm.v)) | D76: {=_xlfn.LET(_xlpm.v,INDEX($B:$B, 4 + INT((ROW()-4)/13)*13 + 8), IF(_xlpm.v=0,"",_xlpm.v))} | F76: =6 -> 6 | G76: =_xlfn.XLOOKUP($F76,题库数据!$A$5:$A$104,题库数据!$J$5:$J$104,"") -> C | H76: =_xlfn.LET(_xlpm.v,_xlfn.XLOOKUP(F76,题库数据!$A$5:$A$104,题库数据!$K$5:$K$104,""),IF(OR(_xlpm.v="",_xlpm.v=0),"",_xlpm.v)) -> Textract and Comprehend 符合 HIPPA.https://aws.amazon.com/blogs/machine-learning/amazon-textract-is-now-hipaaeligible/
A77: 你的答案 | D77: {=_xlfn.LET(_xlpm.v,INDEX($B:$B, 4 + INT((ROW()-4)/13)*13 + 8), IF(_xlpm.v=0,"",_xlpm.v))} | F77: =6 -> 6 | G77: =_xlfn.XLOOKUP($F77,题库数据!$A$5:$A$104,题库数据!$J$5:$J$104,"") -> C | H77: =_xlfn.LET(_xlpm.v,_xlfn.XLOOKUP(F77,题库数据!$A$5:$A$104,题库数据!$K$5:$K$104,""),IF(OR(_xlpm.v="",_xlpm.v=0),"",_xlpm.v)) -> Textract and Comprehend 符合 HIPPA.https://aws.amazon.com/blogs/machine-learning/amazon-textract-is-now-hipaaeligible/
A78: 结果 | B78: =_xlfn.LET(_xlpm.inp,$B$77,_xlpm.nInp,_xlfn.LET(_xlpm.raw,UPPER(TRIM($B$77)),_xlpm.clean,SUBSTITUTE(SUBSTITUTE(SUBSTITUTE(SUBSTITUTE(SUBSTITUTE(_xlpm.raw,"，",","),"、",","),"；",",")," ",""),",",""),_xlfn.TEXTJOIN(",",TRUE,IF(ISNUMBER(SEARCH("A",_xlpm.clean)),"A",""),IF(ISNUMBER(SEARCH("B",_xlpm.clean)),"B",""),IF(ISNUMBER(SEARCH("C",_xlpm.clean)),"C",""),IF(ISNUMBER(SEARCH("D",_xlpm.clean)),"D",""),IF(ISNUMBER(SEARCH("E",_xlpm.clean)),"E",""),IF(ISNUMBER(SEARCH("F",_xlpm.clean)),"F",""))),_xlpm.nStd,_xlfn.LET(_xlpm.raw,UPPER(TRIM($G$69)),_xlpm.clean,SUBSTITUTE(SUBSTITUTE(SUBSTITUTE(SUBSTITUTE(SUBSTITUTE(_xlpm.raw,"，",","),"、",","),"；",",")," ",""),",",""),_xlfn.TEXTJOIN(",",TRUE,IF(ISNUMBER(SEARCH("A",_xlpm.clean)),"A",""),IF(ISNUMBER(SEARCH("B",_xlpm.clean)),"B",""),IF(ISNUMBER(SEARCH("C",_xlpm.clean)),"C",""),IF(ISNUMBER(SEARCH("D",_xlpm.clean)),"D",""),IF(ISNUMBER(SEARCH("E",_xlpm.clean)),"E",""),IF(ISNUMBER(SEARCH("F",_xlpm.clean)),"F",""))),IF(LEN(TRIM(_xlpm.inp))=0,"",IF(AND(_xlpm.nInp<>"",_xlpm.nStd<>"",_xlpm.nInp=_xlpm.nStd),"✅正确","❌错误"))) | D78: {=_xlfn.LET(_xlpm.v,INDEX($B:$B, 4 + INT((ROW()-4)/13)*13 + 8), IF(_xlpm.v=0,"",_xlpm.v))} | F78: =6 -> 6 | G78: =_xlfn.XLOOKUP($F78,题库数据!$A$5:$A$104,题库数据!$J$5:$J$104,"") -> C | H78: =_xlfn.LET(_xlpm.v,_xlfn.XLOOKUP(F78,题库数据!$A$5:$A$104,题库数据!$K$5:$K$104,""),IF(OR(_xlpm.v="",_xlpm.v=0),"",_xlpm.v)) -> Textract and Comprehend 符合 HIPPA.https://aws.amazon.com/blogs/machine-learning/amazon-textract-is-now-hipaaeligible/
A79: 正确答案 | B79: =_xlfn.LET(_xlpm.inp,$B$77,_xlpm.nStd,_xlfn.LET(_xlpm.raw,UPPER(TRIM($G$69)),_xlpm.clean,SUBSTITUTE(SUBSTITUTE(SUBSTITUTE(SUBSTITUTE(SUBSTITUTE(_xlpm.raw,"，",","),"、",","),"；",",")," ",""),",",""),_xlfn.TEXTJOIN(",",TRUE,IF(ISNUMBER(SEARCH("A",_xlpm.clean)),"A",""),IF(ISNUMBER(SEARCH("B",_xlpm.clean)),"B",""),IF(ISNUMBER(SEARCH("C",_xlpm.clean)),"C",""),IF(ISNUMBER(SEARCH("D",_xlpm.clean)),"D",""),IF(ISNUMBER(SEARCH("E",_xlpm.clean)),"E",""),IF(ISNUMBER(SEARCH("F",_xlpm.clean)),"F",""))),IF(OR(LEN(TRIM(_xlpm.inp))=0,_xlpm.nStd=""),"",_xlpm.nStd)) | D79: {=_xlfn.LET(_xlpm.v,INDEX($B:$B, 4 + INT((ROW()-4)/13)*13 + 8), IF(_xlpm.v=0,"",_xlpm.v))} | F79: =6 -> 6 | G79: =_xlfn.XLOOKUP($F79,题库数据!$A$5:$A$104,题库数据!$J$5:$J$104,"") -> C | H79: =_xlfn.LET(_xlpm.v,_xlfn.XLOOKUP(F79,题库数据!$A$5:$A$104,题库数据!$K$5:$K$104,""),IF(OR(_xlpm.v="",_xlpm.v=0),"",_xlpm.v)) -> Textract and Comprehend 符合 HIPPA.https://aws.amazon.com/blogs/machine-learning/amazon-textract-is-now-hipaaeligible/
A80: 解析 | B80: =_xlfn.LET(_xlpm.inp,$B$77,_xlpm.p,$H$69,IF(OR(LEN(TRIM(_xlpm.inp))=0,LEN(TRIM(_xlpm.p))=0,_xlpm.p=0),"",_xlpm.p)) | D80: {=_xlfn.LET(_xlpm.v,INDEX($B:$B, 4 + INT((ROW()-4)/13)*13 + 8), IF(_xlpm.v=0,"",_xlpm.v))} | F80: =6 -> 6 | G80: =_xlfn.XLOOKUP($F80,题库数据!$A$5:$A$104,题库数据!$J$5:$J$104,"") -> C | H80: =_xlfn.LET(_xlpm.v,_xlfn.XLOOKUP(F80,题库数据!$A$5:$A$104,题库数据!$K$5:$K$104,""),IF(OR(_xlpm.v="",_xlpm.v=0),"",_xlpm.v)) -> Textract and Comprehend 符合 HIPPA.https://aws.amazon.com/blogs/machine-learning/amazon-textract-is-now-hipaaeligible/
D81: {=_xlfn.LET(_xlpm.v,INDEX($B:$B, 4 + INT((ROW()-4)/13)*13 + 8), IF(_xlpm.v=0,"",_xlpm.v))} | F81: =6 -> 6 | G81: =_xlfn.XLOOKUP($F81,题库数据!$A$5:$A$104,题库数据!$J$5:$J$104,"") -> C | H81: =_xlfn.LET(_xlpm.v,_xlfn.XLOOKUP(F81,题库数据!$A$5:$A$104,题库数据!$K$5:$K$104,""),IF(OR(_xlpm.v="",_xlpm.v=0),"",_xlpm.v)) -> Textract and Comprehend 符合 HIPPA.https://aws.amazon.com/blogs/machine-learning/amazon-textract-is-now-hipaaeligible/
A82: 题目 7： | B82: 一家公司有一个应用程序生成大量文件,每个文件大小约为5 MB.这些文件存储在 Amazon S3 中.公司政策要求文件存储 4年才能删除始终可立即访问需要,因为文件包含不易复制的关键业务数据.文件在对象创建的前30天内经常访问,但在前30天后很少访问哪种存储解决方案最具成本效益? | D82: {=_xlfn.LET(_xlpm.v,INDEX($B:$B, 4 + INT((ROW()-4)/13)*13 + 8), IF(_xlpm.v=0,"",_xlpm.v))} | F82: =7 -> 7 | G82: =_xlfn.XLOOKUP($F82,题库数据!$A$5:$A$104,题库数据!$J$5:$J$104,"") -> C | H82: =_xlfn.LET(_xlpm.v,_xlfn.XLOOKUP(F82,题库数据!$A$5:$A$104,题库数据!$K$5:$K$104,""),IF(OR(_xlpm.v="",_xlpm.v=0),"",_xlpm.v)) -> 始终需要立即访问,因为文件包含关键业务数据
D83: {=_xlfn.LET(_xlpm.v,INDEX($B:$B, 4 + INT((ROW()-4)/13)*13 + 8), IF(_xlpm.v=0,"",_xlpm.v))} | F83: =7 -> 7 | G83: =_xlfn.XLOOKUP($F83,题库数据!$A$5:$A$104,题库数据!$J$5:$J$104,"") -> C | H83: =_xlfn.LET(_xlpm.v,_xlfn.XLOOKUP(F83,题库数据!$A$5:$A$104,题库数据!$K$5:$K$104,""),IF(OR(_xlpm.v="",_xlpm.v=0),"",_xlpm.v)) -> 始终需要立即访问,因为文件包含关键业务数据
A84: A: | B84: =_xlfn.XLOOKUP($F84,题库[题号],题库[选项A]) -> 创建一个S3存储桶生命周期策略,在创建对象后30天内将文件从S3 Standard移动到S3 Glacier。在创建对象4年后删除文件 | D84: {=_xlfn.LET(_xlpm.v,INDEX($B:$B, 4 + INT((ROW()-4)/13)*13 + 8), IF(_xlpm.v=0,"",_xlpm.v))} | F84: =7 -> 7 | G84: =_xlfn.XLOOKUP($F84,题库数据!$A$5:$A$104,题库数据!$J$5:$J$104,"") -> C | H84: =_xlfn.LET(_xlpm.v,_xlfn.XLOOKUP(F84,题库数据!$A$5:$A$104,题库数据!$K$5:$K$104,""),IF(OR(_xlpm.v="",_xlpm.v=0),"",_xlpm.v)) -> 始终需要立即访问,因为文件包含关键业务数据
A85: B: | B85: =_xlfn.XLOOKUP($F85,题库[题号],题库[选项B]) -> 创建一个S3存储桶生命周期策略,在创建对象后30天内将文件从S3 Standard移动到S3 One Zone Un频繁访问(S3 One Zone IA)。在创建对象4年后删除文件 | D85: {=_xlfn.LET(_xlpm.v,INDEX($B:$B, 4 + INT((ROW()-4)/13)*13 + 8), IF(_xlpm.v=0,"",_xlpm.v))} | F85: =7 -> 7 | G85: =_xlfn.XLOOKUP($F85,题库数据!$A$5:$A$104,题库数据!$J$5:$J$104,"") -> C | H85: =_xlfn.LET(_xlpm.v,_xlfn.XLOOKUP(F85,题库数据!$A$5:$A$104,题库数据!$K$5:$K$104,""),IF(OR(_xlpm.v="",_xlpm.v=0),"",_xlpm.v)) -> 始终需要立即访问,因为文件包含关键业务数据
A86: C: | B86: =_xlfn.XLOOKUP($F86,题库[题号],题库[选项C]) -> 创建一个S3存储桶生命周期策略,在创建对象后30天内将文件从S3 Standard移动到S3 Standard Infrequent Access (S3 Standard IA)。在创建对象4年后删除文件。 | D86: {=_xlfn.LET(_xlpm.v,INDEX($B:$B, 4 + INT((ROW()-4)/13)*13 + 8), IF(_xlpm.v=0,"",_xlpm.v))} | F86: =7 -> 7 | G86: =_xlfn.XLOOKUP($F86,题库数据!$A$5:$A$104,题库数据!$J$5:$J$104,"") -> C | H86: =_xlfn.LET(_xlpm.v,_xlfn.XLOOKUP(F86,题库数据!$A$5:$A$104,题库数据!$K$5:$K$104,""),IF(OR(_xlpm.v="",_xlpm.v=0),"",_xlpm.v)) -> 始终需要立即访问,因为文件包含关键业务数据
A87: D: | B87: =_xlfn.XLOOKUP($F87,题库[题号],题库[选项D]) -> 创建 S3 存储桶生命周期策略,在对象创建后 30 天将文件从S3 标准移动到 S3 标准-不频繁访问(S3 标准-IA).在对象装箱 4年后将文件移动到 S3 Glacier. | D87: {=_xlfn.LET(_xlpm.v,INDEX($B:$B, 4 + INT((ROW()-4)/13)*13 + 8), IF(_xlpm.v=0,"",_xlpm.v))} | F87: =7 -> 7 | G87: =_xlfn.XLOOKUP($F87,题库数据!$A$5:$A$104,题库数据!$J$5:$J$104,"") -> C | H87: =_xlfn.LET(_xlpm.v,_xlfn.XLOOKUP(F87,题库数据!$A$5:$A$104,题库数据!$K$5:$K$104,""),IF(OR(_xlpm.v="",_xlpm.v=0),"",_xlpm.v)) -> 始终需要立即访问,因为文件包含关键业务数据
B88: =_xlfn.LET(_xlpm.v,_xlfn.XLOOKUP($F88,题库[题号],题库[选项E],""),IF(OR(_xlpm.v="",_xlpm.v=0),"",_xlpm.v)) | D88: {=_xlfn.LET(_xlpm.v,INDEX($B:$B, 4 + INT((ROW()-4)/13)*13 + 8), IF(_xlpm.v=0,"",_xlpm.v))} | F88: =7 -> 7 | G88: =_xlfn.XLOOKUP($F88,题库数据!$A$5:$A$104,题库数据!$J$5:$J$104,"") -> C | H88: =_xlfn.LET(_xlpm.v,_xlfn.XLOOKUP(F88,题库数据!$A$5:$A$104,题库数据!$K$5:$K$104,""),IF(OR(_xlpm.v="",_xlpm.v=0),"",_xlpm.v)) -> 始终需要立即访问,因为文件包含关键业务数据
B89: =_xlfn.LET(_xlpm.v,_xlfn.XLOOKUP($F89,题库[题号],题库[选项F],""),IF(OR(_xlpm.v="",_xlpm.v=0),"",_xlpm.v)) | D89: {=_xlfn.LET(_xlpm.v,INDEX($B:$B, 4 + INT((ROW()-4)/13)*13 + 8), IF(_xlpm.v=0,"",_xlpm.v))} | F89: =7 -> 7 | G89: =_xlfn.XLOOKUP($F89,题库数据!$A$5:$A$104,题库数据!$J$5:$J$104,"") -> C | H89: =_xlfn.LET(_xlpm.v,_xlfn.XLOOKUP(F89,题库数据!$A$5:$A$104,题库数据!$K$5:$K$104,""),IF(OR(_xlpm.v="",_xlpm.v=0),"",_xlpm.v)) -> 始终需要立即访问,因为文件包含关键业务数据
A90: 你的答案 | D90: {=_xlfn.LET(_xlpm.v,INDEX($B:$B, 4 + INT((ROW()-4)/13)*13 + 8), IF(_xlpm.v=0,"",_xlpm.v))} | F90: =7 -> 7 | G90: =_xlfn.XLOOKUP($F90,题库数据!$A$5:$A$104,题库数据!$J$5:$J$104,"") -> C | H90: =_xlfn.LET(_xlpm.v,_xlfn.XLOOKUP(F90,题库数据!$A$5:$A$104,题库数据!$K$5:$K$104,""),IF(OR(_xlpm.v="",_xlpm.v=0),"",_xlpm.v)) -> 始终需要立即访问,因为文件包含关键业务数据
A91: 结果 | B91: =_xlfn.LET(_xlpm.inp,$B$90,_xlpm.nInp,_xlfn.LET(_xlpm.raw,UPPER(TRIM($B$90)),_xlpm.clean,SUBSTITUTE(SUBSTITUTE(SUBSTITUTE(SUBSTITUTE(SUBSTITUTE(_xlpm.raw,"，",","),"、",","),"；",",")," ",""),",",""),_xlfn.TEXTJOIN(",",TRUE,IF(ISNUMBER(SEARCH("A",_xlpm.clean)),"A",""),IF(ISNUMBER(SEARCH("B",_xlpm.clean)),"B",""),IF(ISNUMBER(SEARCH("C",_xlpm.clean)),"C",""),IF(ISNUMBER(SEARCH("D",_xlpm.clean)),"D",""),IF(ISNUMBER(SEARCH("E",_xlpm.clean)),"E",""),IF(ISNUMBER(SEARCH("F",_xlpm.clean)),"F",""))),_xlpm.nStd,_xlfn.LET(_xlpm.raw,UPPER(TRIM($G$82)),_xlpm.clean,SUBSTITUTE(SUBSTITUTE(SUBSTITUTE(SUBSTITUTE(SUBSTITUTE(_xlpm.raw,"，",","),"、",","),"；",",")," ",""),",",""),_xlfn.TEXTJOIN(",",TRUE,IF(ISNUMBER(SEARCH("A",_xlpm.clean)),"A",""),IF(ISNUMBER(SEARCH("B",_xlpm.clean)),"B",""),IF(ISNUMBER(SEARCH("C",_xlpm.clean)),"C",""),IF(ISNUMBER(SEARCH("D",_xlpm.clean)),"D",""),IF(ISNUMBER(SEARCH("E",_xlpm.clean)),"E",""),IF(ISNUMBER(SEARCH("F",_xlpm.clean)),"F",""))),IF(LEN(TRIM(_xlpm.inp))=0,"",IF(AND(_xlpm.nInp<>"",_xlpm.nStd<>"",_xlpm.nInp=_xlpm.nStd),"✅正确","❌错误"))) | D91: {=_xlfn.LET(_xlpm.v,INDEX($B:$B, 4 + INT((ROW()-4)/13)*13 + 8), IF(_xlpm.v=0,"",_xlpm.v))} | F91: =7 -> 7 | G91: =_xlfn.XLOOKUP($F91,题库数据!$A$5:$A$104,题库数据!$J$5:$J$104,"") -> C | H91: =_xlfn.LET(_xlpm.v,_xlfn.XLOOKUP(F91,题库数据!$A$5:$A$104,题库数据!$K$5:$K$104,""),IF(OR(_xlpm.v="",_xlpm.v=0),"",_xlpm.v)) -> 始终需要立即访问,因为文件包含关键业务数据
A92: 正确答案 | B92: =_xlfn.LET(_xlpm.inp,$B$90,_xlpm.nStd,_xlfn.LET(_xlpm.raw,UPPER(TRIM($G$82)),_xlpm.clean,SUBSTITUTE(SUBSTITUTE(SUBSTITUTE(SUBSTITUTE(SUBSTITUTE(_xlpm.raw,"，",","),"、",","),"；",",")," ",""),",",""),_xlfn.TEXTJOIN(",",TRUE,IF(ISNUMBER(SEARCH("A",_xlpm.clean)),"A",""),IF(ISNUMBER(SEARCH("B",_xlpm.clean)),"B",""),IF(ISNUMBER(SEARCH("C",_xlpm.clean)),"C",""),IF(ISNUMBER(SEARCH("D",_xlpm.clean)),"D",""),IF(ISNUMBER(SEARCH("E",_xlpm.clean)),"E",""),IF(ISNUMBER(SEARCH("F",_xlpm.clean)),"F",""))),IF(OR(LEN(TRIM(_xlpm.inp))=0,_xlpm.nStd=""),"",_xlpm.nStd)) | D92: {=_xlfn.LET(_xlpm.v,INDEX($B:$B, 4 + INT((ROW()-4)/13)*13 + 8), IF(_xlpm.v=0,"",_xlpm.v))} | F92: =7 -> 7 | G92: =_xlfn.XLOOKUP($F92,题库数据!$A$5:$A$104,题库数据!$J$5:$J$104,"") -> C | H92: =_xlfn.LET(_xlpm.v,_xlfn.XLOOKUP(F92,题库数据!$A$5:$A$104,题库数据!$K$5:$K$104,""),IF(OR(_xlpm.v="",_xlpm.v=0),"",_xlpm.v)) -> 始终需要立即访问,因为文件包含关键业务数据
A93: 解析 | B93: =_xlfn.LET(_xlpm.inp,$B$90,_xlpm.p,$H$82,IF(OR(LEN(TRIM(_xlpm.inp))=0,LEN(TRIM(_xlpm.p))=0,_xlpm.p=0),"",_xlpm.p)) | D93: {=_xlfn.LET(_xlpm.v,INDEX($B:$B, 4 + INT((ROW()-4)/13)*13 + 8), IF(_xlpm.v=0,"",_xlpm.v))} | F93: =7 -> 7 | G93: =_xlfn.XLOOKUP($F93,题库数据!$A$5:$A$104,题库数据!$J$5:$J$104,"") -> C | H93: =_xlfn.LET(_xlpm.v,_xlfn.XLOOKUP(F93,题库数据!$A$5:$A$104,题库数据!$K$5:$K$104,""),IF(OR(_xlpm.v="",_xlpm.v=0),"",_xlpm.v)) -> 始终需要立即访问,因为文件包含关键业务数据
D94: {=_xlfn.LET(_xlpm.v,INDEX($B:$B, 4 + INT((ROW()-4)/13)*13 + 8), IF(_xlpm.v=0,"",_xlpm.v))} | F94: =7 -> 7 | G94: =_xlfn.XLOOKUP($F94,题库数据!$A$5:$A$104,题库数据!$J$5:$J$104,"") -> C | H94: =_xlfn.LET(_xlpm.v,_xlfn.XLOOKUP(F94,题库数据!$A$5:$A$104,题库数据!$K$5:$K$104,""),IF(OR(_xlpm.v="",_xlpm.v=0),"",_xlpm.v)) -> 始终需要立即访问,因为文件包含关键业务数据
A95: 题目 8： | B95: 一家公司在多个 Amazon EC2 实例上托管应用程序,应用程序处理来自 Amazon SQS 队列的消息写入 Amazon RDS 表并从队列中删除消息在 RDS 表中偶尔发现重复记录.SQS 队列没有包含任何重复的消息.解决方案架构师应该怎么做才能确保消息只被处理一次? | D95: {=_xlfn.LET(_xlpm.v,INDEX($B:$B, 4 + INT((ROW()-4)/13)*13 + 8), IF(_xlpm.v=0,"",_xlpm.v))} | F95: =8 -> 8 | G95: =_xlfn.XLOOKUP($F95,题库数据!$A$5:$A$104,题库数据!$J$5:$J$104,"") -> D | H95: =_xlfn.LET(_xlpm.v,_xlfn.XLOOKUP(F95,题库数据!$A$5:$A$104,题库数据!$K$5:$K$104,""),IF(OR(_xlpm.v="",_xlpm.v=0),"",_xlpm.v)) -> 可见性超时在 Amazon SQS 返回消息时开始.在此期间,消费者会处理并删除消息.但是,如果消费者在删除消息之前失败,并且您的系统在可见性超时到期,该消息对其他消费者可见,并再次收到该消息.如果一条消息必须只接收一次,您的消费者应在可见性超时期限内将其删除.https://docs.aws.amazon.com/AWSSimpleQueueService/latest/SQSDeveloperGuide/sqs-visibilitytimeout.html 关键字:SQS 队列写入 Amazon RDS 由此,选项 D 最佳套件 &其他选项排除[选项A-您不能在现有队列中再插入一个队列;选项 B-only Permission & Option C-Only Retrieves Messages] FIF O 队列旨在从不引入重复消息.但是,您的消息生产者可能会在某些情况下引入重复消息:例如,如果生产者发送消息,没有收到响应,然后重新发送消息相同的消息.Amazon SQS API 提供重复数据删除功能,可防止您的消息生产者发送重复数据.消息生产者引入的任何重复数据都会在5分钟的重复数据删除间隔内删除.对于标准队列,您可能偶尔会收到消息的重复副本(至少一次传递).如果使用标准队列,则必须将应用程序设计为幂等的(即,在多次处理同一消息时,它们不得受到不利影响).
D96: {=_xlfn.LET(_xlpm.v,INDEX($B:$B, 4 + INT((ROW()-4)/13)*13 + 8), IF(_xlpm.v=0,"",_xlpm.v))} | F96: =8 -> 8 | G96: =_xlfn.XLOOKUP($F96,题库数据!$A$5:$A$104,题库数据!$J$5:$J$104,"") -> D | H96: =_xlfn.LET(_xlpm.v,_xlfn.XLOOKUP(F96,题库数据!$A$5:$A$104,题库数据!$K$5:$K$104,""),IF(OR(_xlpm.v="",_xlpm.v=0),"",_xlpm.v)) -> 可见性超时在 Amazon SQS 返回消息时开始.在此期间,消费者会处理并删除消息.但是,如果消费者在删除消息之前失败,并且您的系统在可见性超时到期,该消息对其他消费者可见,并再次收到该消息.如果一条消息必须只接收一次,您的消费者应在可见性超时期限内将其删除.https://docs.aws.amazon.com/AWSSimpleQueueService/latest/SQSDeveloperGuide/sqs-visibilitytimeout.html 关键字:SQS 队列写入 Amazon RDS 由此,选项 D 最佳套件 &其他选项排除[选项A-您不能在现有队列中再插入一个队列;选项 B-only Permission & Option C-Only Retrieves Messages] FIF O 队列旨在从不引入重复消息.但是,您的消息生产者可能会在某些情况下引入重复消息:例如,如果生产者发送消息,没有收到响应,然后重新发送消息相同的消息.Amazon SQS API 提供重复数据删除功能,可防止您的消息生产者发送重复数据.消息生产者引入的任何重复数据都会在5分钟的重复数据删除间隔内删除.对于标准队列,您可能偶尔会收到消息的重复副本(至少一次传递).如果使用标准队列,则必须将应用程序设计为幂等的(即,在多次处理同一消息时,它们不得受到不利影响).
A97: A: | B97: =_xlfn.XLOOKUP($F97,题库[题号],题库[选项A]) -> 使用 CreateQueue API 调用创建新队列 | D97: {=_xlfn.LET(_xlpm.v,INDEX($B:$B, 4 + INT((ROW()-4)/13)*13 + 8), IF(_xlpm.v=0,"",_xlpm.v))} | F97: =8 -> 8 | G97: =_xlfn.XLOOKUP($F97,题库数据!$A$5:$A$104,题库数据!$J$5:$J$104,"") -> D | H97: =_xlfn.LET(_xlpm.v,_xlfn.XLOOKUP(F97,题库数据!$A$5:$A$104,题库数据!$K$5:$K$104,""),IF(OR(_xlpm.v="",_xlpm.v=0),"",_xlpm.v)) -> 可见性超时在 Amazon SQS 返回消息时开始.在此期间,消费者会处理并删除消息.但是,如果消费者在删除消息之前失败,并且您的系统在可见性超时到期,该消息对其他消费者可见,并再次收到该消息.如果一条消息必须只接收一次,您的消费者应在可见性超时期限内将其删除.https://docs.aws.amazon.com/AWSSimpleQueueService/latest/SQSDeveloperGuide/sqs-visibilitytimeout.html 关键字:SQS 队列写入 Amazon RDS 由此,选项 D 最佳套件 &其他选项排除[选项A-您不能在现有队列中再插入一个队列;选项 B-only Permission & Option C-Only Retrieves Messages] FIF O 队列旨在从不引入重复消息.但是,您的消息生产者可能会在某些情况下引入重复消息:例如,如果生产者发送消息,没有收到响应,然后重新发送消息相同的消息.Amazon SQS API 提供重复数据删除功能,可防止您的消息生产者发送重复数据.消息生产者引入的任何重复数据都会在5分钟的重复数据删除间隔内删除.对于标准队列,您可能偶尔会收到消息的重复副本(至少一次传递).如果使用标准队列,则必须将应用程序设计为幂等的(即,在多次处理同一消息时,它们不得受到不利影响).
A98: B: | B98: =_xlfn.XLOOKUP($F98,题库[题号],题库[选项B]) -> 使用 Add Permission API 调用添加适当的权限 | D98: {=_xlfn.LET(_xlpm.v,INDEX($B:$B, 4 + INT((ROW()-4)/13)*13 + 8), IF(_xlpm.v=0,"",_xlpm.v))} | F98: =8 -> 8 | G98: =_xlfn.XLOOKUP($F98,题库数据!$A$5:$A$104,题库数据!$J$5:$J$104,"") -> D | H98: =_xlfn.LET(_xlpm.v,_xlfn.XLOOKUP(F98,题库数据!$A$5:$A$104,题库数据!$K$5:$K$104,""),IF(OR(_xlpm.v="",_xlpm.v=0),"",_xlpm.v)) -> 可见性超时在 Amazon SQS 返回消息时开始.在此期间,消费者会处理并删除消息.但是,如果消费者在删除消息之前失败,并且您的系统在可见性超时到期,该消息对其他消费者可见,并再次收到该消息.如果一条消息必须只接收一次,您的消费者应在可见性超时期限内将其删除.https://docs.aws.amazon.com/AWSSimpleQueueService/latest/SQSDeveloperGuide/sqs-visibilitytimeout.html 关键字:SQS 队列写入 Amazon RDS 由此,选项 D 最佳套件 &其他选项排除[选项A-您不能在现有队列中再插入一个队列;选项 B-only Permission & Option C-Only Retrieves Messages] FIF O 队列旨在从不引入重复消息.但是,您的消息生产者可能会在某些情况下引入重复消息:例如,如果生产者发送消息,没有收到响应,然后重新发送消息相同的消息.Amazon SQS API 提供重复数据删除功能,可防止您的消息生产者发送重复数据.消息生产者引入的任何重复数据都会在5分钟的重复数据删除间隔内删除.对于标准队列,您可能偶尔会收到消息的重复副本(至少一次传递).如果使用标准队列,则必须将应用程序设计为幂等的(即,在多次处理同一消息时,它们不得受到不利影响).
A99: C: | B99: =_xlfn.XLOOKUP($F99,题库[题号],题库[选项C]) -> 使用 ReceiveMessage API 调用设置适当的等待时间 | D99: {=_xlfn.LET(_xlpm.v,INDEX($B:$B, 4 + INT((ROW()-4)/13)*13 + 8), IF(_xlpm.v=0,"",_xlpm.v))} | F99: =8 -> 8 | G99: =_xlfn.XLOOKUP($F99,题库数据!$A$5:$A$104,题库数据!$J$5:$J$104,"") -> D | H99: =_xlfn.LET(_xlpm.v,_xlfn.XLOOKUP(F99,题库数据!$A$5:$A$104,题库数据!$K$5:$K$104,""),IF(OR(_xlpm.v="",_xlpm.v=0),"",_xlpm.v)) -> 可见性超时在 Amazon SQS 返回消息时开始.在此期间,消费者会处理并删除消息.但是,如果消费者在删除消息之前失败,并且您的系统在可见性超时到期,该消息对其他消费者可见,并再次收到该消息.如果一条消息必须只接收一次,您的消费者应在可见性超时期限内将其删除.https://docs.aws.amazon.com/AWSSimpleQueueService/latest/SQSDeveloperGuide/sqs-visibilitytimeout.html 关键字:SQS 队列写入 Amazon RDS 由此,选项 D 最佳套件 &其他选项排除[选项A-您不能在现有队列中再插入一个队列;选项 B-only Permission & Option C-Only Retrieves Messages] FIF O 队列旨在从不引入重复消息.但是,您的消息生产者可能会在某些情况下引入重复消息:例如,如果生产者发送消息,没有收到响应,然后重新发送消息相同的消息.Amazon SQS API 提供重复数据删除功能,可防止您的消息生产者发送重复数据.消息生产者引入的任何重复数据都会在5分钟的重复数据删除间隔内删除.对于标准队列,您可能偶尔会收到消息的重复副本(至少一次传递).如果使用标准队列,则必须将应用程序设计为幂等的(即,在多次处理同一消息时,它们不得受到不利影响).
A100: D: | B100: =_xlfn.XLOOKUP($F100,题库[题号],题库[选项D]) -> 使用 ChangeMessageVisibility APi 调用来增加可见性超时 | D100: {=_xlfn.LET(_xlpm.v,INDEX($B:$B, 4 + INT((ROW()-4)/13)*13 + 8), IF(_xlpm.v=0,"",_xlpm.v))} | F100: =8 -> 8 | G100: =_xlfn.XLOOKUP($F100,题库数据!$A$5:$A$104,题库数据!$J$5:$J$104,"") -> D | H100: =_xlfn.LET(_xlpm.v,_xlfn.XLOOKUP(F100,题库数据!$A$5:$A$104,题库数据!$K$5:$K$104,""),IF(OR(_xlpm.v="",_xlpm.v=0),"",_xlpm.v)) -> 可见性超时在 Amazon SQS 返回消息时开始.在此期间,消费者会处理并删除消息.但是,如果消费者在删除消息之前失败,并且您的系统在可见性超时到期,该消息对其他消费者可见,并再次收到该消息.如果一条消息必须只接收一次,您的消费者应在可见性超时期限内将其删除.https://docs.aws.amazon.com/AWSSimpleQueueService/latest/SQSDeveloperGuide/sqs-visibilitytimeout.html 关键字:SQS 队列写入 Amazon RDS 由此,选项 D 最佳套件 &其他选项排除[选项A-您不能在现有队列中再插入一个队列;选项 B-only Permission & Option C-Only Retrieves Messages] FIF O 队列旨在从不引入重复消息.但是,您的消息生产者可能会在某些情况下引入重复消息:例如,如果生产者发送消息,没有收到响应,然后重新发送消息相同的消息.Amazon SQS API 提供重复数据删除功能,可防止您的消息生产者发送重复数据.消息生产者引入的任何重复数据都会在5分钟的重复数据删除间隔内删除.对于标准队列,您可能偶尔会收到消息的重复副本(至少一次传递).如果使用标准队列,则必须将应用程序设计为幂等的(即,在多次处理同一消息时,它们不得受到不利影响).
...

Sheet 101-200
A1: 📘 AWS-SAA-C03 顺序刷题（101-200）
A2: 在每题「你的答案」输入 A 或 C,D（英文逗号）后，才会显示：结果 / 正确答案 / 解析，并自动对选项标色（绿=正确，红=你选错）。
A3: {=_xlfn.LET(_xlpm.ans,SUMPRODUCT(($A$4:$A$1304="你的答案")*($B$4:$B$1304<>"")),_xlpm.corr,SUMPRODUCT(($A$4:$A$1304="结果")*($B$4:$B$1304="✅正确")),_xlpm.total,100,_xlpm.rate,IF(_xlpm.ans=0,0,_xlpm.corr/_xlpm.ans),"📊 进度：已作答 "&_xlpm.ans&"/"&_xlpm.total&" | 正确 "&_xlpm.corr&" | 正确率 "&TEXT(_xlpm.rate,"0.0%"))} -> 📊 进度：已作答 0/100 | 正确 0 | 正确率 0.0%
A4: 题目 101： | B4: Q101 一家公司在多个大洲的城市收集温度.湿度和大气压力数据.每个站点每天收集的平均数据量为 500 GB.每个站点都有高速互联网连接.该公司的天气预报应用程序基于在单个区域并每天分析数据.从所有这些全球站点汇总数据的最快方法是什么? | F4: 101 | G4: A | H4: 您可能出于各种原因想要在存储桶上使用 Transfer Acceleration,包括以下原因 :- 您的客户从世界各地上传到集中式存储桶 .您定期跨大陆传输 GB 到 TB 的数据 .- 上传到 Amazon S3 时,您无法利用 Internet 上的所有可用带宽. https://docs.aws.amazon.com/AmazonS3/latest/dev/transfer-acceleration.html https://aws.amazon.com/s3/transferacceleration/#:~:text=S3%20Transfer%20Acceleration%20(S3TA)%20reduces,to%20S3%20for%20remote%20applications Amazon S3 Transfer Acceleration 可以加快内容传输到和对于大型对象的长距离传输,从 Amazon S3 中节省多达 50-500%.拥有广泛用户的 Web 或移动应用程序或托管在远离其 S3 存储桶的应用程序的客户可以体验到较长且可变的上传和下载速度互联网 https://docs.aws.amazon.com/AmazonS3/latest/userguide/mpuoverview.html 提高吞吐量 - 您可以并行上传部分以提高吞吐量.
A6: A: | B6: 在目标存储桶上启用 Amazon S3 Transfer Acceleration.使用分段上传将站点数据直接上传到目标存储桶. | F6: 101 | G6: A | H6: 您可能出于各种原因想要在存储桶上使用 Transfer Acceleration,包括以下原因 :- 您的客户从世界各地上传到集中式存储桶 .您定期跨大陆传输 GB 到 TB 的数据 .- 上传到 Amazon S3 时,您无法利用 Internet 上的所有可用带宽. https://docs.aws.amazon.com/AmazonS3/latest/dev/transfer-acceleration.html https://aws.amazon.com/s3/transferacceleration/#:~:text=S3%20Transfer%20Acceleration%20(S3TA)%20reduces,to%20S3%20for%20remote%20applications Amazon S3 Transfer Acceleration 可以加快内容传输到和对于大型对象的长距离传输,从 Amazon S3 中节省多达 50-500%.拥有广泛用户的 Web 或移动应用程序或托管在远离其 S3 存储桶的应用程序的客户可以体验到较长且可变的上传和下载速度互联网 https://docs.aws.amazon.com/AmazonS3/latest/userguide/mpuoverview.html 提高吞吐量 - 您可以并行上传部分以提高吞吐量.
A7: B: | B7: 将站点数据上传到最近的 AWS 区域中的 Amazon S3 存储桶.使用 S3 跨区域复制将对象复制到目标存储桶. | F7: 101 | G7: A | H7: 您可能出于各种原因想要在存储桶上使用 Transfer Acceleration,包括以下原因 :- 您的客户从世界各地上传到集中式存储桶 .您定期跨大陆传输 GB 到 TB 的数据 .- 上传到 Amazon S3 时,您无法利用 Internet 上的所有可用带宽. https://docs.aws.amazon.com/AmazonS3/latest/dev/transfer-acceleration.html https://aws.amazon.com/s3/transferacceleration/#:~:text=S3%20Transfer%20Acceleration%20(S3TA)%20reduces,to%20S3%20for%20remote%20applications Amazon S3 Transfer Acceleration 可以加快内容传输到和对于大型对象的长距离传输,从 Amazon S3 中节省多达 50-500%.拥有广泛用户的 Web 或移动应用程序或托管在远离其 S3 存储桶的应用程序的客户可以体验到较长且可变的上传和下载速度互联网 https://docs.aws.amazon.com/AmazonS3/latest/userguide/mpuoverview.html 提高吞吐量 - 您可以并行上传部分以提高吞吐量.
A8: C: | B8: 每天安排 AWS Snowball 作业以将数据传输到最近的 AWS 区域.使用S3 跨区域复制将对象复制到目标存储桶. | F8: 101 | G8: A | H8: 您可能出于各种原因想要在存储桶上使用 Transfer Acceleration,包括以下原因 :- 您的客户从世界各地上传到集中式存储桶 .您定期跨大陆传输 GB 到 TB 的数据 .- 上传到 Amazon S3 时,您无法利用 Internet 上的所有可用带宽. https://docs.aws.amazon.com/AmazonS3/latest/dev/transfer-acceleration.html https://aws.amazon.com/s3/transferacceleration/#:~:text=S3%20Transfer%20Acceleration%20(S3TA)%20reduces,to%20S3%20for%20remote%20applications Amazon S3 Transfer Acceleration 可以加快内容传输到和对于大型对象的长距离传输,从 Amazon S3 中节省多达 50-500%.拥有广泛用户的 Web 或移动应用程序或托管在远离其 S3 存储桶的应用程序的客户可以体验到较长且可变的上传和下载速度互联网 https://docs.aws.amazon.com/AmazonS3/latest/userguide/mpuoverview.html 提高吞吐量 - 您可以并行上传部分以提高吞吐量.
A9: D: | B9: 将数据上传到最近区域的 Amazon EC2 实例.将数据存储在 Amazon Elastic Block Store (Amazon EBS) 卷中.每天拍摄一次 EBS 快照并将其复制到集中区域.将 EBS 卷恢复到集中区域并每天对数据进行分析. | F9: 101 | G9: A | H9: 您可能出于各种原因想要在存储桶上使用 Transfer Acceleration,包括以下原因 :- 您的客户从世界各地上传到集中式存储桶 .您定期跨大陆传输 GB 到 TB 的数据 .- 上传到 Amazon S3 时,您无法利用 Internet 上的所有可用带宽. https://docs.aws.amazon.com/AmazonS3/latest/dev/transfer-acceleration.html https://aws.amazon.com/s3/transferacceleration/#:~:text=S3%20Transfer%20Acceleration%20(S3TA)%20reduces,to%20S3%20for%20remote%20applications Amazon S3 Transfer Acceleration 可以加快内容传输到和对于大型对象的长距离传输,从 Amazon S3 中节省多达 50-500%.拥有广泛用户的 Web 或移动应用程序或托管在远离其 S3 存储桶的应用程序的客户可以体验到较长且可变的上传和下载速度互联网 https://docs.aws.amazon.com/AmazonS3/latest/userguide/mpuoverview.html 提高吞吐量 - 您可以并行上传部分以提高吞吐量.
F10: 101 | G10: A | H10: 您可能出于各种原因想要在存储桶上使用 Transfer Acceleration,包括以下原因 :- 您的客户从世界各地上传到集中式存储桶 .您定期跨大陆传输 GB 到 TB 的数据 .- 上传到 Amazon S3 时,您无法利用 Internet 上的所有可用带宽. https://docs.aws.amazon.com/AmazonS3/latest/dev/transfer-acceleration.html https://aws.amazon.com/s3/transferacceleration/#:~:text=S3%20Transfer%20Acceleration%20(S3TA)%20reduces,to%20S3%20for%20remote%20applications Amazon S3 Transfer Acceleration 可以加快内容传输到和对于大型对象的长距离传输,从 Amazon S3 中节省多达 50-500%.拥有广泛用户的 Web 或移动应用程序或托管在远离其 S3 存储桶的应用程序的客户可以体验到较长且可变的上传和下载速度互联网 https://docs.aws.amazon.com/AmazonS3/latest/userguide/mpuoverview.html 提高吞吐量 - 您可以并行上传部分以提高吞吐量.
F11: 101 | G11: A | H11: 您可能出于各种原因想要在存储桶上使用 Transfer Acceleration,包括以下原因 :- 您的客户从世界各地上传到集中式存储桶 .您定期跨大陆传输 GB 到 TB 的数据 .- 上传到 Amazon S3 时,您无法利用 Internet 上的所有可用带宽. https://docs.aws.amazon.com/AmazonS3/latest/dev/transfer-acceleration.html https://aws.amazon.com/s3/transferacceleration/#:~:text=S3%20Transfer%20Acceleration%20(S3TA)%20reduces,to%20S3%20for%20remote%20applications Amazon S3 Transfer Acceleration 可以加快内容传输到和对于大型对象的长距离传输,从 Amazon S3 中节省多达 50-500%.拥有广泛用户的 Web 或移动应用程序或托管在远离其 S3 存储桶的应用程序的客户可以体验到较长且可变的上传和下载速度互联网 https://docs.aws.amazon.com/AmazonS3/latest/userguide/mpuoverview.html 提高吞吐量 - 您可以并行上传部分以提高吞吐量.
A12: 你的答案 | F12: 101 | G12: A | H12: 您可能出于各种原因想要在存储桶上使用 Transfer Acceleration,包括以下原因 :- 您的客户从世界各地上传到集中式存储桶 .您定期跨大陆传输 GB 到 TB 的数据 .- 上传到 Amazon S3 时,您无法利用 Internet 上的所有可用带宽. https://docs.aws.amazon.com/AmazonS3/latest/dev/transfer-acceleration.html https://aws.amazon.com/s3/transferacceleration/#:~:text=S3%20Transfer%20Acceleration%20(S3TA)%20reduces,to%20S3%20for%20remote%20applications Amazon S3 Transfer Acceleration 可以加快内容传输到和对于大型对象的长距离传输,从 Amazon S3 中节省多达 50-500%.拥有广泛用户的 Web 或移动应用程序或托管在远离其 S3 存储桶的应用程序的客户可以体验到较长且可变的上传和下载速度互联网 https://docs.aws.amazon.com/AmazonS3/latest/userguide/mpuoverview.html 提高吞吐量 - 您可以并行上传部分以提高吞吐量.
A13: 结果 | B13: =_xlfn.LET(_xlpm.inp,$B$12,_xlpm.nInp,_xlfn.LET(_xlpm.raw,UPPER(TRIM($B$12)),_xlpm.clean,SUBSTITUTE(SUBSTITUTE(SUBSTITUTE(SUBSTITUTE(SUBSTITUTE(_xlpm.raw,"，",","),"、",","),"；",",")," ",""),",",""),_xlfn.TEXTJOIN(",",TRUE,IF(ISNUMBER(SEARCH("A",_xlpm.clean)),"A",""),IF(ISNUMBER(SEARCH("B",_xlpm.clean)),"B",""),IF(ISNUMBER(SEARCH("C",_xlpm.clean)),"C",""),IF(ISNUMBER(SEARCH("D",_xlpm.clean)),"D",""),IF(ISNUMBER(SEARCH("E",_xlpm.clean)),"E",""),IF(ISNUMBER(SEARCH("F",_xlpm.clean)),"F",""))),_xlpm.nStd,_xlfn.LET(_xlpm.raw,UPPER(TRIM($G$4)),_xlpm.clean,SUBSTITUTE(SUBSTITUTE(SUBSTITUTE(SUBSTITUTE(SUBSTITUTE(_xlpm.raw,"，",","),"、",","),"；",",")," ",""),",",""),_xlfn.TEXTJOIN(",",TRUE,IF(ISNUMBER(SEARCH("A",_xlpm.clean)),"A",""),IF(ISNUMBER(SEARCH("B",_xlpm.clean)),"B",""),IF(ISNUMBER(SEARCH("C",_xlpm.clean)),"C",""),IF(ISNUMBER(SEARCH("D",_xlpm.clean)),"D",""),IF(ISNUMBER(SEARCH("E",_xlpm.clean)),"E",""),IF(ISNUMBER(SEARCH("F",_xlpm.clean)),"F",""))),IF(LEN(TRIM(_xlpm.inp))=0,"",IF(AND(_xlpm.nInp<>"",_xlpm.nStd<>"",_xlpm.nInp=_xlpm.nStd),"✅正确","❌错误"))) | F13: 101 | G13: A | H13: 您可能出于各种原因想要在存储桶上使用 Transfer Acceleration,包括以下原因 :- 您的客户从世界各地上传到集中式存储桶 .您定期跨大陆传输 GB 到 TB 的数据 .- 上传到 Amazon S3 时,您无法利用 Internet 上的所有可用带宽. https://docs.aws.amazon.com/AmazonS3/latest/dev/transfer-acceleration.html https://aws.amazon.com/s3/transferacceleration/#:~:text=S3%20Transfer%20Acceleration%20(S3TA)%20reduces,to%20S3%20for%20remote%20applications Amazon S3 Transfer Acceleration 可以加快内容传输到和对于大型对象的长距离传输,从 Amazon S3 中节省多达 50-500%.拥有广泛用户的 Web 或移动应用程序或托管在远离其 S3 存储桶的应用程序的客户可以体验到较长且可变的上传和下载速度互联网 https://docs.aws.amazon.com/AmazonS3/latest/userguide/mpuoverview.html 提高吞吐量 - 您可以并行上传部分以提高吞吐量.
A14: 正确答案 | B14: =_xlfn.LET(_xlpm.inp,$B$12,_xlpm.nStd,_xlfn.LET(_xlpm.raw,UPPER(TRIM($G$4)),_xlpm.clean,SUBSTITUTE(SUBSTITUTE(SUBSTITUTE(SUBSTITUTE(SUBSTITUTE(_xlpm.raw,"，",","),"、",","),"；",",")," ",""),",",""),_xlfn.TEXTJOIN(",",TRUE,IF(ISNUMBER(SEARCH("A",_xlpm.clean)),"A",""),IF(ISNUMBER(SEARCH("B",_xlpm.clean)),"B",""),IF(ISNUMBER(SEARCH("C",_xlpm.clean)),"C",""),IF(ISNUMBER(SEARCH("D",_xlpm.clean)),"D",""),IF(ISNUMBER(SEARCH("E",_xlpm.clean)),"E",""),IF(ISNUMBER(SEARCH("F",_xlpm.clean)),"F",""))),IF(OR(LEN(TRIM(_xlpm.inp))=0,_xlpm.nStd=""),"",_xlpm.nStd)) | F14: 101 | G14: A | H14: 您可能出于各种原因想要在存储桶上使用 Transfer Acceleration,包括以下原因 :- 您的客户从世界各地上传到集中式存储桶 .您定期跨大陆传输 GB 到 TB 的数据 .- 上传到 Amazon S3 时,您无法利用 Internet 上的所有可用带宽. https://docs.aws.amazon.com/AmazonS3/latest/dev/transfer-acceleration.html https://aws.amazon.com/s3/transferacceleration/#:~:text=S3%20Transfer%20Acceleration%20(S3TA)%20reduces,to%20S3%20for%20remote%20applications Amazon S3 Transfer Acceleration 可以加快内容传输到和对于大型对象的长距离传输,从 Amazon S3 中节省多达 50-500%.拥有广泛用户的 Web 或移动应用程序或托管在远离其 S3 存储桶的应用程序的客户可以体验到较长且可变的上传和下载速度互联网 https://docs.aws.amazon.com/AmazonS3/latest/userguide/mpuoverview.html 提高吞吐量 - 您可以并行上传部分以提高吞吐量.
A15: 解析 | B15: =_xlfn.LET(_xlpm.inp,$B$12,_xlpm.p,$H$4,IF(OR(LEN(TRIM(_xlpm.inp))=0,LEN(TRIM(_xlpm.p))=0,_xlpm.p=0),"",_xlpm.p)) | F15: 101 | G15: A | H15: 您可能出于各种原因想要在存储桶上使用 Transfer Acceleration,包括以下原因 :- 您的客户从世界各地上传到集中式存储桶 .您定期跨大陆传输 GB 到 TB 的数据 .- 上传到 Amazon S3 时,您无法利用 Internet 上的所有可用带宽. https://docs.aws.amazon.com/AmazonS3/latest/dev/transfer-acceleration.html https://aws.amazon.com/s3/transferacceleration/#:~:text=S3%20Transfer%20Acceleration%20(S3TA)%20reduces,to%20S3%20for%20remote%20applications Amazon S3 Transfer Acceleration 可以加快内容传输到和对于大型对象的长距离传输,从 Amazon S3 中节省多达 50-500%.拥有广泛用户的 Web 或移动应用程序或托管在远离其 S3 存储桶的应用程序的客户可以体验到较长且可变的上传和下载速度互联网 https://docs.aws.amazon.com/AmazonS3/latest/userguide/mpuoverview.html 提高吞吐量 - 您可以并行上传部分以提高吞吐量.
F16: 101 | G16: A | H16: 您可能出于各种原因想要在存储桶上使用 Transfer Acceleration,包括以下原因 :- 您的客户从世界各地上传到集中式存储桶 .您定期跨大陆传输 GB 到 TB 的数据 .- 上传到 Amazon S3 时,您无法利用 Internet 上的所有可用带宽. https://docs.aws.amazon.com/AmazonS3/latest/dev/transfer-acceleration.html https://aws.amazon.com/s3/transferacceleration/#:~:text=S3%20Transfer%20Acceleration%20(S3TA)%20reduces,to%20S3%20for%20remote%20applications Amazon S3 Transfer Acceleration 可以加快内容传输到和对于大型对象的长距离传输,从 Amazon S3 中节省多达 50-500%.拥有广泛用户的 Web 或移动应用程序或托管在远离其 S3 存储桶的应用程序的客户可以体验到较长且可变的上传和下载速度互联网 https://docs.aws.amazon.com/AmazonS3/latest/userguide/mpuoverview.html 提高吞吐量 - 您可以并行上传部分以提高吞吐量.
A17: 题目 102： | B17: Q102 公司需要能够分析其专有应用程序的日志文件.日志以 JSON 格式存储在 Amazon S3 存储桶中 查询将很简单,并且可以按需运行.解决方案架构师需要以最少的时间执行分析对现有架构的更改.解决方案架构师应该如何以最少的运营开销满足这些要求? | F17: 102 | G17: C | H17: Amazon Athena 可用于在 S3 中查询 JSON.
A19: A: | B19: 使用 Amazon Redshift 将所有内容加载到一个位置并根据需要运行 SQL 查询 | F19: 102 | G19: C | H19: Amazon Athena 可用于在 S3 中查询 JSON.
A20: B: | B20: 使用 Amazon CloudWatch Logs 存储日志 根据需要从 Amazon CloudWatch 控制台运行 SQL 查询 | F20: 102 | G20: C | H20: Amazon Athena 可用于在 S3 中查询 JSON.
A21: C: | B21: 根据需要直接使用 Amazon Athena 和 Amazon S3 运行查询 | F21: 102 | G21: C | H21: Amazon Athena 可用于在 S3 中查询 JSON.
A22: D: | B22: 使用 AWS Glue 对日志进行编目 根据需要使用 Amazon EMR 上的临时 Apache Spark 集群运行 SQL 查询 | F22: 102 | G22: C | H22: Amazon Athena 可用于在 S3 中查询 JSON.
F23: 102 | G23: C | H23: Amazon Athena 可用于在 S3 中查询 JSON.
F24: 102 | G24: C | H24: Amazon Athena 可用于在 S3 中查询 JSON.
A25: 你的答案 | F25: 102 | G25: C | H25: Amazon Athena 可用于在 S3 中查询 JSON.
A26: 结果 | B26: =_xlfn.LET(_xlpm.inp,$B$25,_xlpm.nInp,_xlfn.LET(_xlpm.raw,UPPER(TRIM($B$25)),_xlpm.clean,SUBSTITUTE(SUBSTITUTE(SUBSTITUTE(SUBSTITUTE(SUBSTITUTE(_xlpm.raw,"，",","),"、",","),"；",",")," ",""),",",""),_xlfn.TEXTJOIN(",",TRUE,IF(ISNUMBER(SEARCH("A",_xlpm.clean)),"A",""),IF(ISNUMBER(SEARCH("B",_xlpm.clean)),"B",""),IF(ISNUMBER(SEARCH("C",_xlpm.clean)),"C",""),IF(ISNUMBER(SEARCH("D",_xlpm.clean)),"D",""),IF(ISNUMBER(SEARCH("E",_xlpm.clean)),"E",""),IF(ISNUMBER(SEARCH("F",_xlpm.clean)),"F",""))),_xlpm.nStd,_xlfn.LET(_xlpm.raw,UPPER(TRIM($G$17)),_xlpm.clean,SUBSTITUTE(SUBSTITUTE(SUBSTITUTE(SUBSTITUTE(SUBSTITUTE(_xlpm.raw,"，",","),"、",","),"；",",")," ",""),",",""),_xlfn.TEXTJOIN(",",TRUE,IF(ISNUMBER(SEARCH("A",_xlpm.clean)),"A",""),IF(ISNUMBER(SEARCH("B",_xlpm.clean)),"B",""),IF(ISNUMBER(SEARCH("C",_xlpm.clean)),"C",""),IF(ISNUMBER(SEARCH("D",_xlpm.clean)),"D",""),IF(ISNUMBER(SEARCH("E",_xlpm.clean)),"E",""),IF(ISNUMBER(SEARCH("F",_xlpm.clean)),"F",""))),IF(LEN(TRIM(_xlpm.inp))=0,"",IF(AND(_xlpm.nInp<>"",_xlpm.nStd<>"",_xlpm.nInp=_xlpm.nStd),"✅正确","❌错误"))) | F26: 102 | G26: C | H26: Amazon Athena 可用于在 S3 中查询 JSON.
A27: 正确答案 | B27: =_xlfn.LET(_xlpm.inp,$B$25,_xlpm.nStd,_xlfn.LET(_xlpm.raw,UPPER(TRIM($G$17)),_xlpm.clean,SUBSTITUTE(SUBSTITUTE(SUBSTITUTE(SUBSTITUTE(SUBSTITUTE(_xlpm.raw,"，",","),"、",","),"；",",")," ",""),",",""),_xlfn.TEXTJOIN(",",TRUE,IF(ISNUMBER(SEARCH("A",_xlpm.clean)),"A",""),IF(ISNUMBER(SEARCH("B",_xlpm.clean)),"B",""),IF(ISNUMBER(SEARCH("C",_xlpm.clean)),"C",""),IF(ISNUMBER(SEARCH("D",_xlpm.clean)),"D",""),IF(ISNUMBER(SEARCH("E",_xlpm.clean)),"E",""),IF(ISNUMBER(SEARCH("F",_xlpm.clean)),"F",""))),IF(OR(LEN(TRIM(_xlpm.inp))=0,_xlpm.nStd=""),"",_xlpm.nStd)) | F27: 102 | G27: C | H27: Amazon Athena 可用于在 S3 中查询 JSON.
A28: 解析 | B28: =_xlfn.LET(_xlpm.inp,$B$25,_xlpm.p,$H$17,IF(OR(LEN(TRIM(_xlpm.inp))=0,LEN(TRIM(_xlpm.p))=0,_xlpm.p=0),"",_xlpm.p)) | F28: 102 | G28: C | H28: Amazon Athena 可用于在 S3 中查询 JSON.
F29: 102 | G29: C | H29: Amazon Athena 可用于在 S3 中查询 JSON.
A30: 题目 103： | B30: Q103 一家公司使用 AWS Organizations 来管理不同部内的多个 AWS 账户.管理账户有一个包含项目报告的 Amazon S3 存储桶.该公司希望将对该 S3 存储桶的访问限制为 AWS Organizations 中组织内账户的用户.哪种解决方案以最少的运营开销满足这些要求? | F30: 103 | G30: A | H30: 现在,您可以在这些策略中使用新的条件键 aws:PrincipalOrgID 来要求访问资源的所有委托人都来自组织中的账户(包括主) .https://aws.amazon.com/blogs/security/control-access-to-aws-resources-by-using-the-aws-organization-of-iam-principals/
A32: A: | B32: 将带有对组织 ID 的引用的 aws:PrincipalOrgID 全局条件键添加到 S3 存储桶策略. | F32: 103 | G32: A | H32: 现在,您可以在这些策略中使用新的条件键 aws:PrincipalOrgID 来要求访问资源的所有委托人都来自组织中的账户(包括主) .https://aws.amazon.com/blogs/security/control-access-to-aws-resources-by-using-the-aws-organization-of-iam-principals/
A33: B: | B33: 为每个部内创建一个组织单位(OU).将 aws:PrincipalOrgPaths 全局条件键添加到 S3 存储桶策略. | F33: 103 | G33: A | H33: 现在,您可以在这些策略中使用新的条件键 aws:PrincipalOrgID 来要求访问资源的所有委托人都来自组织中的账户(包括主) .https://aws.amazon.com/blogs/security/control-access-to-aws-resources-by-using-the-aws-organization-of-iam-principals/
A34: C: | B34: 使用 AWS CloudTrail 监控 CreateAccount.InviteAccountToOrganization.LeaveOrganization 和 RemoveAccountFromOrganization 事件.相应地更新 S3 存储桶策略. | F34: 103 | G34: A | H34: 现在,您可以在这些策略中使用新的条件键 aws:PrincipalOrgID 来要求访问资源的所有委托人都来自组织中的账户(包括主) .https://aws.amazon.com/blogs/security/control-access-to-aws-resources-by-using-the-aws-organization-of-iam-principals/
A35: D: | B35: 标记需要访问 S3 存储桶的每个用户.将 aws:PrincipalTag 全局条件键添加到 S3 存储桶策略. | F35: 103 | G35: A | H35: 现在,您可以在这些策略中使用新的条件键 aws:PrincipalOrgID 来要求访问资源的所有委托人都来自组织中的账户(包括主) .https://aws.amazon.com/blogs/security/control-access-to-aws-resources-by-using-the-aws-organization-of-iam-principals/
F36: 103 | G36: A | H36: 现在,您可以在这些策略中使用新的条件键 aws:PrincipalOrgID 来要求访问资源的所有委托人都来自组织中的账户(包括主) .https://aws.amazon.com/blogs/security/control-access-to-aws-resources-by-using-the-aws-organization-of-iam-principals/
F37: 103 | G37: A | H37: 现在,您可以在这些策略中使用新的条件键 aws:PrincipalOrgID 来要求访问资源的所有委托人都来自组织中的账户(包括主) .https://aws.amazon.com/blogs/security/control-access-to-aws-resources-by-using-the-aws-organization-of-iam-principals/
A38: 你的答案 | F38: 103 | G38: A | H38: 现在,您可以在这些策略中使用新的条件键 aws:PrincipalOrgID 来要求访问资源的所有委托人都来自组织中的账户(包括主) .https://aws.amazon.com/blogs/security/control-access-to-aws-resources-by-using-the-aws-organization-of-iam-principals/
A39: 结果 | B39: =_xlfn.LET(_xlpm.inp,$B$38,_xlpm.nInp,_xlfn.LET(_xlpm.raw,UPPER(TRIM($B$38)),_xlpm.clean,SUBSTITUTE(SUBSTITUTE(SUBSTITUTE(SUBSTITUTE(SUBSTITUTE(_xlpm.raw,"，",","),"、",","),"；",",")," ",""),",",""),_xlfn.TEXTJOIN(",",TRUE,IF(ISNUMBER(SEARCH("A",_xlpm.clean)),"A",""),IF(ISNUMBER(SEARCH("B",_xlpm.clean)),"B",""),IF(ISNUMBER(SEARCH("C",_xlpm.clean)),"C",""),IF(ISNUMBER(SEARCH("D",_xlpm.clean)),"D",""),IF(ISNUMBER(SEARCH("E",_xlpm.clean)),"E",""),IF(ISNUMBER(SEARCH("F",_xlpm.clean)),"F",""))),_xlpm.nStd,_xlfn.LET(_xlpm.raw,UPPER(TRIM($G$30)),_xlpm.clean,SUBSTITUTE(SUBSTITUTE(SUBSTITUTE(SUBSTITUTE(SUBSTITUTE(_xlpm.raw,"，",","),"、",","),"；",",")," ",""),",",""),_xlfn.TEXTJOIN(",",TRUE,IF(ISNUMBER(SEARCH("A",_xlpm.clean)),"A",""),IF(ISNUMBER(SEARCH("B",_xlpm.clean)),"B",""),IF(ISNUMBER(SEARCH("C",_xlpm.clean)),"C",""),IF(ISNUMBER(SEARCH("D",_xlpm.clean)),"D",""),IF(ISNUMBER(SEARCH("E",_xlpm.clean)),"E",""),IF(ISNUMBER(SEARCH("F",_xlpm.clean)),"F",""))),IF(LEN(TRIM(_xlpm.inp))=0,"",IF(AND(_xlpm.nInp<>"",_xlpm.nStd<>"",_xlpm.nInp=_xlpm.nStd),"✅正确","❌错误"))) | F39: 103 | G39: A | H39: 现在,您可以在这些策略中使用新的条件键 aws:PrincipalOrgID 来要求访问资源的所有委托人都来自组织中的账户(包括主) .https://aws.amazon.com/blogs/security/control-access-to-aws-resources-by-using-the-aws-organization-of-iam-principals/
A40: 正确答案 | B40: =_xlfn.LET(_xlpm.inp,$B$38,_xlpm.nStd,_xlfn.LET(_xlpm.raw,UPPER(TRIM($G$30)),_xlpm.clean,SUBSTITUTE(SUBSTITUTE(SUBSTITUTE(SUBSTITUTE(SUBSTITUTE(_xlpm.raw,"，",","),"、",","),"；",",")," ",""),",",""),_xlfn.TEXTJOIN(",",TRUE,IF(ISNUMBER(SEARCH("A",_xlpm.clean)),"A",""),IF(ISNUMBER(SEARCH("B",_xlpm.clean)),"B",""),IF(ISNUMBER(SEARCH("C",_xlpm.clean)),"C",""),IF(ISNUMBER(SEARCH("D",_xlpm.clean)),"D",""),IF(ISNUMBER(SEARCH("E",_xlpm.clean)),"E",""),IF(ISNUMBER(SEARCH("F",_xlpm.clean)),"F",""))),IF(OR(LEN(TRIM(_xlpm.inp))=0,_xlpm.nStd=""),"",_xlpm.nStd)) | F40: 103 | G40: A | H40: 现在,您可以在这些策略中使用新的条件键 aws:PrincipalOrgID 来要求访问资源的所有委托人都来自组织中的账户(包括主) .https://aws.amazon.com/blogs/security/control-access-to-aws-resources-by-using-the-aws-organization-of-iam-principals/
A41: 解析 | B41: =_xlfn.LET(_xlpm.inp,$B$38,_xlpm.p,$H$30,IF(OR(LEN(TRIM(_xlpm.inp))=0,LEN(TRIM(_xlpm.p))=0,_xlpm.p=0),"",_xlpm.p)) | F41: 103 | G41: A | H41: 现在,您可以在这些策略中使用新的条件键 aws:PrincipalOrgID 来要求访问资源的所有委托人都来自组织中的账户(包括主) .https://aws.amazon.com/blogs/security/control-access-to-aws-resources-by-using-the-aws-organization-of-iam-principals/
F42: 103 | G42: A | H42: 现在,您可以在这些策略中使用新的条件键 aws:PrincipalOrgID 来要求访问资源的所有委托人都来自组织中的账户(包括主) .https://aws.amazon.com/blogs/security/control-access-to-aws-resources-by-using-the-aws-organization-of-iam-principals/
A43: 题目 104： | B43: Q104 应用程序在 VPC 中的 Amazon EC2 实例上运行,应用程序处理存储在 Amazon S3 存储桶中的日志.EC2 实例需要访问S3 存储桶而无需连接到互联网.哪种解决方案将提供私有网络连接到亚马逊 S3? | F43: 104 | G43: A | H43: VPC 终端节点允许您使用私有网络而不是使用公共 Internet 连接到 AWS 服务
A45: A: | B45: 为 S3 存储桶创建网关 VPC 终端节点. | F45: 104 | G45: A | H45: VPC 终端节点允许您使用私有网络而不是使用公共 Internet 连接到 AWS 服务
A46: B: | B46: 将日志流式传输到 Amazon CloudWatch Logs.将日志导出到 S3 存储桶. | F46: 104 | G46: A | H46: VPC 终端节点允许您使用私有网络而不是使用公共 Internet 连接到 AWS 服务
A47: C: | B47: 在 Amazon EC2 上创建实例配置文件以允许S3 访问. | F47: 104 | G47: A | H47: VPC 终端节点允许您使用私有网络而不是使用公共 Internet 连接到 AWS 服务
A48: D: | B48: 使用私有链接创建 Amazon API Gateway API 以访问 S3 终端节点 | F48: 104 | G48: A | H48: VPC 终端节点允许您使用私有网络而不是使用公共 Internet 连接到 AWS 服务
F49: 104 | G49: A | H49: VPC 终端节点允许您使用私有网络而不是使用公共 Internet 连接到 AWS 服务
F50: 104 | G50: A | H50: VPC 终端节点允许您使用私有网络而不是使用公共 Internet 连接到 AWS 服务
A51: 你的答案 | F51: 104 | G51: A | H51: VPC 终端节点允许您使用私有网络而不是使用公共 Internet 连接到 AWS 服务
A52: 结果 | B52: =_xlfn.LET(_xlpm.inp,$B$51,_xlpm.nInp,_xlfn.LET(_xlpm.raw,UPPER(TRIM($B$51)),_xlpm.clean,SUBSTITUTE(SUBSTITUTE(SUBSTITUTE(SUBSTITUTE(SUBSTITUTE(_xlpm.raw,"，",","),"、",","),"；",",")," ",""),",",""),_xlfn.TEXTJOIN(",",TRUE,IF(ISNUMBER(SEARCH("A",_xlpm.clean)),"A",""),IF(ISNUMBER(SEARCH("B",_xlpm.clean)),"B",""),IF(ISNUMBER(SEARCH("C",_xlpm.clean)),"C",""),IF(ISNUMBER(SEARCH("D",_xlpm.clean)),"D",""),IF(ISNUMBER(SEARCH("E",_xlpm.clean)),"E",""),IF(ISNUMBER(SEARCH("F",_xlpm.clean)),"F",""))),_xlpm.nStd,_xlfn.LET(_xlpm.raw,UPPER(TRIM($G$43)),_xlpm.clean,SUBSTITUTE(SUBSTITUTE(SUBSTITUTE(SUBSTITUTE(SUBSTITUTE(_xlpm.raw,"，",","),"、",","),"；",",")," ",""),",",""),_xlfn.TEXTJOIN(",",TRUE,IF(ISNUMBER(SEARCH("A",_xlpm.clean)),"A",""),IF(ISNUMBER(SEARCH("B",_xlpm.clean)),"B",""),IF(ISNUMBER(SEARCH("C",_xlpm.clean)),"C",""),IF(ISNUMBER(SEARCH("D",_xlpm.clean)),"D",""),IF(ISNUMBER(SEARCH("E",_xlpm.clean)),"E",""),IF(ISNUMBER(SEARCH("F",_xlpm.clean)),"F",""))),IF(LEN(TRIM(_xlpm.inp))=0,"",IF(AND(_xlpm.nInp<>"",_xlpm.nStd<>"",_xlpm.nInp=_xlpm.nStd),"✅正确","❌错误"))) | F52: 104 | G52: A | H52: VPC 终端节点允许您使用私有网络而不是使用公共 Internet 连接到 AWS 服务
A53: 正确答案 | B53: =_xlfn.LET(_xlpm.inp,$B$51,_xlpm.nStd,_xlfn.LET(_xlpm.raw,UPPER(TRIM($G$43)),_xlpm.clean,SUBSTITUTE(SUBSTITUTE(SUBSTITUTE(SUBSTITUTE(SUBSTITUTE(_xlpm.raw,"，",","),"、",","),"；",",")," ",""),",",""),_xlfn.TEXTJOIN(",",TRUE,IF(ISNUMBER(SEARCH("A",_xlpm.clean)),"A",""),IF(ISNUMBER(SEARCH("B",_xlpm.clean)),"B",""),IF(ISNUMBER(SEARCH("C",_xlpm.clean)),"C",""),IF(ISNUMBER(SEARCH("D",_xlpm.clean)),"D",""),IF(ISNUMBER(SEARCH("E",_xlpm.clean)),"E",""),IF(ISNUMBER(SEARCH("F",_xlpm.clean)),"F",""))),IF(OR(LEN(TRIM(_xlpm.inp))=0,_xlpm.nStd=""),"",_xlpm.nStd)) | F53: 104 | G53: A | H53: VPC 终端节点允许您使用私有网络而不是使用公共 Internet 连接到 AWS 服务
A54: 解析 | B54: =_xlfn.LET(_xlpm.inp,$B$51,_xlpm.p,$H$43,IF(OR(LEN(TRIM(_xlpm.inp))=0,LEN(TRIM(_xlpm.p))=0,_xlpm.p=0),"",_xlpm.p)) | F54: 104 | G54: A | H54: VPC 终端节点允许您使用私有网络而不是使用公共 Internet 连接到 AWS 服务
F55: 104 | G55: A | H55: VPC 终端节点允许您使用私有网络而不是使用公共 Internet 连接到 AWS 服务
A56: 题目 105： | B56: Q105 一家公司在 AWS 上使用单个 Amazon EC2 实例托管 Web 应用程序,该实例将用户上传的文档存储在 Amazon EBS 卷中.为了更好的可扩展性和可用性,该公司复制了该架构并创建了第二个EC2 实例和 EBS 卷另一个可用区将两者放在应用程序负载均衡器之后.完成此更改后,用户报告说,每次他们刷新网站时,他们可以看到他们的文档的一个子集或另一个,但不能同时看到所有文档.解决方案架构师应该提出什么建议来确保用户一次看到他们的所有文档? | F56: 105 | G56: C | H56: 自适应吞吐量 -EFS 的性能可以与其存储同步扩展,在突发的大容量文件转储时以更高的吞吐量运行,达到 500,000 IOPS 或每秒 10 GB. 完全有弹性 - 一旦您启动了EFS 实例,您就可以添加添加文件,而无需担心配置或干扰应用程序的性能. 额外的可访问性 EFS 可以从不同的EC2 实例挂载,但它也可以通过使用 VPC 对等连接跨越 AWS 区域边界.
A58: A: | B58: 复制数据,使两个 EBS 卷都包含所有文档. | F58: 105 | G58: C | H58: 自适应吞吐量 -EFS 的性能可以与其存储同步扩展,在突发的大容量文件转储时以更高的吞吐量运行,达到 500,000 IOPS 或每秒 10 GB. 完全有弹性 - 一旦您启动了EFS 实例,您就可以添加添加文件,而无需担心配置或干扰应用程序的性能. 额外的可访问性 EFS 可以从不同的EC2 实例挂载,但它也可以通过使用 VPC 对等连接跨越 AWS 区域边界.
A59: B: | B59: 配置应用程序负载均衡器以将用户引导到带有文档的服务器 | F59: 105 | G59: C | H59: 自适应吞吐量 -EFS 的性能可以与其存储同步扩展,在突发的大容量文件转储时以更高的吞吐量运行,达到 500,000 IOPS 或每秒 10 GB. 完全有弹性 - 一旦您启动了EFS 实例,您就可以添加添加文件,而无需担心配置或干扰应用程序的性能. 额外的可访问性 EFS 可以从不同的EC2 实例挂载,但它也可以通过使用 VPC 对等连接跨越 AWS 区域边界.
A60: C: | B60: 将数据从两个 EBS 卷复制到 Amazon EFS.修改应用程序以将新文档保存到 Amazon EFS | F60: 105 | G60: C | H60: 自适应吞吐量 -EFS 的性能可以与其存储同步扩展,在突发的大容量文件转储时以更高的吞吐量运行,达到 500,000 IOPS 或每秒 10 GB. 完全有弹性 - 一旦您启动了EFS 实例,您就可以添加添加文件,而无需担心配置或干扰应用程序的性能. 额外的可访问性 EFS 可以从不同的EC2 实例挂载,但它也可以通过使用 VPC 对等连接跨越 AWS 区域边界.
A61: D: | B61: 配置 Application Load Balancer 以将请求发送到两个服务器.从正确的服务器返回每个文档. | F61: 105 | G61: C | H61: 自适应吞吐量 -EFS 的性能可以与其存储同步扩展,在突发的大容量文件转储时以更高的吞吐量运行,达到 500,000 IOPS 或每秒 10 GB. 完全有弹性 - 一旦您启动了EFS 实例,您就可以添加添加文件,而无需担心配置或干扰应用程序的性能. 额外的可访问性 EFS 可以从不同的EC2 实例挂载,但它也可以通过使用 VPC 对等连接跨越 AWS 区域边界.
F62: 105 | G62: C | H62: 自适应吞吐量 -EFS 的性能可以与其存储同步扩展,在突发的大容量文件转储时以更高的吞吐量运行,达到 500,000 IOPS 或每秒 10 GB. 完全有弹性 - 一旦您启动了EFS 实例,您就可以添加添加文件,而无需担心配置或干扰应用程序的性能. 额外的可访问性 EFS 可以从不同的EC2 实例挂载,但它也可以通过使用 VPC 对等连接跨越 AWS 区域边界.
F63: 105 | G63: C | H63: 自适应吞吐量 -EFS 的性能可以与其存储同步扩展,在突发的大容量文件转储时以更高的吞吐量运行,达到 500,000 IOPS 或每秒 10 GB. 完全有弹性 - 一旦您启动了EFS 实例,您就可以添加添加文件,而无需担心配置或干扰应用程序的性能. 额外的可访问性 EFS 可以从不同的EC2 实例挂载,但它也可以通过使用 VPC 对等连接跨越 AWS 区域边界.
A64: 你的答案 | F64: 105 | G64: C | H64: 自适应吞吐量 -EFS 的性能可以与其存储同步扩展,在突发的大容量文件转储时以更高的吞吐量运行,达到 500,000 IOPS 或每秒 10 GB. 完全有弹性 - 一旦您启动了EFS 实例,您就可以添加添加文件,而无需担心配置或干扰应用程序的性能. 额外的可访问性 EFS 可以从不同的EC2 实例挂载,但它也可以通过使用 VPC 对等连接跨越 AWS 区域边界.
A65: 结果 | B65: =_xlfn.LET(_xlpm.inp,$B$64,_xlpm.nInp,_xlfn.LET(_xlpm.raw,UPPER(TRIM($B$64)),_xlpm.clean,SUBSTITUTE(SUBSTITUTE(SUBSTITUTE(SUBSTITUTE(SUBSTITUTE(_xlpm.raw,"，",","),"、",","),"；",",")," ",""),",",""),_xlfn.TEXTJOIN(",",TRUE,IF(ISNUMBER(SEARCH("A",_xlpm.clean)),"A",""),IF(ISNUMBER(SEARCH("B",_xlpm.clean)),"B",""),IF(ISNUMBER(SEARCH("C",_xlpm.clean)),"C",""),IF(ISNUMBER(SEARCH("D",_xlpm.clean)),"D",""),IF(ISNUMBER(SEARCH("E",_xlpm.clean)),"E",""),IF(ISNUMBER(SEARCH("F",_xlpm.clean)),"F",""))),_xlpm.nStd,_xlfn.LET(_xlpm.raw,UPPER(TRIM($G$56)),_xlpm.clean,SUBSTITUTE(SUBSTITUTE(SUBSTITUTE(SUBSTITUTE(SUBSTITUTE(_xlpm.raw,"，",","),"、",","),"；",",")," ",""),",",""),_xlfn.TEXTJOIN(",",TRUE,IF(ISNUMBER(SEARCH("A",_xlpm.clean)),"A",""),IF(ISNUMBER(SEARCH("B",_xlpm.clean)),"B",""),IF(ISNUMBER(SEARCH("C",_xlpm.clean)),"C",""),IF(ISNUMBER(SEARCH("D",_xlpm.clean)),"D",""),IF(ISNUMBER(SEARCH("E",_xlpm.clean)),"E",""),IF(ISNUMBER(SEARCH("F",_xlpm.clean)),"F",""))),IF(LEN(TRIM(_xlpm.inp))=0,"",IF(AND(_xlpm.nInp<>"",_xlpm.nStd<>"",_xlpm.nInp=_xlpm.nStd),"✅正确","❌错误"))) | F65: 105 | G65: C | H65: 自适应吞吐量 -EFS 的性能可以与其存储同步扩展,在突发的大容量文件转储时以更高的吞吐量运行,达到 500,000 IOPS 或每秒 10 GB. 完全有弹性 - 一旦您启动了EFS 实例,您就可以添加添加文件,而无需担心配置或干扰应用程序的性能. 额外的可访问性 EFS 可以从不同的EC2 实例挂载,但它也可以通过使用 VPC 对等连接跨越 AWS 区域边界.
A66: 正确答案 | B66: =_xlfn.LET(_xlpm.inp,$B$64,_xlpm.nStd,_xlfn.LET(_xlpm.raw,UPPER(TRIM($G$56)),_xlpm.clean,SUBSTITUTE(SUBSTITUTE(SUBSTITUTE(SUBSTITUTE(SUBSTITUTE(_xlpm.raw,"，",","),"、",","),"；",",")," ",""),",",""),_xlfn.TEXTJOIN(",",TRUE,IF(ISNUMBER(SEARCH("A",_xlpm.clean)),"A",""),IF(ISNUMBER(SEARCH("B",_xlpm.clean)),"B",""),IF(ISNUMBER(SEARCH("C",_xlpm.clean)),"C",""),IF(ISNUMBER(SEARCH("D",_xlpm.clean)),"D",""),IF(ISNUMBER(SEARCH("E",_xlpm.clean)),"E",""),IF(ISNUMBER(SEARCH("F",_xlpm.clean)),"F",""))),IF(OR(LEN(TRIM(_xlpm.inp))=0,_xlpm.nStd=""),"",_xlpm.nStd)) | F66: 105 | G66: C | H66: 自适应吞吐量 -EFS 的性能可以与其存储同步扩展,在突发的大容量文件转储时以更高的吞吐量运行,达到 500,000 IOPS 或每秒 10 GB. 完全有弹性 - 一旦您启动了EFS 实例,您就可以添加添加文件,而无需担心配置或干扰应用程序的性能. 额外的可访问性 EFS 可以从不同的EC2 实例挂载,但它也可以通过使用 VPC 对等连接跨越 AWS 区域边界.
A67: 解析 | B67: =_xlfn.LET(_xlpm.inp,$B$64,_xlpm.p,$H$56,IF(OR(LEN(TRIM(_xlpm.inp))=0,LEN(TRIM(_xlpm.p))=0,_xlpm.p=0),"",_xlpm.p)) | F67: 105 | G67: C | H67: 自适应吞吐量 -EFS 的性能可以与其存储同步扩展,在突发的大容量文件转储时以更高的吞吐量运行,达到 500,000 IOPS 或每秒 10 GB. 完全有弹性 - 一旦您启动了EFS 实例,您就可以添加添加文件,而无需担心配置或干扰应用程序的性能. 额外的可访问性 EFS 可以从不同的EC2 实例挂载,但它也可以通过使用 VPC 对等连接跨越 AWS 区域边界.
F68: 105 | G68: C | H68: 自适应吞吐量 -EFS 的性能可以与其存储同步扩展,在突发的大容量文件转储时以更高的吞吐量运行,达到 500,000 IOPS 或每秒 10 GB. 完全有弹性 - 一旦您启动了EFS 实例,您就可以添加添加文件,而无需担心配置或干扰应用程序的性能. 额外的可访问性 EFS 可以从不同的EC2 实例挂载,但它也可以通过使用 VPC 对等连接跨越 AWS 区域边界.
A69: 题目 106： | B69: Q106 某公司使用 NFS 将大型视频文件存储在本地网络附加存储中,每个视频文件的大小范围从1MB 到 500 GB.总存储为 70 TB,并且不再增长.公司决定迁移视频文件到 Amazon S3.公司必须尽快迁移视频文件,同时使用尽可能少的网络带宽.哪种解决方案可以满足这些要求? | F69: 106 | G69: B | H69: B. On a Snowball Edge device you can copy files with a speed of up to 100Gbps. 70TB will take around 5600 seconds, so very quickly, less than 2 hours. The downside is that it'll take between 4-6 working days to receive the device and then another 2-3 working days to send it back and for AWS to move the data onto S3 once it reaches them. Total time: 6-9 working days. Bandwidth used: 0.
A71: A: | B71: 创建 S3 存储桶.创建有权写入 S3 存储桶的 IAM 角色.使用 AWS CLI 将所有文件本地复制到 S3 存储桶. | F71: 106 | G71: B | H71: B. On a Snowball Edge device you can copy files with a speed of up to 100Gbps. 70TB will take around 5600 seconds, so very quickly, less than 2 hours. The downside is that it'll take between 4-6 working days to receive the device and then another 2-3 working days to send it back and for AWS to move the data onto S3 once it reaches them. Total time: 6-9 working days. Bandwidth used: 0.
A72: B: | B72: 创建 AWS Snowball Edge 作业.在本地接收 Snowball Edge 设备.使用 Snowball Edge 客户端将数据传输到设备.返回设备,以便AWS 可以将数据导入 Amazon S3. | F72: 106 | G72: B | H72: B. On a Snowball Edge device you can copy files with a speed of up to 100Gbps. 70TB will take around 5600 seconds, so very quickly, less than 2 hours. The downside is that it'll take between 4-6 working days to receive the device and then another 2-3 working days to send it back and for AWS to move the data onto S3 once it reaches them. Total time: 6-9 working days. Bandwidth used: 0.
A73: C: | B73: 文件网关使用互联网,因此最高速度最高为 1Gbps,因此最少需要6.5天,您使用 70TB 的互联网带宽. | F73: 106 | G73: B | H73: B. On a Snowball Edge device you can copy files with a speed of up to 100Gbps. 70TB will take around 5600 seconds, so very quickly, less than 2 hours. The downside is that it'll take between 4-6 working days to receive the device and then another 2-3 working days to send it back and for AWS to move the data onto S3 once it reaches them. Total time: 6-9 working days. Bandwidth used: 0.
A74: D: | B74: 您可以通过 Direct Connect 实现高达 10Gbps 的速度.总时间 15.5 小时,您将使用70TB 的带宽.然而,有趣的是,这个问题并没有具体说明什么类型的带宽?Direct Connect 不使用您的 Internet 带宽,因为您将在本地和 AWS 云之间拥有专用的点对点连接,因此从技术上讲,您没有使用“公共”带宽. 要求有点含糊,但我认为B是最合适的答案,尽管如果带宽使用严格指您的公共连接,D也可能是正确的. | F74: 106 | G74: B | H74: B. On a Snowball Edge device you can copy files with a speed of up to 100Gbps. 70TB will take around 5600 seconds, so very quickly, less than 2 hours. The downside is that it'll take between 4-6 working days to receive the device and then another 2-3 working days to send it back and for AWS to move the data onto S3 once it reaches them. Total time: 6-9 working days. Bandwidth used: 0.
F75: 106 | G75: B | H75: B. On a Snowball Edge device you can copy files with a speed of up to 100Gbps. 70TB will take around 5600 seconds, so very quickly, less than 2 hours. The downside is that it'll take between 4-6 working days to receive the device and then another 2-3 working days to send it back and for AWS to move the data onto S3 once it reaches them. Total time: 6-9 working days. Bandwidth used: 0.
F76: 106 | G76: B | H76: B. On a Snowball Edge device you can copy files with a speed of up to 100Gbps. 70TB will take around 5600 seconds, so very quickly, less than 2 hours. The downside is that it'll take between 4-6 working days to receive the device and then another 2-3 working days to send it back and for AWS to move the data onto S3 once it reaches them. Total time: 6-9 working days. Bandwidth used: 0.
A77: 你的答案 | F77: 106 | G77: B | H77: B. On a Snowball Edge device you can copy files with a speed of up to 100Gbps. 70TB will take around 5600 seconds, so very quickly, less than 2 hours. The downside is that it'll take between 4-6 working days to receive the device and then another 2-3 working days to send it back and for AWS to move the data onto S3 once it reaches them. Total time: 6-9 working days. Bandwidth used: 0.
A78: 结果 | B78: =_xlfn.LET(_xlpm.inp,$B$77,_xlpm.nInp,_xlfn.LET(_xlpm.raw,UPPER(TRIM($B$77)),_xlpm.clean,SUBSTITUTE(SUBSTITUTE(SUBSTITUTE(SUBSTITUTE(SUBSTITUTE(_xlpm.raw,"，",","),"、",","),"；",",")," ",""),",",""),_xlfn.TEXTJOIN(",",TRUE,IF(ISNUMBER(SEARCH("A",_xlpm.clean)),"A",""),IF(ISNUMBER(SEARCH("B",_xlpm.clean)),"B",""),IF(ISNUMBER(SEARCH("C",_xlpm.clean)),"C",""),IF(ISNUMBER(SEARCH("D",_xlpm.clean)),"D",""),IF(ISNUMBER(SEARCH("E",_xlpm.clean)),"E",""),IF(ISNUMBER(SEARCH("F",_xlpm.clean)),"F",""))),_xlpm.nStd,_xlfn.LET(_xlpm.raw,UPPER(TRIM($G$69)),_xlpm.clean,SUBSTITUTE(SUBSTITUTE(SUBSTITUTE(SUBSTITUTE(SUBSTITUTE(_xlpm.raw,"，",","),"、",","),"；",",")," ",""),",",""),_xlfn.TEXTJOIN(",",TRUE,IF(ISNUMBER(SEARCH("A",_xlpm.clean)),"A",""),IF(ISNUMBER(SEARCH("B",_xlpm.clean)),"B",""),IF(ISNUMBER(SEARCH("C",_xlpm.clean)),"C",""),IF(ISNUMBER(SEARCH("D",_xlpm.clean)),"D",""),IF(ISNUMBER(SEARCH("E",_xlpm.clean)),"E",""),IF(ISNUMBER(SEARCH("F",_xlpm.clean)),"F",""))),IF(LEN(TRIM(_xlpm.inp))=0,"",IF(AND(_xlpm.nInp<>"",_xlpm.nStd<>"",_xlpm.nInp=_xlpm.nStd),"✅正确","❌错误"))) | F78: 106 | G78: B | H78: B. On a Snowball Edge device you can copy files with a speed of up to 100Gbps. 70TB will take around 5600 seconds, so very quickly, less than 2 hours. The downside is that it'll take between 4-6 working days to receive the device and then another 2-3 working days to send it back and for AWS to move the data onto S3 once it reaches them. Total time: 6-9 working days. Bandwidth used: 0.
A79: 正确答案 | B79: =_xlfn.LET(_xlpm.inp,$B$77,_xlpm.nStd,_xlfn.LET(_xlpm.raw,UPPER(TRIM($G$69)),_xlpm.clean,SUBSTITUTE(SUBSTITUTE(SUBSTITUTE(SUBSTITUTE(SUBSTITUTE(_xlpm.raw,"，",","),"、",","),"；",",")," ",""),",",""),_xlfn.TEXTJOIN(",",TRUE,IF(ISNUMBER(SEARCH("A",_xlpm.clean)),"A",""),IF(ISNUMBER(SEARCH("B",_xlpm.clean)),"B",""),IF(ISNUMBER(SEARCH("C",_xlpm.clean)),"C",""),IF(ISNUMBER(SEARCH("D",_xlpm.clean)),"D",""),IF(ISNUMBER(SEARCH("E",_xlpm.clean)),"E",""),IF(ISNUMBER(SEARCH("F",_xlpm.clean)),"F",""))),IF(OR(LEN(TRIM(_xlpm.inp))=0,_xlpm.nStd=""),"",_xlpm.nStd)) | F79: 106 | G79: B | H79: B. On a Snowball Edge device you can copy files with a speed of up to 100Gbps. 70TB will take around 5600 seconds, so very quickly, less than 2 hours. The downside is that it'll take between 4-6 working days to receive the device and then another 2-3 working days to send it back and for AWS to move the data onto S3 once it reaches them. Total time: 6-9 working days. Bandwidth used: 0.
A80: 解析 | B80: =_xlfn.LET(_xlpm.inp,$B$77,_xlpm.p,$H$69,IF(OR(LEN(TRIM(_xlpm.inp))=0,LEN(TRIM(_xlpm.p))=0,_xlpm.p=0),"",_xlpm.p)) | F80: 106 | G80: B | H80: B. On a Snowball Edge device you can copy files with a speed of up to 100Gbps. 70TB will take around 5600 seconds, so very quickly, less than 2 hours. The downside is that it'll take between 4-6 working days to receive the device and then another 2-3 working days to send it back and for AWS to move the data onto S3 once it reaches them. Total time: 6-9 working days. Bandwidth used: 0.
F81: 106 | G81: B | H81: B. On a Snowball Edge device you can copy files with a speed of up to 100Gbps. 70TB will take around 5600 seconds, so very quickly, less than 2 hours. The downside is that it'll take between 4-6 working days to receive the device and then another 2-3 working days to send it back and for AWS to move the data onto S3 once it reaches them. Total time: 6-9 working days. Bandwidth used: 0.
A82: 题目 107： | B82: Q107 一家公司有一个应用程序接收传入的消息.这些消息随后被许多其他应用程序和微服务快速消耗.消息的数量变化很大,有时每秒高达100,000条.公司希望解耦解决方案和增加可扩展性.哪种解决方案满足这些要求? | F82: 107 | G82: D | H82: SNS 标准主题最大吞吐量:标准主题支持每秒几乎无限数量的消息. https://aws.amazon.com/sns/features/ SQS 标准队列无限吞吐量:标准队列支持几乎无限每个 API 操作的每秒事务数(TPS). https://aws.amazon.com/sqs/features/
A84: A: | B84: 将消息保存到 Amazon Kinesis Data Analytics.所有应用程序都将读取和处理消息. | F84: 107 | G84: D | H84: SNS 标准主题最大吞吐量:标准主题支持每秒几乎无限数量的消息. https://aws.amazon.com/sns/features/ SQS 标准队列无限吞吐量:标准队列支持几乎无限每个 API 操作的每秒事务数(TPS). https://aws.amazon.com/sqs/features/
A85: B: | B85: 在 Auto Scaling 组中的 Amazon EC2 实例上部署应用程序,该组根据 CPU 指标扩展 EC2 实例的数量. | F85: 107 | G85: D | H85: SNS 标准主题最大吞吐量:标准主题支持每秒几乎无限数量的消息. https://aws.amazon.com/sns/features/ SQS 标准队列无限吞吐量:标准队列支持几乎无限每个 API 操作的每秒事务数(TPS). https://aws.amazon.com/sqs/features/
A86: C: | B86: 使用单个分片将消息写入 Amazon Kinesis Data Streams.所有应用程序将从流中读取并处理消息. | F86: 107 | G86: D | H86: SNS 标准主题最大吞吐量:标准主题支持每秒几乎无限数量的消息. https://aws.amazon.com/sns/features/ SQS 标准队列无限吞吐量:标准队列支持几乎无限每个 API 操作的每秒事务数(TPS). https://aws.amazon.com/sqs/features/
A87: D: | B87: 使用一个或多个 Amazon Simple Queue Service (Amazon SQS)订阅将消息发布到 Amazon Simple Notification Service (Amazon SNS)主题.然后所有应用程序处理来自队列的消息. | F87: 107 | G87: D | H87: SNS 标准主题最大吞吐量:标准主题支持每秒几乎无限数量的消息. https://aws.amazon.com/sns/features/ SQS 标准队列无限吞吐量:标准队列支持几乎无限每个 API 操作的每秒事务数(TPS). https://aws.amazon.com/sqs/features/
F88: 107 | G88: D | H88: SNS 标准主题最大吞吐量:标准主题支持每秒几乎无限数量的消息. https://aws.amazon.com/sns/features/ SQS 标准队列无限吞吐量:标准队列支持几乎无限每个 API 操作的每秒事务数(TPS). https://aws.amazon.com/sqs/features/
F89: 107 | G89: D | H89: SNS 标准主题最大吞吐量:标准主题支持每秒几乎无限数量的消息. https://aws.amazon.com/sns/features/ SQS 标准队列无限吞吐量:标准队列支持几乎无限每个 API 操作的每秒事务数(TPS). https://aws.amazon.com/sqs/features/
A90: 你的答案 | F90: 107 | G90: D | H90: SNS 标准主题最大吞吐量:标准主题支持每秒几乎无限数量的消息. https://aws.amazon.com/sns/features/ SQS 标准队列无限吞吐量:标准队列支持几乎无限每个 API 操作的每秒事务数(TPS). https://aws.amazon.com/sqs/features/
A91: 结果 | B91: =_xlfn.LET(_xlpm.inp,$B$90,_xlpm.nInp,_xlfn.LET(_xlpm.raw,UPPER(TRIM($B$90)),_xlpm.clean,SUBSTITUTE(SUBSTITUTE(SUBSTITUTE(SUBSTITUTE(SUBSTITUTE(_xlpm.raw,"，",","),"、",","),"；",",")," ",""),",",""),_xlfn.TEXTJOIN(",",TRUE,IF(ISNUMBER(SEARCH("A",_xlpm.clean)),"A",""),IF(ISNUMBER(SEARCH("B",_xlpm.clean)),"B",""),IF(ISNUMBER(SEARCH("C",_xlpm.clean)),"C",""),IF(ISNUMBER(SEARCH("D",_xlpm.clean)),"D",""),IF(ISNUMBER(SEARCH("E",_xlpm.clean)),"E",""),IF(ISNUMBER(SEARCH("F",_xlpm.clean)),"F",""))),_xlpm.nStd,_xlfn.LET(_xlpm.raw,UPPER(TRIM($G$82)),_xlpm.clean,SUBSTITUTE(SUBSTITUTE(SUBSTITUTE(SUBSTITUTE(SUBSTITUTE(_xlpm.raw,"，",","),"、",","),"；",",")," ",""),",",""),_xlfn.TEXTJOIN(",",TRUE,IF(ISNUMBER(SEARCH("A",_xlpm.clean)),"A",""),IF(ISNUMBER(SEARCH("B",_xlpm.clean)),"B",""),IF(ISNUMBER(SEARCH("C",_xlpm.clean)),"C",""),IF(ISNUMBER(SEARCH("D",_xlpm.clean)),"D",""),IF(ISNUMBER(SEARCH("E",_xlpm.clean)),"E",""),IF(ISNUMBER(SEARCH("F",_xlpm.clean)),"F",""))),IF(LEN(TRIM(_xlpm.inp))=0,"",IF(AND(_xlpm.nInp<>"",_xlpm.nStd<>"",_xlpm.nInp=_xlpm.nStd),"✅正确","❌错误"))) | F91: 107 | G91: D | H91: SNS 标准主题最大吞吐量:标准主题支持每秒几乎无限数量的消息. https://aws.amazon.com/sns/features/ SQS 标准队列无限吞吐量:标准队列支持几乎无限每个 API 操作的每秒事务数(TPS). https://aws.amazon.com/sqs/features/
A92: 正确答案 | B92: =_xlfn.LET(_xlpm.inp,$B$90,_xlpm.nStd,_xlfn.LET(_xlpm.raw,UPPER(TRIM($G$82)),_xlpm.clean,SUBSTITUTE(SUBSTITUTE(SUBSTITUTE(SUBSTITUTE(SUBSTITUTE(_xlpm.raw,"，",","),"、",","),"；",",")," ",""),",",""),_xlfn.TEXTJOIN(",",TRUE,IF(ISNUMBER(SEARCH("A",_xlpm.clean)),"A",""),IF(ISNUMBER(SEARCH("B",_xlpm.clean)),"B",""),IF(ISNUMBER(SEARCH("C",_xlpm.clean)),"C",""),IF(ISNUMBER(SEARCH("D",_xlpm.clean)),"D",""),IF(ISNUMBER(SEARCH("E",_xlpm.clean)),"E",""),IF(ISNUMBER(SEARCH("F",_xlpm.clean)),"F",""))),IF(OR(LEN(TRIM(_xlpm.inp))=0,_xlpm.nStd=""),"",_xlpm.nStd)) | F92: 107 | G92: D | H92: SNS 标准主题最大吞吐量:标准主题支持每秒几乎无限数量的消息. https://aws.amazon.com/sns/features/ SQS 标准队列无限吞吐量:标准队列支持几乎无限每个 API 操作的每秒事务数(TPS). https://aws.amazon.com/sqs/features/
A93: 解析 | B93: =_xlfn.LET(_xlpm.inp,$B$90,_xlpm.p,$H$82,IF(OR(LEN(TRIM(_xlpm.inp))=0,LEN(TRIM(_xlpm.p))=0,_xlpm.p=0),"",_xlpm.p)) | F93: 107 | G93: D | H93: SNS 标准主题最大吞吐量:标准主题支持每秒几乎无限数量的消息. https://aws.amazon.com/sns/features/ SQS 标准队列无限吞吐量:标准队列支持几乎无限每个 API 操作的每秒事务数(TPS). https://aws.amazon.com/sqs/features/
F94: 107 | G94: D | H94: SNS 标准主题最大吞吐量:标准主题支持每秒几乎无限数量的消息. https://aws.amazon.com/sns/features/ SQS 标准队列无限吞吐量:标准队列支持几乎无限每个 API 操作的每秒事务数(TPS). https://aws.amazon.com/sqs/features/
A95: 题目 108： | B95: Q108 一家公司正在将分布式应用程序迁移到 AWS 该应用程序服务于可变工作负载.旧平台由一个主服务器试用版组成,可协调跨多个计算节点的作业.该公司希望通过最大限度地提高弹性和可扩展性的解决方案对应用程序进行现代化改造.如何解决方案架构师应该设计架构以满足这些要求吗? | F95: 108 | G95: B | H95: A:安排自动缩放没有意义;C:完全不确定 CloudTrail 在这种情况下会有什么帮助. D:EventBridge 并没有真正用于这个目的,不会很可靠
A97: A: | B97: 将 Amazon Simple Queue Service (Amazon SQS) 队列配置为作业的目标.使用 Auto Scaling 组中管理的 Amazon EC2 实例实施计算节点.配置 EC2 Auto Scaling 以使用计划扩展. | F97: 108 | G97: B | H97: A:安排自动缩放没有意义;C:完全不确定 CloudTrail 在这种情况下会有什么帮助. D:EventBridge 并没有真正用于这个目的,不会很可靠
A98: B: | B98: 将 Amazon Simple Queue Service (Amazon SQS) 队列配置为作业的目标.使用在 Auto Scaling 组中管理的 Amazon EC2 实例实施计算节点.根据队列的大小配置 EC2 Auto Scaling. | F98: 108 | G98: B | H98: A:安排自动缩放没有意义;C:完全不确定 CloudTrail 在这种情况下会有什么帮助. D:EventBridge 并没有真正用于这个目的,不会很可靠
A99: C: | B99: 使用在 Auto Scaling 组中管理的 Amazon EC2 实例实施主服务器和计算节点.将 AWS CloudTrail 配置为 fobs 的目标.根据主服务器上的负载配置 EC2 Auto Scaling. | F99: 108 | G99: B | H99: A:安排自动缩放没有意义;C:完全不确定 CloudTrail 在这种情况下会有什么帮助. D:EventBridge 并没有真正用于这个目的,不会很可靠
A100: D: | B100: 使用在 Auto Scaling 组中管理的 Amazon EC2 实例实现主服务器和计算节点.将 Amazon EventBridge (Amazon CloudWatch Events)配置为作业的目标.根据计算节点上的负载配置 EC2 Auto Scaling . | F100: 108 | G100: B | H100: A:安排自动缩放没有意义;C:完全不确定 CloudTrail 在这种情况下会有什么帮助. D:EventBridge 并没有真正用于这个目的,不会很可靠
F101: 108 | G101: B | H101: A:安排自动缩放没有意义;C:完全不确定 CloudTrail 在这种情况下会有什么帮助. D:EventBridge 并没有真正用于这个目的,不会很可靠
F102: 108 | G102: B | H102: A:安排自动缩放没有意义;C:完全不确定 CloudTrail 在这种情况下会有什么帮助. D:EventBridge 并没有真正用于这个目的,不会很可靠
A103: 你的答案 | F103: 108 | G103: B | H103: A:安排自动缩放没有意义;C:完全不确定 CloudTrail 在这种情况下会有什么帮助. D:EventBridge 并没有真正用于这个目的,不会很可靠
A104: 结果 | B104: =_xlfn.LET(_xlpm.inp,$B$103,_xlpm.nInp,_xlfn.LET(_xlpm.raw,UPPER(TRIM($B$103)),_xlpm.clean,SUBSTITUTE(SUBSTITUTE(SUBSTITUTE(SUBSTITUTE(SUBSTITUTE(_xlpm.raw,"，",","),"、",","),"；",",")," ",""),",",""),_xlfn.TEXTJOIN(",",TRUE,IF(ISNUMBER(SEARCH("A",_xlpm.clean)),"A",""),IF(ISNUMBER(SEARCH("B",_xlpm.clean)),"B",""),IF(ISNUMBER(SEARCH("C",_xlpm.clean)),"C",""),IF(ISNUMBER(SEARCH("D",_xlpm.clean)),"D",""),IF(ISNUMBER(SEARCH("E",_xlpm.clean)),"E",""),IF(ISNUMBER(SEARCH("F",_xlpm.clean)),"F",""))),_xlpm.nStd,_xlfn.LET(_xlpm.raw,UPPER(TRIM($G$95)),_xlpm.clean,SUBSTITUTE(SUBSTITUTE(SUBSTITUTE(SUBSTITUTE(SUBSTITUTE(_xlpm.raw,"，",","),"、",","),"；",",")," ",""),",",""),_xlfn.TEXTJOIN(",",TRUE,IF(ISNUMBER(SEARCH("A",_xlpm.clean)),"A",""),IF(ISNUMBER(SEARCH("B",_xlpm.clean)),"B",""),IF(ISNUMBER(SEARCH("C",_xlpm.clean)),"C",""),IF(ISNUMBER(SEARCH("D",_xlpm.clean)),"D",""),IF(ISNUMBER(SEARCH("E",_xlpm.clean)),"E",""),IF(ISNUMBER(SEARCH("F",_xlpm.clean)),"F",""))),IF(LEN(TRIM(_xlpm.inp))=0,"",IF(AND(_xlpm.nInp<>"",_xlpm.nStd<>"",_xlpm.nInp=_xlpm.nStd),"✅正确","❌错误"))) | F104: 108 | G104: B | H104: A:安排自动缩放没有意义;C:完全不确定 CloudTrail 在这种情况下会有什么帮助. D:EventBridge 并没有真正用于这个目的,不会很可靠
A105: 正确答案 | B105: =_xlfn.LET(_xlpm.inp,$B$103,_xlpm.nStd,_xlfn.LET(_xlpm.raw,UPPER(TRIM($G$95)),_xlpm.clean,SUBSTITUTE(SUBSTITUTE(SUBSTITUTE(SUBSTITUTE(SUBSTITUTE(_xlpm.raw,"，",","),"、",","),"；",",")," ",""),",",""),_xlfn.TEXTJOIN(",",TRUE,IF(ISNUMBER(SEARCH("A",_xlpm.clean)),"A",""),IF(ISNUMBER(SEARCH("B",_xlpm.clean)),"B",""),IF(ISNUMBER(SEARCH("C",_xlpm.clean)),"C",""),IF(ISNUMBER(SEARCH("D",_xlpm.clean)),"D",""),IF(ISNUMBER(SEARCH("E",_xlpm.clean)),"E",""),IF(ISNUMBER(SEARCH("F",_xlpm.clean)),"F",""))),IF(OR(LEN(TRIM(_xlpm.inp))=0,_xlpm.nStd=""),"",_xlpm.nStd)) | F105: 108 | G105: B | H105: A:安排自动缩放没有意义;C:完全不确定 CloudTrail 在这种情况下会有什么帮助. D:EventBridge 并没有真正用于这个目的,不会很可靠
A106: 解析 | B106: =_xlfn.LET(_xlpm.inp,$B$103,_xlpm.p,$H$95,IF(OR(LEN(TRIM(_xlpm.inp))=0,LEN(TRIM(_xlpm.p))=0,_xlpm.p=0),"",_xlpm.p)) | F106: 108 | G106: B | H106: A:安排自动缩放没有意义;C:完全不确定 CloudTrail 在这种情况下会有什么帮助. D:EventBridge 并没有真正用于这个目的,不会很可靠
F107: 108 | G107: B | H107: A:安排自动缩放没有意义;C:完全不确定 CloudTrail 在这种情况下会有什么帮助. D:EventBridge 并没有真正用于这个目的,不会很可靠
A108: 题目 109： | B108: Q109 一家公司在其数据中心运行 SMB 文件服务器.文件服务器存储在文件创建后的头几天经常访问的大文件.7 天后很少访问文件.总数据大小为增加并接近公司的总存储容量.解决方案架构师必须增加公司的可用存储空间,而不会丢失对最近访问的文件的低延迟访问.解决方案架构师还必须提供文件生命周期管理以避免未来的存储问题.解决方案能满足这些要求吗? | F108: 109 | G108: B | H108: B 是答案,amazon S3 文件网关通过本地缓存提供对 Amazon S3 中数据的基于 SMB 或 NFS 的访问.然后是生命周期. D 是错误的,因为效用函数是模糊的,不需要灵活的存储.
...

Sheet 质检
A1: 题号 | B1: 当前题干（来自题库数据） | C1: 字数 | D1: 是否以？结尾 | E1: 括号是否成对 | F1: 疑似截断（需复核） | H1: 质检参数 | K1: 题号 | L1: 题块首行 | M1: 标准答案
A2: {=INDEX(题库数据!$A$5:$A$104,ROW()-1)} -> 1 | B2: {=INDEX(题库数据!$B$5:$B$104,ROW()-1)} -> 一家公司有一个托管在 AWS 上的网站该网站位于应用程序负载均衡器(ALB)的后面,该应用程序负载均衡器(ALB)配置为分别处理 HTTP 和 HTTPS.该公司希望将所有请求转发到该网站,以便这些请求将使用 HTTPS.什么解决方案架构师应该做些什么来满足这个要求? | C2: =LEN(B2) -> 134 | D2: =IF(B2="","",RIGHT(B2,1)="？") -> FALSE | E2: =IF(B2="","",(LEN(B2)-LEN(SUBSTITUTE(B2,"(","")))=(LEN(B2)-LEN(SUBSTITUTE(B2,")","")))) -> TRUE | F2: =IF(B2="","",OR(C2<$I$2,D2=FALSE,E2=FALSE)) -> TRUE | H2: 字数阈值（低于则标记） | I2: 120 | K2: 203 | L2: 30 | M2: C
A3: {=INDEX(题库数据!$A$5:$A$104,ROW()-1)} -> 2 | B3: {=INDEX(题库数据!$B$5:$B$104,ROW()-1)} -> 一家公司正在 AWS 上开发一个两层 Web 应用程序,该公司的开发人员已将该应用程序部署在直接连接到后端 Amazon RDS 数据库的 Amazon EC2 实例上.该公司不得在应用程序中硬编码数据库凭证.该公司还必须实施定期自动轮换数据库凭据的解决方案.哪种解决方案能够以最少的运营开销满足这些要求? | C3: =LEN(B3) -> 153 | D3: =IF(B3="","",RIGHT(B3,1)="？") -> FALSE | E3: =IF(B3="","",(LEN(B3)-LEN(SUBSTITUTE(B3,"(","")))=(LEN(B3)-LEN(SUBSTITUTE(B3,")","")))) -> TRUE | F3: =IF(B3="","",OR(C3<$I$2,D3=FALSE,E3=FALSE)) -> TRUE | H3: 备注 | I3: 阈值可自行调整，例如 150 更严格 | K3: 204 | L3: 43 | M3: A
A4: {=INDEX(题库数据!$A$5:$A$104,ROW()-1)} -> 3 | C4: =LEN(B4) -> 0 | D4: =IF(B4="","",RIGHT(B4,1)="？") | E4: =IF(B4="","",(LEN(B4)-LEN(SUBSTITUTE(B4,"(","")))=(LEN(B4)-LEN(SUBSTITUTE(B4,")","")))) | F4: =IF(B4="","",OR(C4<$I$2,D4=FALSE,E4=FALSE)) | K4: 206 | L4: 69 | M4: B
A5: {=INDEX(题库数据!$A$5:$A$104,ROW()-1)} -> 4 | B5: {=INDEX(题库数据!$B$5:$B$104,ROW()-1)} -> 一家公司在 AWS 上运行其基础设施,并拥有700.000 名注册用户,用于 res 文档管理应用程序,该公司打算创建一个将大型 pdf 文件转换为 jpg Imago 文件的产品 .. pdf 文件的平均大小为5 MB.公司需要存储原始文件和转换后的文件,解决方案架构师必须设计一个可扩展的解决方案,以适应随着时间的推移而迅速增长的需求.哪种解决方案最经济高效地满足这些要求? | C5: =LEN(B5) -> 189 | D5: =IF(B5="","",RIGHT(B5,1)="？") -> FALSE | E5: =IF(B5="","",(LEN(B5)-LEN(SUBSTITUTE(B5,"(","")))=(LEN(B5)-LEN(SUBSTITUTE(B5,")","")))) -> TRUE | F5: =IF(B5="","",OR(C5<$I$2,D5=FALSE,E5=FALSE)) -> TRUE | H5: 疑似截断数量 | I5: =COUNTIF(F2:F101,TRUE) -> 99 | K5: 213 | L5: 160 | M5: D
A6: {=INDEX(题库数据!$A$5:$A$104,ROW()-1)} -> 5 | B6: {=INDEX(题库数据!$B$5:$B$104,ROW()-1)} -> 一家公司在本地运行的 Windows 文件服务器上拥有超过5 TB 的文件数据用户和应用程序每天与数据进行交互该公司正在将其 Windows 工作负载转移到 AWS.随着公司继续这一过程,该公司需要访问以最小的延迟连接到AWS 和本地文件存储.公司需要一种解决方案,最大限度地减少运营开销,并且不需要对现有文件访问模式进行重大更改.公司使用 AWS Site-to-Site VPN 连接来连接到 AWS.解决方案架构师应该怎么做才能满足这些要求? | C6: =LEN(B6) -> 224 | D6: =IF(B6="","",RIGHT(B6,1)="？") -> FALSE | E6: =IF(B6="","",(LEN(B6)-LEN(SUBSTITUTE(B6,"(","")))=(LEN(B6)-LEN(SUBSTITUTE(B6,")","")))) -> TRUE | F6: =IF(B6="","",OR(C6<$I$2,D6=FALSE,E6=FALSE)) -> TRUE | K6: 218 | L6: 225 | M6: C
A7: {=INDEX(题库数据!$A$5:$A$104,ROW()-1)} -> 6 | B7: {=INDEX(题库数据!$B$5:$B$104,ROW()-1)} -> 一家医院最近使用Amazon API Gateway 和AWS Lambda 部署了一个RESTful API.该医院使用API Gateway 和Lambda 上传PDF 格式和JPEG 格式的报告.医院需要修改Lambda 代码以识别受保护的健康信息(PHI)在报告中.哪种解决方案将以最少的运营开销满足这些要求? | C7: =LEN(B7) -> 159 | D7: =IF(B7="","",RIGHT(B7,1)="？") -> FALSE | E7: =IF(B7="","",(LEN(B7)-LEN(SUBSTITUTE(B7,"(","")))=(LEN(B7)-LEN(SUBSTITUTE(B7,")","")))) -> TRUE | F7: =IF(B7="","",OR(C7<$I$2,D7=FALSE,E7=FALSE)) -> TRUE | K7: 222 | L7: 277
A8: {=INDEX(题库数据!$A$5:$A$104,ROW()-1)} -> 7 | B8: {=INDEX(题库数据!$B$5:$B$104,ROW()-1)} -> 一家公司有一个应用程序生成大量文件,每个文件大小约为5 MB.这些文件存储在 Amazon S3 中.公司政策要求文件存储 4年才能删除始终可立即访问需要,因为文件包含不易复制的关键业务数据.文件在对象创建的前30天内经常访问,但在前30天后很少访问哪种存储解决方案最具成本效益? | C8: =LEN(B8) -> 140 | D8: =IF(B8="","",RIGHT(B8,1)="？") -> FALSE | E8: =IF(B8="","",(LEN(B8)-LEN(SUBSTITUTE(B8,"(","")))=(LEN(B8)-LEN(SUBSTITUTE(B8,")","")))) -> TRUE | F8: =IF(B8="","",OR(C8<$I$2,D8=FALSE,E8=FALSE)) -> TRUE | K8: 224 | L8: 303
A9: {=INDEX(题库数据!$A$5:$A$104,ROW()-1)} -> 8 | B9: {=INDEX(题库数据!$B$5:$B$104,ROW()-1)} -> 一家公司在多个 Amazon EC2 实例上托管应用程序,应用程序处理来自 Amazon SQS 队列的消息写入 Amazon RDS 表并从队列中删除消息在 RDS 表中偶尔发现重复记录.SQS 队列没有包含任何重复的消息.解决方案架构师应该怎么做才能确保消息只被处理一次? | C9: =LEN(B9) -> 138 | D9: =IF(B9="","",RIGHT(B9,1)="？") -> FALSE | E9: =IF(B9="","",(LEN(B9)-LEN(SUBSTITUTE(B9,"(","")))=(LEN(B9)-LEN(SUBSTITUTE(B9,")","")))) -> TRUE | F9: =IF(B9="","",OR(C9<$I$2,D9=FALSE,E9=FALSE)) -> TRUE | K9: 231 | L9: 394 | M9: B
A10: {=INDEX(题库数据!$A$5:$A$104,ROW()-1)} -> 9 | B10: {=INDEX(题库数据!$B$5:$B$104,ROW()-1)} -> 一位解决方案架构师正在设计一种新的混合架构,以将公司的本地基础设施扩展到 AWS.公司需要与 AWS区域保持一致的低延迟的高可用性连接.公司需要最大限度地降低成本并愿意接受如果主连接失败,则流量会变慢.解决方案架构师应该怎么做才能满足这些要求? | C10: =LEN(B10) -> 122 | D10: =IF(B10="","",RIGHT(B10,1)="？") -> FALSE | E10: =IF(B10="","",(LEN(B10)-LEN(SUBSTITUTE(B10,"(","")))=(LEN(B10)-LEN(SUBSTITUTE(B10,")","")))) -> TRUE | F10: =IF(B10="","",OR(C10<$I$2,D10=FALSE,E10=FALSE)) -> TRUE | K10: 233 | L10: 420 | M10: B
